Workbook
Name __123Graph_A: '[1]1.6 TRS Data'!#REF!
Name __123Graph_A: '[1]1.6 TRS Data'!#REF!
Name __123Graph_A: '[1]1.6 TRS Data'!#REF!
Name __123Graph_B: '[1]1.6 TRS Data'!#REF!
Name __123Graph_B: '[1]1.6 TRS Data'!#REF!
Name __123Graph_B: '[1]1.6 TRS Data'!#REF!
Name __123Graph_LBL_A: '[1]1.6 TRS Data'!#REF!
Name __123Graph_LBL_A: '[1]1.6 TRS Data'!#REF!
Name __123Graph_LBL_A: '[1]1.6 TRS Data'!#REF!
Name __123Graph_X: '[1]1.6 TRS Data'!#REF!
Name __123Graph_X: '[1]1.6 TRS Data'!#REF!
Name __123Graph_X: '[1]1.6 TRS Data'!#REF!
Name __kpn1: [2]Главн!$D$46
Name __kpn2: [2]Главн!$E$46
Name __kpn3: [2]Главн!$F$46
Name __kpn4: [2]Главн!$G$46
Name __kpn5: [2]Главн!$H$46
Name __kpn6: [2]Главн!$I$46
Name __kpn7: [2]Главн!$J$46
Name __kpn8: [2]Главн!$K$46
Name __nds1: [2]Главн!$D$42
Name __nds2: [2]Главн!$E$42
Name __nds3: [2]Главн!$F$42
Name __nds4: [2]Главн!$G$42
Name __nds5: [2]Главн!$H$42
Name __nds6: [2]Главн!$I$42
Name _kpn1: [2]Главн!$D$46
Name _kpn1: [2]Главн!$D$46
Name _kpn1: [2]Главн!$D$46
Name _kpn1: [2]Главн!$D$46
Name _kpn2: [2]Главн!$E$46
Name _kpn2: [2]Главн!$E$46
Name _kpn2: [2]Главн!$E$46
Name _kpn2: [2]Главн!$E$46
Name _kpn3: [2]Главн!$F$46
Name _kpn3: [2]Главн!$F$46
Name _kpn3: [2]Главн!$F$46
Name _kpn3: [2]Главн!$F$46
Name _kpn4: [2]Главн!$G$46
Name _kpn4: [2]Главн!$G$46
Name _kpn4: [2]Главн!$G$46
Name _kpn4: [2]Главн!$G$46
Name _kpn5: [2]Главн!$H$46
Name _kpn5: [2]Главн!$H$46
Name _kpn5: [2]Главн!$H$46
Name _kpn5: [2]Главн!$H$46
Name _kpn6: [2]Главн!$I$46
Name _kpn6: [2]Главн!$I$46
Name _kpn6: [2]Главн!$I$46
Name _kpn6: [2]Главн!$I$46
Name _kpn7: [2]Главн!$J$46
Name _kpn7: [2]Главн!$J$46
Name _kpn7: [2]Главн!$J$46
Name _kpn7: [2]Главн!$J$46
Name _kpn8: [2]Главн!$K$46
Name _kpn8: [2]Главн!$K$46
Name _kpn8: [2]Главн!$K$46
Name _kpn8: [2]Главн!$K$46
Name _nds1: [2]Главн!$D$42
Name _nds1: [2]Главн!$D$42

Sheet Panel
A2: Строительство ГЭС -5 МВТ
A6: Панель управления
A7: Изменение тарифа | B7: 0
A8: Изменение фонда оплаты труда | B8: 0
A9: Изменение стоимости строительно-монтажных работ | B9: 0
A10: Изменение стоимости производственного оборудования | B10: 0
A12: Результат
A13: Ставка дисконтирования, % | B13: ='ОСДП'!B7 -> 0.097271767
A14: NPV | B14: ='ОСДП'!B19 -> 2605678
A16: Срок окупаемости
A17: не дисконтированный, лет | B17: ='ОСДП'!B24 -> 7.3984916
A18: дисконтированный, лет | B18: ='ОСДП'!B25 -> 9.7048422
A20: Ставка амортизации по основным средствам:
A21: Группы основных средств: | B21: Срок службы | C21: Ед. изм | D21: Ставка, %
A22: Здания и сооружения | B22: 15 | C22: лет | D22: =1/B22 -> 0.066666667
A23: Производственное оборудование | B23: 15 | C23: лет | D23: =1/B23 -> 0.066666667
A25: Ставки налогов на коммерческие объекты | B25: 2026
A26: НДС | B26: 0.16
A27: Корпоративный подоходный налог | B27: 0.2
A29: Для расчета социального налога и обязательных отчислений в бюджет (на 2026 год):
A30: Минимальная заработная плата | B30: 85000 | C30: Тенге
A31: Месячный расчетный показатель | B31: 4325 | C31: Тенге
A32: Ставка социального налога | B32: 0.06
A33: Ставка социального страхования | B33: 0.05
A34: Минимальный размер соц.отч. | B34: =B30*B33 -> 4250 | C34: Тенге
A35: Максимальный размер соц.отч. | B35: =7*B30*B33 -> 29750 | C35: Тенге
A36: Минимальный размер соц.налога | B36: =B30*B32 -> 5100 | C36: Тенге
A37: Ставка по обязательным пенсионным отчислениям | B37: 0.1
A38: Ставка Индивидуального Подоходного Налога | B38: 0.1 | C38: используется после выплаты обязательных пенсионных отчислений и минимальной заработной платы
A39: Ставка взносов на ОСМС в 2018-2019 гг. | B39: 0.015
A40: Ставка взносов на ОСМС в 2026-2027 гг. | B40: 0.02
A41: Ставка взносов на ОСМС в 2028 г. и далее | B41: 0.03
A43: Инфляция | B43: 0.117

Sheet Инвестиции
A1: =Panel!A1
A2: =Panel!A2 -> Строительство ГЭС -5 МВТ
J3: оборудование | K3: =69000*3*335 -> 69345000
A4: ИНВЕСТИЦИОННЫЕ ЗАТРАТЫ (ВКЛ. НДС) | J4: цеха | K4: =15000000*6 -> 90000000
A6: в тыс. тенге, если не указано иное
A7: № | B7: Наименование затрат | C7: Сумма, вкл. НДС | D7: Доля, % | E7: Источники финансирования | G7: Источники финансирования, %
E8: Собственные средства | F8: Заемные средства | G8: Собственные средства | H8: Заемные средства
A9: 1 | B9: ПИР | C9: ='Смета'!G29*(1+Panel!$B$26)*(1+2%) -> 107875.75 | D9: =C9/$C$15 -> 0.035835299 | E9: =C9*G9 -> 72379.946 | F9: =C9*H9 -> 35495.805 | G9: =100%-H9 -> 0.67095659 | H9: 0.32904341
A10: 2 | B10: Экспертиза | C10: ='Смета'!G30*(1+Panel!$B$26)*(1+2%) -> 2363.5888 | D10: =C10/$C$15 -> 0.00078516174 | E10: =C10*G10 -> 2363.5888 | F10: =C10*H10 -> 0 | G10: 1 | H10: =100%-G10 -> 0
A11: 3 | B11: Cтроительно-монтажные работы | C11: ='A-0'!AM10 -> 969225.54 | D11: =C11/$C$15 -> 0.32196751 | E11: =C11*G11 -> 570489.22 | F11: =C11*H11 -> 398736.33 | G11: 0.58860316 | H11: =100%-G11 -> 0.41139684
A12: 4 | B12: Производственное оборудование | C12: ='A-0'!AM11 -> 1883220.5 | D12: =C12/$C$15 -> 0.62558796 | E12: =C12*G12 -> 0 | F12: =C12*H12 -> 1883220.5 | G12: 0 | H12: =100%-G12 -> 1
A13: 5 | B13: Технический надзор | C13: ='A-0'!AM12 -> 41930.678 | D13: =C13/$C$15 -> 0.013928973 | E13: =C13*G13 -> 8386.1356 | F13: =C13*H13 -> 33544.542 | G13: 0.2 | H13: =100%-G13 -> 0.8
A14: 6 | B14: Авторский надзор | C14: ='A-0'!AM13 -> 5704.8542 | D14: =C14/$C$15 -> 0.0018950983 | E14: =C14*G14 -> 1140.9708 | F14: =C14*H14 -> 4563.8833 | G14: 0.2 | H14: =100%-G14 -> 0.8
B15: Итого | C15: =SUM(C9:C14) -> 3010321 | D15: =SUM(D9:D14) -> 1 | E15: =SUM(E9:E14) -> 654759.86 | F15: =SUM(F9:F14) -> 2355561.1
F19: =F15-750000 -> 1605561.1 | G19: 0.67023326
F20: 750000 | G20: 0.32976674

Sheet A-0
A1: =Panel!A1 | V1: =SUM(V11:AG11) -> 784675.22 | W1: =SUM(AH11:AL11) -> 0
A2: =Panel!A2 -> Строительство ГЭС -5 МВТ
A4: ГРАФИК ФИНАНСИРОВАНИЯ
A6: в тыс. тенге, если не указано иное
A7: № | B7: Наименование | C7: 2018 | O7: 2026 | AA7: 2027 | AM7: Итого
C8: янв | D8: фев | E8: мар | F8: апр | G8: май | H8: июн | I8: июл | J8: авг | K8: сен | L8: окт | M8: ноя | N8: дек | O8: янв | P8: фев | Q8: мар | R8: апр | S8: май | T8: июн | U8: июл | V8: авг | W8: сен | X8: окт | Y8: ноя | Z8: дек | AA8: янв | AB8: фев | AC8: мар | AD8: апр | AE8: май | AF8: июн | AG8: июл | AH8: авг | AI8: сен | AJ8: окт | AK8: ноя | AL8: дек
A9: 1 | B9: ПИР | I9: =H9 | O9: ='Инвестиции'!F9 -> 35495.805 | AM9: =SUM(C9:AL9) -> 35495.805
A10: 2 | B10: ='Инвестиции'!B11 -> Cтроительно-монтажные работы | I10: =H10 | O10: =(('Смета'!D27)/12)*(1+Panel!$B$26)*(1+2.002%)*(1+Panel!$B$9) -> 80768.795 | P10: =O10 -> 80768.795 | Q10: =P10 -> 80768.795 | R10: =Q10 -> 80768.795 | S10: =R10 -> 80768.795 | T10: =S10 -> 80768.795 | U10: =T10 -> 80768.795 | V10: =U10 -> 80768.795 | W10: =V10 -> 80768.795 | ... Z10: =Y10 -> 80768.795 | AM10: =SUM(C10:AL10) -> 969225.54
A11: 3 | B11: ='Инвестиции'!B12 -> Производственное оборудование | O11: =(('Смета'!E27)/12)*(1+Panel!$B$26)*(1+2%)*(1+Panel!$B$10) -> 156935.04 | P11: =O11 -> 156935.04 | Q11: =P11 -> 156935.04 | R11: =Q11 -> 156935.04 | S11: =R11 -> 156935.04 | T11: =S11 -> 156935.04 | U11: =T11 -> 156935.04 | V11: =U11 -> 156935.04 | W11: =V11 -> 156935.04 | ... Z11: =Y11 -> 156935.04 | AM11: =SUM(C11:AL11) -> 1883220.5
A12: 4 | B12: ='Инвестиции'!B13 -> Технический надзор | O12: =(('Смета'!G32)/12)*(1+Panel!$B$26)*(1+2%)*(1+Panel!$B$9) -> 3494.2232 | P12: =O12 -> 3494.2232 | Q12: =P12 -> 3494.2232 | R12: =Q12 -> 3494.2232 | S12: =R12 -> 3494.2232 | T12: =S12 -> 3494.2232 | U12: =T12 -> 3494.2232 | V12: =U12 -> 3494.2232 | W12: =V12 -> 3494.2232 | ... Z12: =Y12 -> 3494.2232 | AM12: =SUM(C12:AL12) -> 41930.678
A13: 5 | B13: ='Инвестиции'!B14 -> Авторский надзор | I13: =H13 | O13: =(('Смета'!G34)/12)*(1+Panel!$B$26)*(1+2%)*(1+Panel!$B$9) -> 475.40451 | P13: =O13 -> 475.40451 | Q13: =P13 -> 475.40451 | R13: =Q13 -> 475.40451 | S13: =R13 -> 475.40451 | T13: =S13 -> 475.40451 | U13: =T13 -> 475.40451 | V13: =U13 -> 475.40451 | W13: =V13 -> 475.40451 | ... Z13: =Y13 -> 475.40451 | AM13: =SUM(C13:AL13) -> 5704.8542
B14: ИТОГО | C14: =SUM(C10:C13) -> 0 | D14: =SUM(D10:D13) -> 0 | E14: =SUM(E10:E13) -> 0 | F14: =SUM(F10:F13) -> 0 | G14: =SUM(G10:G13) -> 0 | H14: =SUM(H10:H13) -> 0 | I14: =SUM(I10:I13) -> 0 | J14: =SUM(J10:J13) -> 0 | ... AM14: =SUM(AM10:AM13) -> 2900081.6
B16: Собственные средства | C16: =SUM(C17:C21) -> 0 | D16: =SUM(D17:D21) -> 0 | E16: =SUM(E17:E21) -> 0 | F16: =SUM(F17:F21) -> 0 | G16: =SUM(G17:G21) -> 0 | H16: =SUM(H17:H21) -> 0 | I16: =SUM(I17:I21) -> 0 | J16: =SUM(J17:J21) -> 0 | ... AL16: =SUM(AL17:AL21) -> 0 | AM16: =SUM(E16:AL16) -> 580016.32
B17: ПИР | AM17: =SUM(E17:AL17) -> 0
B18: Cтроительно-монтажные работы | O18: =O10*'Инвестиции'!$G$11 -> 47540.768 | P18: =P10*'Инвестиции'!$G$11 -> 47540.768 | Q18: =Q10*'Инвестиции'!$G$11 -> 47540.768 | R18: =R10*'Инвестиции'!$G$11 -> 47540.768 | S18: =S10*'Инвестиции'!$G$11 -> 47540.768 | T18: =T10*'Инвестиции'!$G$11 -> 47540.768 | U18: =U10*'Инвестиции'!$G$11 -> 47540.768 | V18: =V10*'Инвестиции'!$G$11 -> 47540.768 | ... Z18: =Z10*'Инвестиции'!$G$11 -> 47540.768 | AM18: =SUM(E18:AL18) -> 570489.22
B19: Производственное оборудование | O19: =O11*'Инвестиции'!$G$12 -> 0 | P19: =P11*'Инвестиции'!$G$12 -> 0 | Q19: =Q11*'Инвестиции'!$G$12 -> 0 | R19: =R11*'Инвестиции'!$G$12 -> 0 | S19: =S11*'Инвестиции'!$G$12 -> 0 | T19: =T11*'Инвестиции'!$G$12 -> 0 | U19: =U11*'Инвестиции'!$G$12 -> 0 | V19: =V11*'Инвестиции'!$G$12 -> 0 | ... Z19: =Z11*'Инвестиции'!$G$12 -> 0 | AM19: =SUM(E19:AL19) -> 0
B20: Технический надзор | O20: =O12*'Инвестиции'!$G$13 -> 698.84463 | P20: =P12*'Инвестиции'!$G$13 -> 698.84463 | Q20: =Q12*'Инвестиции'!$G$13 -> 698.84463 | R20: =R12*'Инвестиции'!$G$13 -> 698.84463 | S20: =S12*'Инвестиции'!$G$13 -> 698.84463 | T20: =T12*'Инвестиции'!$G$13 -> 698.84463 | U20: =U12*'Инвестиции'!$G$13 -> 698.84463 | V20: =V12*'Инвестиции'!$G$13 -> 698.84463 | ... Z20: =Z12*'Инвестиции'!$G$13 -> 698.84463 | AM20: =SUM(E20:AL20) -> 8386.1356
B21: Авторский надзор | O21: =O13*'Инвестиции'!$G$14 -> 95.080902 | P21: =P13*'Инвестиции'!$G$14 -> 95.080902 | Q21: =Q13*'Инвестиции'!$G$14 -> 95.080902 | R21: =R13*'Инвестиции'!$G$14 -> 95.080902 | S21: =S13*'Инвестиции'!$G$14 -> 95.080902 | T21: =T13*'Инвестиции'!$G$14 -> 95.080902 | U21: =U13*'Инвестиции'!$G$14 -> 95.080902 | V21: =V13*'Инвестиции'!$G$14 -> 95.080902 | ... Z21: =Z13*'Инвестиции'!$G$14 -> 95.080902 | AM21: =SUM(E21:AL21) -> 1140.9708
B22: Заемные средства | C22: =SUM(C23:C27) -> 0 | D22: =SUM(D23:D27) -> 0 | E22: =SUM(E23:E27) -> 0 | F22: =SUM(F23:F27) -> 0 | G22: =SUM(G23:G27) -> 0 | H22: =SUM(H23:H27) -> 0 | I22: =SUM(I23:I27) -> 0 | J22: =SUM(J23:J27) -> 0 | ... AL22: =SUM(AL23:AL27) -> 0 | AM22: =SUM(E22:AL22) -> 2355561.1
B23: ПИР | O23: =O9 -> 35495.805 | P23: =P9 | Q23: =Q9 | R23: =R9 | S23: =S9 | T23: =T9 | U23: =U9 | V23: =V9 | ... Z23: =Z9 | AM23: =SUM(E23:AL23) -> 35495.805
B24: Cтроительно-монтажные работы | O24: =O10*'Инвестиции'!$H$11 -> 33228.027 | P24: =P10*'Инвестиции'!$H$11 -> 33228.027 | Q24: =Q10*'Инвестиции'!$H$11 -> 33228.027 | R24: =R10*'Инвестиции'!$H$11 -> 33228.027 | S24: =S10*'Инвестиции'!$H$11 -> 33228.027 | T24: =T10*'Инвестиции'!$H$11 -> 33228.027 | U24: =U10*'Инвестиции'!$H$11 -> 33228.027 | V24: =V10*'Инвестиции'!$H$11 -> 33228.027 | ... Z24: =Z10*'Инвестиции'!$H$11 -> 33228.027 | AM24: =SUM(E24:AL24) -> 398736.33
B25: Производственное оборудование | O25: =O11*'Инвестиции'!$H$12 -> 156935.04 | P25: =P11*'Инвестиции'!$H$12 -> 156935.04 | Q25: =Q11*'Инвестиции'!$H$12 -> 156935.04 | R25: =R11*'Инвестиции'!$H$12 -> 156935.04 | S25: =S11*'Инвестиции'!$H$12 -> 156935.04 | T25: =T11*'Инвестиции'!$H$12 -> 156935.04 | U25: =U11*'Инвестиции'!$H$12 -> 156935.04 | V25: =V11*'Инвестиции'!$H$12 -> 156935.04 | ... Z25: =Z11*'Инвестиции'!$H$12 -> 156935.04 | AM25: =SUM(E25:AL25) -> 1883220.5
B26: Технический надзор | O26: =O12*'Инвестиции'!$H$13 -> 2795.3785 | P26: =P12*'Инвестиции'!$H$13 -> 2795.3785 | Q26: =Q12*'Инвестиции'!$H$13 -> 2795.3785 | R26: =R12*'Инвестиции'!$H$13 -> 2795.3785 | S26: =S12*'Инвестиции'!$H$13 -> 2795.3785 | T26: =T12*'Инвестиции'!$H$13 -> 2795.3785 | U26: =U12*'Инвестиции'!$H$13 -> 2795.3785 | V26: =V12*'Инвестиции'!$H$13 -> 2795.3785 | ... Z26: =Z12*'Инвестиции'!$H$13 -> 2795.3785 | AM26: =SUM(E26:AL26) -> 33544.542
B27: Авторский надзор | O27: =O13*'Инвестиции'!$H$14 -> 380.32361 | P27: =P13*'Инвестиции'!$H$14 -> 380.32361 | Q27: =Q13*'Инвестиции'!$H$14 -> 380.32361 | R27: =R13*'Инвестиции'!$H$14 -> 380.32361 | S27: =S13*'Инвестиции'!$H$14 -> 380.32361 | T27: =T13*'Инвестиции'!$H$14 -> 380.32361 | U27: =U13*'Инвестиции'!$H$14 -> 380.32361 | V27: =V13*'Инвестиции'!$H$14 -> 380.32361 | ... Z27: =Z13*'Инвестиции'!$H$14 -> 380.32361 | AM27: =SUM(E27:AL27) -> 4563.8833

Sheet Смета
C1: =Panel!A2 -> Строительство ГЭС -5 МВТ
C2: (наименование организации)
A3: "Согласован"
A5: Сводный сметный расчет в сумме | F5: =G40 -> 3010321 | G5: тыс.тенге
B6: в том числе:
B7: налог на добавленную стоимость (НДС) | F7: =G39 -> 415216.68 | G7: тыс.тенге
B11: (ссылка на документ о согласовании)
A13: "____"_______________ 20 г.
B15: СВОДНЫЙ СМЕТНЫЙ РАСЧЕТ
B17: =Panel!A2 -> Строительство ГЭС -5 МВТ
B18: (наименование стройки)
A20: Составлен в текущих ценах по состоянию на 2 квартал 2018 г.
A21: № п/п | B21: № смет и расчетов | C21: Наименование работ и затрат | D21: Сметная стоимость, тысяч тенге | G21: Всего, тысяч тенге
D22: строительно-монтажных работ | E22: оборудования, мебели и инвентаря | F22: прочих затрат
A23: 1 | B23: 2 | C23: 3 | D23: 4 | E23: 5 | F23: 6 | G23: 7
A25: 1 | C25: Сметный расчет стоимости строительства в ценах 2001г. | D25: =423355.51+6622.34-20467.84-176502+18416.2 -> 251424.21 | E25: =336182.14-22553.74-86297.5-213914.81+456698.5+18416.2 -> 488530.79 | G25: =D25+E25+F25 -> 739955
B27: 1 | C27: Итого по сметному расчету в текущих ценах 2026 г К=3,258 | D27: =D25*3.258 -> 819140.08 | E27: =E25*3.258 -> 1591633.3 | G27: =D27+E27+F27 -> 2410773.4
A29: 2 | C29: Стоимость ПИР в 2026г | F29: =61172.88+30000 -> 91172.88 | G29: =F29 -> 91172.88
A30: 3 | C30: Стоимость экспертизы в 2026г. | F30: 1997.6241 | G30: =F30 -> 1997.6241
A32: 4 | C32: Затраты Заказчика на управление проектом и технический надзор на 2026 г. -1,47% | F32: =G27*0.0147 -> 35438.369 | G32: =F32 -> 35438.369
A33: 5
A34: 6 | C34: Затраты на осуществление авторского надзора, от стоимости СМР на 2026 г. - 0,2% | F34: =G27*0.002 -> 4821.5468 | G34: =F34 -> 4821.5468
A35: 7
C36: Итого | D36: =D26+D27+D28+F26+F27+F28 -> 819140.08 | E36: =E26+E27+E28 -> 1591633.3 | F36: =F30+F32+F33+F34+F35+F29 -> 133430.42 | G36: =G26+G27+G28+G31+G32+G33+G34+G35+G29+G30 -> 2544203.8
A37: 8 | C37: Резерв средств заказчика на непредвиденные работы и затраты (2%) | D37: =D36*0.02002 -> 16399.184 | E37: =E36*0.02 -> 31832.666 | F37: =F36*0.02 -> 2668.6084 | G37: =F37+E37+D37 -> 50900.459
C38: Итого | D38: =D36+D37 -> 835539.26 | E38: =E36+E37 -> 1623466 | F38: =F36+F37 -> 136099.03 | G38: =G36+G37 -> 2595104.3
A39: 9 | B39: Решения Правительства | C39: Налог на добавленную стоимость, 16% | D39: =D38*Panel!$B$26 -> 133686.28 | E39: =E38*Panel!$B$26 -> 259754.56 | F39: =F38*Panel!$B$26 -> 21775.844 | G39: =G38*Panel!$B$26 -> 415216.68
C40: Всего по сводному сметному расчету | D40: =D38+D39 -> 969225.54 | E40: =E38+E39 -> 1883220.5 | F40: =F38+F39 -> 157874.87 | G40: =G38+G39 -> 3010321
C41: Всего по сводному сметному расчету без ПИР | G41: =G40-G43 -> #REF!
C42: в том чиле по годам:
C43: стоимость ПИР и экспертизы с НДС | G43: =#REF!+#REF!+#REF!+#REF! -> #REF!
C44: стоимость экспертизы с НДС | G44: =#REF!+#REF! -> #REF!
C45: стоимость ПИР с НДС | G45: =#REF!+#REF! -> #REF!
C46: стоимость ПИР 2016 год ТЭО без НДС | G46: 31302
C47: стоимость ПИР 2016 год ТЭО с НДС | G47: =G46+51000/100*12 -> 37422
C48: стоимость ПИР 2017 год РД с НДС | G48: =(G45-G47)/2 -> #REF!
C49: стоимость ПИР 2018 год РД с НДС | G49: =(G45-G47)/2 -> #REF!
C50: 2016 год стоимость строительства | G50: =G62 -> 35759.405
C51: 2017 год стоимость строительства | G51: =#REF! -> #REF!
C52: 2018 год стоимость строительства | G52: =#REF! -> #REF!
C53: 2019 год стоимость строительства | G53: =#REF! -> #REF!
C55: в том числе с разбивкой по годам
C57: 2016 год
C58: Проектно-изыскательские работы | F58: 31302 | G58: =F58 -> 31302
C59: Резерв средств заказчика на непредвиденные работы и затраты (2%) | F59: =G58/100*2 -> 626.04 | G59: =F59 -> 626.04
C60: итого | F60: =F58+F59 -> 31928.04 | G60: =F60 -> 31928.04
C61: НДС | F61: =F60/100*12 -> 3831.3648 | G61: =F61 -> 3831.3648
C62: Всего в текущих ценах 2016 г. | F62: =F60+F61 -> 35759.405 | G62: =F62 -> 35759.405

Sheet Выручка
A1: =Panel!A1
A2: =Panel!A2 -> Строительство ГЭС -5 МВТ
A4: ВАЛОВАЯ ВЫРУЧКА
A6: Тариф на 2026 год по ГЭС-2 и ГЭС-3 | O6: =20.93*(1+Panel!B7) -> 20.93
AO7: 0
A8: Индекс потребительских цен (Электроэнергия, газ и другие виды топлива) в Республике Казахстан | O8: 0.099 | AB8: https://stat.gov.kz/ru/industries/economy/prices/publications/281083/#:~:text=%D0%BF%D1%80%D0%BE%D1%87%D0%B8%D0%B5%20%D0%B2%D0%B8%D0%B4%D1%8B%20%D1%82%D0%BE%D0%BF%D0%BB%D0%B8%D0%B2%D0%B0-,9%2C9,-0%2C814
A10: в тыс.тенге, если не указано иное
A11: № | B11: Наименование | C11: янв | D11: фев | E11: мар | F11: апр | G11: май | H11: июн | I11: июл | J11: авг | K11: сен | L11: окт | M11: ноя | N11: дек | O11: 2026 | P11: янв | Q11: фев | R11: мар | S11: апр | T11: май | U11: июн | V11: июл | W11: авг | X11: сен | Y11: окт | Z11: ноя | AA11: дек | AB11: 2027 | AC11: янв | AD11: фев | AE11: мар | AF11: апр | AG11: май | AH11: июн | AI11: июл | AJ11: авг | AK11: сен | AL11: окт | AM11: ноя | AN11: дек | AO11: 2028 | AP11: 2029 | AQ11: 2030 | AR11: 2031 | AS11: 2032 | AT11: 2033 | AU11: 2034 | AV11: 2035 | AW11: 2036 | AX11: 2037 | AY11: 2038 | AZ11: 2039 | BA11: 2040 | BB11: 2041 | BC11: 2042
A12: 1 | B12: ГЭС-1 на р. | C12: =$O$6*E46*1000 -> 29009.299 | D12: =$O$6*F46*1000 -> 24623.493 | E12: =$O$6*G46*1000 -> 38688.925 | F12: =$O$6*H46*1000 -> 22817.101 | G12: =$O$6*I46*1000 -> 51857.622 | H12: =$O$6*J46*1000 -> 58345.554 | I12: =$O$6*K46*1000 -> 72710.354 | J12: =$O$6*L46*1000 -> 72710.354 | ... N12: =$O$6*P46*1000 -> 29890.895 | O12: =SUM(C12:N12) -> 548578.41 | P12: =C12*(1+$O$8) -> 31881.22 | Q12: =D12*(1+$O$8) -> 27061.219 | R12: =E12*(1+$O$8) -> 42519.129 | S12: =F12*(1+$O$8) -> 25075.994 | T12: =G12*(1+$O$8) -> 56991.526 | U12: =H12*(1+$O$8) -> 64121.763 | V12: =I12*(1+$O$8) -> 79908.679 | W12: =J12*(1+$O$8) -> 79908.679 | ... AA12: =N12*(1+$O$8) -> 32850.093 | AB12: =SUM(P12:AA12) -> 602887.67 | AC12: =P12*(1+$O$8) -> 35037.461 | AD12: =Q12*(1+$O$8) -> 29740.279 | AE12: =R12*(1+$O$8) -> 46728.523 | AF12: =S12*(1+$O$8) -> 27558.518 | AG12: =T12*(1+$O$8) -> 62633.687 | AH12: =U12*(1+$O$8) -> 70469.818 | AI12: =V12*(1+$O$8) -> 87819.638 | AJ12: =W12*(1+$O$8) -> 87819.638 | ... AN12: =AA12*(1+$O$8) -> 36102.253 | AO12: =SUM(AC12:AN12) -> 662573.55 | AP12: =AO12*(1+$O$8) -> 728168.33 | AQ12: =AP12*(1+$O$8) -> 800256.99 | AR12: =AQ12*(1+$O$8) -> 879482.44 | AS12: =AR12*(1+$O$8) -> 966551.2 | AT12: =AS12*(1+$O$8) -> 1062239.8 | AU12: =AT12*(1+$O$8) -> 1167401.5 | AV12: =AU12*(1+$O$8) -> 1282974.2 | AW12: =AV12*(1+$O$8) -> 1409988.7 | ... BC12: =BB12*(1+$O$8) -> 2484287.1
B13: Итого | C13: =SUM(C12) -> 29009.299 | D13: =SUM(D12) -> 24623.493 | E13: =SUM(E12) -> 38688.925 | F13: =SUM(F12) -> 22817.101 | G13: =SUM(G12) -> 51857.622 | H13: =SUM(H12) -> 58345.554 | I13: =SUM(I12) -> 72710.354 | J13: =SUM(J12) -> 72710.354 | ... BC13: =SUM(BC12) -> 2484287.1
A15: ВОДНОЭНЕРГЕТИЧЕСКИЕ РАСЧЕТЫ ГЭС
A16: Технические параметры | D16: Един. | E16: Среднмесячные расходы воды, м3/с | Q16: За год
D17: измер. | E17: I | F17: II | G17: III | H17: IV | I17: V | J17: VI | K17: VII | L17: VIII | M17: IX | N17: X | O17: XI | P17: XII
A18: 0 | D18: 1 | E18: 2 | F18: 3 | G18: 4 | H18: 5 | I18: 6 | J18: 7 | K18: 8 | L18: 9 | M18: 10 | N18: 11 | O18: 12 | P18: 13 | Q18: 14
A19: 1. Продолжительность периода в часах, Т | D19: часы | E19: 744 | F19: 672 | G19: 744 | H19: 720 | I19: 744 | J19: 720 | K19: 744 | L19: 744 | M19: 720 | N19: 744 | O19: 720 | P19: 744 | Q19: =SUM(E19:P19) -> 8760
A20: 2. Расходы воды в реке Qр (р=50%) | D20: м3/с | E20: 3.97 | F20: 3.72 | G20: 5.47 | H20: 6.63 | I20: 14.5 | J20: 24.4 | K20: 28.4 | L20: 21.5 | M20: 11.2 | N20: 7.14 | O20: 5.73 | P20: 4.17 | Q20: =SUM(E20:P20)/12 -> 11.4025
A21: 3. Расходы воды, забираемые на орошение | D21: м3/с | E21: 0 | F21: 0 | G21: 0 | H21: 2.8 | I21: 5.63 | J21: 12.45 | K21: 9.63 | L21: 2.83 | M21: 1.27 | N21: 0 | O21: 0 | P21: 0
A22: 4. Расходы санитарного(эколог.) попуска ΔQэк | D22: м3/с | E22: =0.15*E20 -> 0.5955 | F22: =0.15*F20 -> 0.558 | G22: =0.15*G20 -> 0.8205 | H22: =0.15*H20 -> 0.9945 | I22: =0.15*I20 -> 2.175 | J22: =0.15*J20 -> 3.66 | K22: =0.15*K20 -> 4.26 | L22: =0.15*L20 -> 3.225 | ... P22: =0.15*P20 -> 0.6255
A23: 5. Технолог. потери воды в голове деривации ГЭС Qгэсп | D23: м3/с | E23: =0.01*E20 -> 0.0397 | F23: =0.01*F20 -> 0.0372 | G23: =0.02*G20 -> 0.1094 | H23: =0.02*H20 -> 0.1326 | I23: =0.02*I20 -> 0.29 | J23: =0.02*J20 -> 0.488 | K23: =0.02*K20 -> 0.568 | L23: =0.01*L20 -> 0.215 | M23: =0.01*M20 -> 0.112 | N23: =0.01*N20 -> 0.0714 | O23: =0.01*O20 -> 0.0573 | P23: =0.02*P20 -> 0.0834
A24: 6. Рабочие расходы ГЭС Qгэср | D24: м3/с | E24: =IF(E20-(E21+E22+E23)>11,11,E20-(E21+E22+E23)) -> 3.3348 | F24: =IF(F20-(F21+F22+F23)>11,11,F20-(F21+F22+F23)) -> 3.1248 | G24: =IF(G20-(G21+G22+G23)>11,11,G20-(G21+G22+G23)) -> 4.5401 | H24: =IF(H20-(H21+H22+H23)>11,11,H20-(H21+H22+H23)) -> 2.7029 | I24: =IF(I20-(I21+I22+I23)>11,11,I20-(I21+I22+I23)) -> 6.405 | J24: =IF(J20-(J21+J22+J23)>11,11,J20-(J21+J22+J23)) -> 7.802 | K24: =IF(K20-(K21+K22+K23)>11,11,K20-(K21+K22+K23)) -> 11 | L24: =IF(L20-(L21+L22+L23)>11,11,L20-(L21+L22+L23)) -> 11 | ... P24: =IF(P20-(P21+P22+P23)>11,11,P20-(P21+P22+P23)) -> 3.4611
A25: 7. Свободный сток в реке(холостыесбросы) Qхол.сбр. | D25: м3/с | E25: =E20-(E21+E24) -> 0.6352 | F25: =F20-(F21+F24) -> 0.5952 | G25: =G20-(G21+G24) -> 0.9299 | H25: =H20-(H21+H24) -> 1.1271 | I25: =I20-(I21+I24) -> 2.465 | J25: =J20-(J21+J24) -> 4.148 | K25: =K20-(K21+K24) -> 7.77 | L25: =L20-(L21+L24) -> 7.67 | ... P25: =P20-(P21+P24) -> 0.7089
A26: 8. Статический напор, Нгеод=862.5-797,5=65м | D26: м | E26: 65 | F26: 65 | G26: 65 | H26: 65 | I26: 65 | J26: 65 | K26: 65 | L26: 65 | M26: 65 | N26: 65 | O26: 65 | P26: 65 | Q26: 65
A27: 9. Расчёт гидропотерь в деривационном тракте:
A28: 9.1. Потери в ГВУ, подводящем канале и отстойнике hгву | D28: м | E28: 0.5 | F28: 0.5 | G28: 0.5 | H28: 0.5 | I28: 0.5 | J28: 0.5 | K28: 0.5 | L28: 0.5 | M28: 0.5 | N28: 0.5 | O28: 0.5 | P28: 0.5
A29: 9.2. Деривационный ВОДОВОД
A30: 9.2.1. Протяжённость деривац.ВОДОВОДА Lд.в. | D30: м | E30: 4450 | F30: 4450 | G30: 4450 | H30: 4450 | I30: 4450 | J30: 4450 | K30: 4450 | L30: 4450 | M30: 4450 | N30: 4450 | O30: 4450 | P30: 4450 | Q30: 4450
A31: 9.2.2. Диаметр водовода D=2,1м | D31: м | E31: 2.1 | F31: 2.1 | G31: 2.1 | H31: 2.1 | I31: 2.1 | J31: 2.1 | K31: 2.1 | L31: 2.1 | M31: 2.1 | N31: 2.1 | O31: 2.1 | P31: 2.1
A32: 9.2.3. Абсолютная эквивал.шероховатость, kэ | D32: мм | E32: 0.5 | F32: 0.5 | G32: 0.5 | H32: 0.5 | I32: 0.5 | J32: 0.5 | K32: 0.5 | L32: 0.5 | M32: 0.5 | N32: 0.5 | O32: 0.5 | P32: 0.5
A33: 9.2.4. К-т потерь по длине λ=0,11х ( k/ D)0,25 | D33: ₋ | E33: =0.11*(E32/(1000*E31))^0.25 -> 0.013664079 | F33: =0.11*(F32/(1000*F31))^0.25 -> 0.013664079 | G33: =0.11*(G32/(1000*G31))^0.25 -> 0.013664079 | H33: =0.11*(H32/(1000*H31))^0.25 -> 0.013664079 | I33: =0.11*(I32/(1000*I31))^0.25 -> 0.013664079 | J33: =0.11*(J32/(1000*J31))^0.25 -> 0.013664079 | K33: =0.11*(K32/(1000*K31))^0.25 -> 0.013664079 | L33: =0.11*(L32/(1000*L31))^0.25 -> 0.013664079 | ... P33: =0.11*(P32/(1000*P31))^0.25 -> 0.013664079
A34: 9.2.5. λ x L/D | D34: ₋ | E34: =E33*E30/E31 -> 28.954834 | F34: =F33*F30/F31 -> 28.954834 | G34: =G33*G30/G31 -> 28.954834 | H34: =H33*H30/H31 -> 28.954834 | I34: =I33*I30/I31 -> 28.954834 | J34: =J33*J30/J31 -> 28.954834 | K34: =K33*K30/K31 -> 28.954834 | L34: =L33*L30/L31 -> 28.954834 | ... P34: =P33*P30/P31 -> 28.954834
A35: 9.2.6. ω=π x D2/4 - площадь водовода в свету | D35: м2 | E35: =3.1416*(E31)^2/4 -> 3.463614 | F35: =3.1416*(F31)^2/4 -> 3.463614 | G35: =3.1416*(G31)^2/4 -> 3.463614 | H35: =3.1416*(H31)^2/4 -> 3.463614 | I35: =3.1416*(I31)^2/4 -> 3.463614 | J35: =3.1416*(J31)^2/4 -> 3.463614 | K35: =3.1416*(K31)^2/4 -> 3.463614 | L35: =3.1416*(L31)^2/4 -> 3.463614 | ... P35: =3.1416*(P31)^2/4 -> 3.463614
A36: 9.2.7. V = Q/ω - скорость воды в деривации | D36: м/с | E36: =E24/E35 -> 0.96280937 | F36: =F24/F35 -> 0.90217905 | G36: =G24/G35 -> 1.3107985 | H36: =H24/H35 -> 0.78036987 | I36: =I24/I35 -> 1.8492245 | J36: =J24/J35 -> 2.2525605 | K36: =K24/K35 -> 3.1758735 | L36: =L24/L35 -> 3.1758735 | ... P36: =P24/P35 -> 0.99927417
A37: 9.2.8. V2 / 2g - скоростной напор | D37: м | E37: =(E36)^2/(2*9.81) -> 0.047247802 | F37: =(F36)^2/(2*9.81) -> 0.041484559 | G37: =(G36)^2/(2*9.81) -> 0.087573531 | H37: =(H36)^2/(2*9.81) -> 0.03103859 | I37: =(I36)^2/(2*9.81) -> 0.17429314 | J37: =(J36)^2/(2*9.81) -> 0.25861512 | K37: =(K36)^2/(2*9.81) -> 0.51407608 | L37: =(L36)^2/(2*9.81) -> 0.51407608 | ... P37: =(P36)^2/(2*9.81) -> 0.050894438
A38: 9.2.9. Гидропотери по длине водовода: hwl = λ x L / DxV2/2g | D38: м | E38: =E34*E37 -> 1.3680523 | F38: =F34*F37 -> 1.2011785 | G38: =G34*G37 -> 2.5356771 | H38: =H34*H37 -> 0.89871721 | I38: =I34*I37 -> 5.0466289 | J38: =J34*J37 -> 7.4881579 | K38: =K34*K37 -> 14.884987 | L38: =L34*L37 -> 14.884987 | ... P38: =P34*P37 -> 1.47364
A39: 9.2.10. Местные гидропотери в дер.водоводе: hм= 0,1хhwl | D39: м | E39: =0.1*E38 -> 0.13680523 | F39: =0.1*F38 -> 0.12011785 | G39: =0.1*G38 -> 0.25356771 | H39: =0.1*H38 -> 0.089871721 | I39: =0.1*I38 -> 0.50466289 | J39: =0.1*J38 -> 0.74881579 | K39: =0.1*K38 -> 1.4884987 | L39: =0.1*L38 -> 1.4884987 | ... P39: =0.1*P38 -> 0.147364
A40: 9.2.11.Суммарные потери в дер.водоводе: Нд.в.= hwl +hм | D40: м | E40: =E38+E39 -> 1.5048575 | F40: =F38+F39 -> 1.3212964 | G40: =G38+G39 -> 2.7892448 | H40: =H38+H39 -> 0.98858893 | I40: =I38+I39 -> 5.5512918 | J40: =J38+J39 -> 8.2369737 | K40: =K38+K39 -> 16.373486 | L40: =L38+L39 -> 16.373486 | ... P40: =P38+P39 -> 1.621004
A41: Полные гидропотери в тракте Hполн=hгву+Нд.в. | D41: м | E41: =E28+E40 -> 2.0048575 | F41: =F28+F40 -> 1.8212964 | G41: =G28+G40 -> 3.2892448 | H41: =H28+H40 -> 1.4885889 | I41: =I28+I40 -> 6.0512918 | J41: =J28+J40 -> 8.7369737 | K41: =K28+K40 -> 16.873486 | L41: =L28+L40 -> 16.873486 | ... P41: =P28+P40 -> 2.121004
A42: 5. Рабочий напор на ГЭС, Нгэс | D42: м | E42: =E26-E41 -> 62.995143 | F42: =F26-F41 -> 63.178704 | G42: =G26-G41 -> 61.710755 | H42: =H26-H41 -> 63.511411 | I42: =I26-I41 -> 58.948708 | J42: =J26-J41 -> 56.263026 | K42: =K26-K41 -> 48.126514 | L42: =L26-L41 -> 48.126514 | ... P42: =P26-P41 -> 62.878996
A43: 6. К.П.Д. турбины ηт | D43: % | E43: 93 | F43: 93 | G43: 93 | H43: 92.5 | I43: 92.5 | J43: 92.5 | K43: 92.5 | L43: 92.5 | M43: 92.5 | N43: 92.7 | O43: 91 | P43: 92.5
A44: 7. К.П.Д. генератора ηг | D44: % | E44: 97.2 | F44: 97.2 | G44: 97.2 | H44: 97.2 | I44: 97.2 | J44: 97.2 | K44: 97.2 | L44: 97.2 | M44: 97.2 | N44: 97.2 | O44: 97.2 | P44: 97.2
A45: 8. Мощность ГЭС Nустгэс = АхQгэсхНгэс | D45: МВт | E45: =IF((9.81*E24*E42*E43*E44*0.0000001)>5,5,9.81*E24*E42*E43*E44*0.0000001) -> 1.8629237 | F45: =IF((9.81*F24*F42*F43*F44*0.0000001)>5,5,9.81*F24*F42*F43*F44*0.0000001) -> 1.7506977 | G45: =IF((9.81*G24*G42*G43*G44*0.0000001)>5,5,9.81*G24*G42*G43*G44*0.0000001) -> 2.4845315 | H45: =IF((9.81*H24*H42*H43*H44*0.0000001)>5,5,9.81*H24*H42*H43*H44*0.0000001) -> 1.5141146 | I45: =IF((9.81*I24*I42*I43*I44*0.0000001)>5,5,9.81*I24*I42*I43*I44*0.0000001) -> 3.3302009 | J45: =IF((9.81*J24*J42*J43*J44*0.0000001)>5,5,9.81*J24*J42*J43*J44*0.0000001) -> 3.8717387 | K45: =IF((9.81*K24*K42*K43*K44*0.0000001)>5,5,9.81*K24*K42*K43*K44*0.0000001) -> 4.6693249 | L45: =IF((9.81*L24*L42*L43*L44*0.0000001)>5,5,9.81*L24*L42*L43*L44*0.0000001) -> 4.6693249 | ... P45: =IF((9.81*P24*P42*P43*P44*0.0000001)>5,5,9.81*P24*P42*P43*P44*0.0000001) -> 1.9195382 | Q45: 5
A46: 9. Среднегодовая выработка электроэнергии, Эгэс | D46: ГВт• Ч | E46: =E45*E19*0.001 -> 1.3860153 | F46: =F45*F19*0.001 -> 1.1764688 | G46: =G45*G19*0.001 -> 1.8484914 | H46: =H45*H19*0.001 -> 1.0901625 | I46: =I45*I19*0.001 -> 2.4776695 | J46: =J45*J19*0.001 -> 2.7876519 | K46: =K45*K19*0.001 -> 3.4739777 | L46: =L45*L19*0.001 -> 3.4739777 | ... P46: =P45*P19*0.001 -> 1.4281364 | Q46: =SUM(E46:P46) -> 26.210148
A47: 10. Среднегодовое число часов использования Nустгэс | D47: Часы | Q47: =Q46*1000/Q45 -> 5242.0297

Sheet Произв.затраты
A1: =Panel!A1
A2: =Panel!A2 -> Строительство ГЭС -5 МВТ
A4: ПРОИЗВОДСТВЕННЫЕ ИЗДЕРЖКИ
A6: в тыс.тенге, если не указано иное
A7: № | B7: Элементы затрат | C7: янв | D7: фев | E7: мар | F7: апр | G7: май | H7: июн | I7: июл | J7: авг | K7: сен | L7: окт | M7: ноя | N7: дек | O7: 2026 | P7: янв | Q7: фев | R7: мар | S7: апр | T7: май | U7: июн | V7: июл | W7: авг | X7: сен | Y7: окт | Z7: ноя | AA7: дек | AB7: 2027 | AC7: янв | AD7: фев | AE7: мар | AF7: апр | AG7: май | AH7: июн | AI7: июл | AJ7: авг | AK7: сен | AL7: окт | AM7: ноя | AN7: дек | AO7: 2028 | AP7: 2029 | AQ7: 2030 | AR7: 2031 | AS7: 2032 | AT7: 2033 | AU7: 2034 | AV7: 2035 | AW7: 2036 | AX7: 2037 | AY7: 2038 | AZ7: 2039 | BA7: 2040 | BB7: 2041 | BC7: 2042
A8: 1.1 | B8: =B24 -> Амортизационные отчисления | C8: =C24 -> 14417.246 | D8: =D24 -> 14417.246 | E8: =E24 -> 14417.246 | F8: =F24 -> 14417.246 | G8: =G24 -> 14417.246 | H8: =H24 -> 14417.246 | I8: =I24 -> 14417.246 | ... BC8: =BC24 -> 173006.95
A9: 1.2 | B9: ='Произв.затраты'!B41 -> Текущий ремонт оборудования | C9: ='Произв.затраты'!C42 -> 194.05348 | D9: ='Произв.затраты'!D42 -> 194.05348 | E9: ='Произв.затраты'!E42 -> 194.05348 | F9: ='Произв.затраты'!F42 -> 194.05348 | G9: ='Произв.затраты'!G42 -> 194.05348 | H9: ='Произв.затраты'!H42 -> 194.05348 | I9: ='Произв.затраты'!I42 -> 194.05348 | J9: ='Произв.затраты'!J42 -> 194.05348 | ... BC9: ='Произв.затраты'!BC42 -> 13675.822
A10: 1.3 | B10: ='Произв.затраты'!B51 -> Электроэнергия на объекте | C10: ='Произв.затраты'!C52 -> 99.055116 | D10: ='Произв.затраты'!D52 -> 99.055116 | E10: ='Произв.затраты'!E52 -> 99.055116 | F10: ='Произв.затраты'!F52 -> 99.055116 | G10: ='Произв.затраты'!G52 -> 99.055116 | H10: ='Произв.затраты'!H52 -> 99.055116 | I10: ='Произв.затраты'!I52 -> 99.055116 | J10: ='Произв.затраты'!J52 -> 99.055116 | ... BC10: ='Произв.затраты'!BC52 -> 6980.86
A11: 1.4 | B11: ='Произв.затраты'!B59 -> Налог на имущество | C11: ='Произв.затраты'!C60 -> 1008.2866 | D11: ='Произв.затраты'!D60 -> 1008.2866 | E11: ='Произв.затраты'!E60 -> 1008.2866 | F11: ='Произв.затраты'!F60 -> 1008.2866 | G11: ='Произв.затраты'!G60 -> 1008.2866 | H11: ='Произв.затраты'!H60 -> 1008.2866 | I11: ='Произв.затраты'!I60 -> 1008.2866 | J11: ='Произв.затраты'!J60 -> 1008.2866 | ... BC11: ='Произв.затраты'!BC60 -> 0
A12: 1.5 | B12: ='Произв.затраты'!B71 -> Земельный налог | C12: ='Произв.затраты'!C72 -> 8.6245833 | D12: ='Произв.затраты'!D72 -> 8.6245833 | E12: ='Произв.затраты'!E72 -> 8.6245833 | F12: ='Произв.затраты'!F72 -> 8.6245833 | G12: ='Произв.затраты'!G72 -> 8.6245833 | H12: ='Произв.затраты'!H72 -> 8.6245833 | I12: ='Произв.затраты'!I72 -> 8.6245833 | J12: ='Произв.затраты'!J72 -> 8.6245833 | ... BC12: ='Произв.затраты'!BC72 -> 103.495
A13: 1.6 | B13: ='Произв.затраты'!B81 -> Плата за пользование водными ресурсами | C13: ='Произв.затраты'!C82 -> 101.31772 | D13: ='Произв.затраты'!D82 -> 85.999872 | E13: ='Произв.затраты'!E82 -> 135.12472 | F13: ='Произв.затраты'!F82 -> 79.690879 | G13: ='Произв.затраты'!G82 -> 181.11764 | H13: ='Произв.затраты'!H82 -> 203.77735 | I13: ='Произв.затраты'!I82 -> 253.94777 | J13: ='Произв.затраты'!J82 -> 253.94777 | ... BC13: ='Произв.затраты'!BC82 -> 1915.9618
A14: 1.7 | B14: ='Произв.затраты'!B91 -> Услуги диспетчеризации | C14: ='Произв.затраты'!C92 -> 403.80267 | D14: ='Произв.затраты'!D92 -> 382.8554 | E14: ='Произв.затраты'!E92 -> 601.55007 | F14: ='Произв.затраты'!F92 -> 354.76893 | G14: ='Произв.затраты'!G92 -> 806.30195 | H14: ='Произв.затраты'!H92 -> 907.17877 | I14: ='Произв.затраты'!I92 -> 1130.5281 | J14: ='Произв.затраты'!J92 -> 1130.5281 | ... BC14: ='Произв.затраты'!BC92 -> 49815.254
A15: 1.8 | B15: ='Произв.затраты'!B101 -> Оперативно-техническое и диспетчерское обслуживание | C15: ='Произв.затраты'!C102 -> 2151.1879 | D15: ='Произв.затраты'!D102 -> 2151.1879 | E15: ='Произв.затраты'!E102 -> 2151.1879 | F15: ='Произв.затраты'!F102 -> 2151.1879 | G15: ='Произв.затраты'!G102 -> 2151.1879 | H15: ='Произв.затраты'!H102 -> 2151.1879 | I15: ='Произв.затраты'!I102 -> 2151.1879 | J15: ='Произв.затраты'!J102 -> 2151.1879 | ... BC15: ='Произв.затраты'!BC102 -> 151603.9
A16: 1.9 | B16: Непредвиденные расходы | C16: ='Произв.затраты'!C113 -> 145.0465 | D16: ='Произв.затраты'!D113 -> 123.11746 | E16: ='Произв.затраты'!E113 -> 193.44463 | F16: ='Произв.затраты'!F113 -> 114.08551 | G16: ='Произв.затраты'!G113 -> 259.28811 | H16: ='Произв.затраты'!H113 -> 291.72777 | I16: ='Произв.затраты'!I113 -> 363.55177 | J16: ='Произв.затраты'!J113 -> 363.55177 | ... BC16: ='Произв.затраты'!BC113 -> 12421.436
B17: Итого | C17: =SUM(C8:C16) -> 18528.62 | D17: =SUM(D8:D16) -> 18470.426 | E17: =SUM(E8:E16) -> 18808.573 | F17: =SUM(F8:F16) -> 18426.999 | G17: =SUM(G8:G16) -> 19125.161 | H17: =SUM(H8:H16) -> 19281.138 | I17: =SUM(I8:I16) -> 19626.481 | J17: =SUM(J8:J16) -> 19626.481 | ... BC17: =SUM(BC8:BC16) -> 409523.68
A20: РАСЧЕТ АМОРТИЗАЦИОННЫХ ОТЧИСЛЕНИЙ НА ПРОИЗВОДСТВЕННЫЕ ОСНОВНЫЕ СРЕДСТВА
A22: в тыс. тенге, если не указано иное
A23: № | B23: Наименование | C23: янв | D23: фев | E23: мар | F23: апр | G23: май | H23: июн | I23: июл | J23: авг | K23: сен | L23: окт | M23: ноя | N23: дек | O23: 2026 | P23: янв | Q23: фев | R23: мар | S23: апр | T23: май | U23: июн | V23: июл | W23: авг | X23: сен | Y23: окт | Z23: ноя | AA23: дек | AB23: 2027 | AC23: янв | AD23: фев | AE23: мар | AF23: апр | AG23: май | AH23: июн | AI23: июл | AJ23: авг | AK23: сен | AL23: окт | AM23: ноя | AN23: дек | AO23: 2028 | AP23: 2029 | AQ23: 2030 | AR23: 2031 | AS23: 2032 | AT23: 2033 | AU23: 2034 | AV23: 2035 | AW23: 2036 | AX23: 2037 | AY23: 2038 | AZ23: 2039 | BA23: 2040 | BB23: 2041 | BC23: 2042
A24: 1 | B24: Амортизационные отчисления | C24: =F32 -> 14417.246 | D24: =C24 -> 14417.246 | E24: =D24 -> 14417.246 | F24: =E24 -> 14417.246 | G24: =F24 -> 14417.246 | H24: =G24 -> 14417.246 | I24: =H24 -> 14417.246 | J24: =I24 -> 14417.246 | K24: =J24 -> 14417.246 | ... N24: =M24 -> 14417.246 | O24: =SUM(C24:N24) -> 173006.95 | P24: =C24 -> 14417.246 | Q24: =D24 -> 14417.246 | R24: =E24 -> 14417.246 | S24: =F24 -> 14417.246 | T24: =G24 -> 14417.246 | U24: =H24 -> 14417.246 | V24: =I24 -> 14417.246 | W24: =J24 -> 14417.246 | ... AA24: =N24 -> 14417.246 | AB24: =SUM(P24:AA24) -> 173006.95 | AC24: =P24 -> 14417.246 | AD24: =AC24 -> 14417.246 | AE24: =AD24 -> 14417.246 | AF24: =AE24 -> 14417.246 | AG24: =AF24 -> 14417.246 | AH24: =AG24 -> 14417.246 | AI24: =AH24 -> 14417.246 | AJ24: =AI24 -> 14417.246 | AK24: =AJ24 -> 14417.246 | ... AN24: =AM24 -> 14417.246 | AO24: =SUM(AC24:AN24) -> 173006.95 | AP24: =AO24 -> 173006.95 | AQ24: =AP24 -> 173006.95 | AR24: =AQ24 -> 173006.95 | AS24: =AR24 -> 173006.95 | AT24: =AS24 -> 173006.95 | AU24: =AT24 -> 173006.95 | AV24: =AU24 -> 173006.95 | AW24: =AV24 -> 173006.95 | ... BC24: =BB24 -> 173006.95
B25: Итого | C25: =SUM(C24) -> 14417.246 | D25: =SUM(D24) -> 14417.246 | E25: =SUM(E24) -> 14417.246 | F25: =SUM(F24) -> 14417.246 | G25: =SUM(G24) -> 14417.246 | H25: =SUM(H24) -> 14417.246 | I25: =SUM(I24) -> 14417.246 | J25: =SUM(J24) -> 14417.246 | ... BC25: =SUM(BC24) -> 173006.95
A28: в тыс. тенге, если не указано иное
A29: № | B29: Наименование | C29: Стоимость без учета НДС | D29: Срок службы, лет | E29: Ставка, % | F29: Амортизационные отчисления
F30: в мес. | G30: в год
A31: 1.1 | B31: ГЭС-1 | C31: =('Инвестиции'!C14+'Инвестиции'!C13+'Инвестиции'!C12+'Инвестиции'!C11+'Инвестиции'!C9+'Инвестиции'!C10)/(1+Panel!B26) -> 2595104.3 | D31: =Panel!B22 -> 15 | E31: =1/D31 -> 0.066666667 | F31: =C31*E31/12 -> 14417.246 | G31: =F31*12 -> 173006.95
B32: Итого | C32: =SUM(C31) -> 2595104.3 | F32: =SUM(F31) -> 14417.246 | G32: =SUM(G31) -> 173006.95
A35: Текущий ремонт оборудования
B37: Норматив затрат | C37: =2084728.53/12 -> 173727.38 | D37: тенге/мес. | E37: Норматив на основе эксплуатации
A39: в тыс. тенге, если не указано иное
A40: № | B40: Наименование | C40: янв | D40: фев | E40: мар | F40: апр | G40: май | H40: июн | I40: июл | J40: авг | K40: сен | L40: окт | M40: ноя | N40: дек | O40: 2026 | P40: янв | Q40: фев | R40: мар | S40: апр | T40: май | U40: июн | V40: июл | W40: авг | X40: сен | Y40: окт | Z40: ноя | AA40: дек | AB40: 2027 | AC40: янв | AD40: фев | AE40: мар | AF40: апр | AG40: май | AH40: июн | AI40: июл | AJ40: авг | AK40: сен | AL40: окт | AM40: ноя | AN40: дек | AO40: 2028 | AP40: 2029 | AQ40: 2030 | AR40: 2031 | AS40: 2032 | AT40: 2033 | AU40: 2034 | AV40: 2035 | AW40: 2036 | AX40: 2037 | AY40: 2038 | AZ40: 2039 | BA40: 2040 | BB40: 2041 | BC40: 2042
A41: 1 | B41: Текущий ремонт оборудования | C41: =C37*(1+Panel!$B$43)/1000 -> 194.05348 | D41: =C41 -> 194.05348 | E41: =D41 -> 194.05348 | F41: =E41 -> 194.05348 | G41: =F41 -> 194.05348 | H41: =G41 -> 194.05348 | I41: =H41 -> 194.05348 | J41: =I41 -> 194.05348 | K41: =J41 -> 194.05348 | ... N41: =M41 -> 194.05348 | O41: =SUM(C41:N41) -> 2328.6418 | P41: =N41*(1+Panel!$B$43) -> 216.75774 | Q41: =P41 -> 216.75774 | R41: =Q41 -> 216.75774 | S41: =R41 -> 216.75774 | T41: =S41 -> 216.75774 | U41: =T41 -> 216.75774 | V41: =U41 -> 216.75774 | W41: =V41 -> 216.75774 | X41: =W41 -> 216.75774 | ... AA41: =Z41 -> 216.75774 | AB41: =SUM(P41:AA41) -> 2601.0929 | AC41: =AA41*(1+Panel!$B$43) -> 242.11839 | AD41: =AC41 -> 242.11839 | AE41: =AD41 -> 242.11839 | AF41: =AE41 -> 242.11839 | AG41: =AF41 -> 242.11839 | AH41: =AG41 -> 242.11839 | AI41: =AH41 -> 242.11839 | AJ41: =AI41 -> 242.11839 | AK41: =AJ41 -> 242.11839 | ... AN41: =AM41 -> 242.11839 | AO41: =SUM(AC41:AN41) -> 2905.4207 | AP41: =AO41*(1+Panel!$B$43) -> 3245.3549 | AQ41: =AP41*(1+Panel!$B$43) -> 3625.0615 | AR41: =AQ41*(1+Panel!$B$43) -> 4049.1937 | AS41: =AR41*(1+Panel!$B$43) -> 4522.9493 | AT41: =AS41*(1+Panel!$B$43) -> 5052.1344 | AU41: =AT41*(1+Panel!$B$43) -> 5643.2341 | AV41: =AU41*(1+Panel!$B$43) -> 6303.4925 | AW41: =AV41*(1+Panel!$B$43) -> 7041.0011 | ... BC41: =BB41*(1+Panel!$B$43) -> 13675.822
B42: Итого | C42: =SUM(C41) -> 194.05348 | D42: =SUM(D41) -> 194.05348 | E42: =SUM(E41) -> 194.05348 | F42: =SUM(F41) -> 194.05348 | G42: =SUM(G41) -> 194.05348 | H42: =SUM(H41) -> 194.05348 | I42: =SUM(I41) -> 194.05348 | J42: =SUM(J41) -> 194.05348 | ... BC42: =SUM(BC41) -> 13675.822
A45: Электроэнергия на объекте
B47: Норматив затрат | C47: =952690.45/12 -> 79390.871 | D47: тенге/мес. | E47: Норматив на основе эксплуатации
A49: в тыс. тенге, если не указано иное
A50: № | B50: Наименование | C50: янв | D50: фев | E50: мар | F50: апр | G50: май | H50: июн | I50: июл | J50: авг | K50: сен | L50: окт | M50: ноя | N50: дек | O50: 2026 | P50: янв | Q50: фев | R50: мар | S50: апр | T50: май | U50: июн | V50: июл | W50: авг | X50: сен | Y50: окт | Z50: ноя | AA50: дек | AB50: 2027 | AC50: янв | AD50: фев | AE50: мар | AF50: апр | AG50: май | AH50: июн | AI50: июл | AJ50: авг | AK50: сен | AL50: окт | AM50: ноя | AN50: дек | AO50: 2028 | AP50: 2029 | AQ50: 2030 | AR50: 2031 | AS50: 2032 | AT50: 2033 | AU50: 2034 | AV50: 2035 | AW50: 2036 | AX50: 2037 | AY50: 2038 | AZ50: 2039 | BA50: 2040 | BB50: 2041 | BC50: 2042
A51: 1 | B51: Электроэнергия на объекте | C51: =C47*(1+Panel!$B$43)*(1+Panel!$B$43)/1000 -> 99.055116 | D51: =C51 -> 99.055116 | E51: =D51 -> 99.055116 | F51: =E51 -> 99.055116 | G51: =F51 -> 99.055116 | H51: =G51 -> 99.055116 | I51: =H51 -> 99.055116 | J51: =I51 -> 99.055116 | K51: =J51 -> 99.055116 | ... N51: =M51 -> 99.055116 | O51: =SUM(C51:N51) -> 1188.6614 | P51: =N51*(1+Panel!$B$43) -> 110.64456 | Q51: =P51 -> 110.64456 | R51: =Q51 -> 110.64456 | S51: =R51 -> 110.64456 | T51: =S51 -> 110.64456 | U51: =T51 -> 110.64456 | V51: =U51 -> 110.64456 | W51: =V51 -> 110.64456 | X51: =W51 -> 110.64456 | ... AA51: =Z51 -> 110.64456 | AB51: =SUM(P51:AA51) -> 1327.7348 | AC51: =AA51*(1+Panel!$B$43) -> 123.58998 | AD51: =AC51 -> 123.58998 | AE51: =AD51 -> 123.58998 | AF51: =AE51 -> 123.58998 | AG51: =AF51 -> 123.58998 | AH51: =AG51 -> 123.58998 | AI51: =AH51 -> 123.58998 | AJ51: =AI51 -> 123.58998 | AK51: =AJ51 -> 123.58998 | ... AN51: =AM51 -> 123.58998 | AO51: =SUM(AC51:AN51) -> 1483.0797 | AP51: =AO51*(1+Panel!$B$43) -> 1656.6001 | AQ51: =AP51*(1+Panel!$B$43) -> 1850.4223 | AR51: =AQ51*(1+Panel!$B$43) -> 2066.9217 | AS51: =AR51*(1+Panel!$B$43) -> 2308.7515 | AT51: =AS51*(1+Panel!$B$43) -> 2578.8755 | AU51: =AT51*(1+Panel!$B$43) -> 2880.6039 | AV51: =AU51*(1+Panel!$B$43) -> 3217.6345 | AW51: =AV51*(1+Panel!$B$43) -> 3594.0978 | ... BC51: =BB51*(1+Panel!$B$43) -> 6980.86
B52: Итого | C52: =SUM(C51) -> 99.055116 | D52: =SUM(D51) -> 99.055116 | E52: =SUM(E51) -> 99.055116 | F52: =SUM(F51) -> 99.055116 | G52: =SUM(G51) -> 99.055116 | H52: =SUM(H51) -> 99.055116 | I52: =SUM(I51) -> 99.055116 | J52: =SUM(J51) -> 99.055116 | ... BC52: =SUM(BC51) -> 6980.86
A55: РАСЧЕТ НАЛОГА НА ИМУЩЕСТВО
A57: в тыс.тенге, если не указано иное
B58: Наименование | C58: янв | D58: фев | E58: мар | F58: апр | G58: май | H58: июн | I58: июл | J58: авг | K58: сен | L58: окт | M58: ноя | N58: дек | O58: 2026 | P58: янв | Q58: фев | R58: мар | S58: апр | T58: май | U58: июн | V58: июл | W58: авг | X58: сен | Y58: окт | Z58: ноя | AA58: дек | AB58: 2027 | AC58: янв | AD58: фев | AE58: мар | AF58: апр | AG58: май | AH58: июн | AI58: июл | AJ58: авг | AK58: сен | AL58: окт | AM58: ноя | AN58: дек | AO58: 2028 | AP58: 2029 | AQ58: 2030 | AR58: 2031 | AS58: 2032 | AT58: 2033 | AU58: 2034 | AV58: 2035 | AW58: 2036 | AX58: 2037 | AY58: 2038 | AZ58: 2039 | BA58: 2040 | BB58: 2041 | BC58: 2042
A59: 1.1 | B59: Налог на имущество | C59: =O59/12 -> 1008.2866 | D59: =C59 -> 1008.2866 | E59: =D59 -> 1008.2866 | F59: =E59 -> 1008.2866 | G59: =F59 -> 1008.2866 | H59: =G59 -> 1008.2866 | I59: =H59 -> 1008.2866 | J59: =I59 -> 1008.2866 | K59: =J59 -> 1008.2866 | ... N59: =M59 -> 1008.2866 | O59: ='Произв.затраты'!H134 -> 12099.439 | P59: =AB59/12 -> 936.01155 | Q59: =P59 -> 936.01155 | R59: =Q59 -> 936.01155 | S59: =R59 -> 936.01155 | T59: =S59 -> 936.01155 | U59: =T59 -> 936.01155 | V59: =U59 -> 936.01155 | W59: =V59 -> 936.01155 | X59: =W59 -> 936.01155 | ... AA59: =Z59 -> 936.01155 | AB59: ='Произв.затраты'!H146 -> 11232.139 | AC59: =AO59/12 -> 863.73654 | AD59: =AC59 -> 863.73654 | AE59: =AD59 -> 863.73654 | AF59: =AE59 -> 863.73654 | AG59: =AF59 -> 863.73654 | AH59: =AG59 -> 863.73654 | AI59: =AH59 -> 863.73654 | AJ59: =AI59 -> 863.73654 | AK59: =AJ59 -> 863.73654 | ... AN59: =AM59 -> 863.73654 | AO59: ='Произв.затраты'!H158 -> 10364.838 | AP59: ='Произв.затраты'!H170 -> 9497.5382 | AQ59: ='Произв.затраты'!H182 -> 8630.238 | AR59: ='Произв.затраты'!H194 -> 7762.9378 | AS59: ='Произв.затраты'!H206 -> 6895.6377 | AT59: ='Произв.затраты'!H218 -> 6028.3375 | AU59: ='Произв.затраты'!H230 -> 5161.0373 | AV59: ='Произв.затраты'!H242 -> 4293.7371 | AW59: ='Произв.затраты'!H254 -> 3426.4369 | AX59: ='Произв.затраты'!H266 -> 2559.1367 | AY59: ='Произв.затраты'!H278 -> 1691.8365 | AZ59: ='Произв.затраты'!H290 -> 824.5363 | BA59: ='Произв.затраты'!H302 -> 97.014767 | BB59: ='Произв.затраты'!H314 -> 0 | BC59: ='Произв.затраты'!H326 -> 0
B60: Итого | C60: =SUM(C59) -> 1008.2866 | D60: =SUM(D59) -> 1008.2866 | E60: =SUM(E59) -> 1008.2866 | F60: =SUM(F59) -> 1008.2866 | G60: =SUM(G59) -> 1008.2866 | H60: =SUM(H59) -> 1008.2866 | I60: =SUM(I59) -> 1008.2866 | J60: =SUM(J59) -> 1008.2866 | ... BC60: =SUM(BC59) -> 0
A64: РАСЧЕТ ЗЕМЕЛЬНОГО НАЛОГА
A66: 1 | B66: Ставка налога ГЭС-2 | C66: 2069.9 | D66: тенгега
A67: 2 | B67: Площадь участка ГЭС-2 | C67: 50 | D67: га
A69: в тыс.тенге, если не указано иное
A70: № | B70: Наименование | C70: янв | D70: фев | E70: мар | F70: апр | G70: май | H70: июн | I70: июл | J70: авг | K70: сен | L70: окт | M70: ноя | N70: дек | O70: 2026 | P70: янв | Q70: фев | R70: мар | S70: апр | T70: май | U70: июн | V70: июл | W70: авг | X70: сен | Y70: окт | Z70: ноя | AA70: дек | AB70: 2027 | AC70: янв | AD70: фев | AE70: мар | AF70: апр | AG70: май | AH70: июн | AI70: июл | AJ70: авг | AK70: сен | AL70: окт | AM70: ноя | AN70: дек | AO70: 2028 | AP70: 2029 | AQ70: 2030 | AR70: 2031 | AS70: 2032 | AT70: 2033 | AU70: 2034 | AV70: 2035 | AW70: 2036 | AX70: 2037 | AY70: 2038 | AZ70: 2039 | BA70: 2040 | BB70: 2041 | BC70: 2042
A71: 1.1 | B71: Земельный налог | C71: =C66*C67/1000/12 -> 8.6245833 | D71: =C71 -> 8.6245833 | E71: =D71 -> 8.6245833 | F71: =E71 -> 8.6245833 | G71: =F71 -> 8.6245833 | H71: =G71 -> 8.6245833 | I71: =H71 -> 8.6245833 | J71: =I71 -> 8.6245833 | K71: =J71 -> 8.6245833 | ... N71: =M71 -> 8.6245833 | O71: =SUM(C71:N71) -> 103.495 | P71: =N71 -> 8.6245833 | Q71: =P71 -> 8.6245833 | R71: =Q71 -> 8.6245833 | S71: =R71 -> 8.6245833 | T71: =S71 -> 8.6245833 | U71: =T71 -> 8.6245833 | V71: =U71 -> 8.6245833 | W71: =V71 -> 8.6245833 | X71: =W71 -> 8.6245833 | ... AA71: =Z71 -> 8.6245833 | AB71: =SUM(P71:AA71) -> 103.495 | AC71: =AA71 -> 8.6245833 | AD71: =AC71 -> 8.6245833 | AE71: =AD71 -> 8.6245833 | AF71: =AE71 -> 8.6245833 | AG71: =AF71 -> 8.6245833 | AH71: =AG71 -> 8.6245833 | AI71: =AH71 -> 8.6245833 | AJ71: =AI71 -> 8.6245833 | AK71: =AJ71 -> 8.6245833 | ... AN71: =AM71 -> 8.6245833 | AO71: =SUM(AC71:AN71) -> 103.495 | AP71: =AO71 -> 103.495 | AQ71: =AP71 -> 103.495 | AR71: =AQ71 -> 103.495 | AS71: =AR71 -> 103.495 | AT71: =AS71 -> 103.495 | AU71: =AT71 -> 103.495 | AV71: =AU71 -> 103.495 | AW71: =AV71 -> 103.495 | ... BC71: =BB71 -> 103.495
B72: Итого | C72: =SUM(C71) -> 8.6245833 | D72: =SUM(D71) -> 8.6245833 | E72: =SUM(E71) -> 8.6245833 | F72: =SUM(F71) -> 8.6245833 | G72: =SUM(G71) -> 8.6245833 | H72: =SUM(H71) -> 8.6245833 | I72: =SUM(I71) -> 8.6245833 | J72: =SUM(J71) -> 8.6245833 | ... BC72: =SUM(BC71) -> 103.495
A75: РАСЧЕТ ПЛАТЫ ЗА ПОЛЬЗОВАНИЕ ВОДНЫМИ ИСТОЧНИКАМИ
A77: Ставка | C77: 0.0731 | D77: тенге/кВтч | E77: Об установлении ставок платы за пользование водными ресурсами из поверхностных источников Алматинской области/ Решение Алматинского областного маслихата от 25 июля 2018 года No 34-176.
A79: в тыс. тенге, если не указано иное
A80: № | B80: Наименование | C80: янв | D80: фев | E80: мар | F80: апр | G80: май | H80: июн | I80: июл | J80: авг | K80: сен | L80: окт | M80: ноя | N80: дек | O80: 2026 | P80: янв | Q80: фев | R80: мар | S80: апр | T80: май | U80: июн | V80: июл | W80: авг | X80: сен | Y80: окт | Z80: ноя | AA80: дек | AB80: 2027 | AC80: янв | AD80: фев | AE80: мар | AF80: апр | AG80: май | AH80: июн | AI80: июл | AJ80: авг | AK80: сен | AL80: окт | AM80: ноя | AN80: дек | AO80: 2028 | AP80: 2029 | AQ80: 2030 | AR80: 2031 | AS80: 2032 | AT80: 2033 | AU80: 2034 | AV80: 2035 | AW80: 2036 | AX80: 2037 | AY80: 2038 | AZ80: 2039 | BA80: 2040 | BB80: 2041 | BC80: 2042
A81: 1 | B81: Плата за пользование водными ресурсами | C81: =$C$77*('Выручка'!E46)*1000 -> 101.31772 | D81: =$C$77*('Выручка'!F46)*1000 -> 85.999872 | E81: =$C$77*('Выручка'!G46)*1000 -> 135.12472 | F81: =$C$77*('Выручка'!H46)*1000 -> 79.690879 | G81: =$C$77*('Выручка'!I46)*1000 -> 181.11764 | H81: =$C$77*('Выручка'!J46)*1000 -> 203.77735 | I81: =$C$77*('Выручка'!K46)*1000 -> 253.94777 | J81: =$C$77*('Выручка'!L46)*1000 -> 253.94777 | ... N81: =$C$77*('Выручка'!P46)*1000 -> 104.39677 | O81: =SUM(C81:N81) -> 1915.9618 | P81: =C81 -> 101.31772 | Q81: =D81 -> 85.999872 | R81: =E81 -> 135.12472 | S81: =F81 -> 79.690879 | T81: =G81 -> 181.11764 | U81: =H81 -> 203.77735 | V81: =I81 -> 253.94777 | W81: =J81 -> 253.94777 | ... AA81: =N81 -> 104.39677 | AB81: =SUM(P81:AA81) -> 1915.9618 | AC81: =P81 -> 101.31772 | AD81: =Q81 -> 85.999872 | AE81: =R81 -> 135.12472 | AF81: =S81 -> 79.690879 | AG81: =T81 -> 181.11764 | AH81: =U81 -> 203.77735 | AI81: =V81 -> 253.94777 | AJ81: =W81 -> 253.94777 | ... AN81: =AA81 -> 104.39677 | AO81: =SUM(AC81:AN81) -> 1915.9618 | AP81: =AO81 -> 1915.9618 | AQ81: =AP81 -> 1915.9618 | AR81: =AQ81 -> 1915.9618 | AS81: =AR81 -> 1915.9618 | AT81: =AS81 -> 1915.9618 | AU81: =AT81 -> 1915.9618 | AV81: =AU81 -> 1915.9618 | AW81: =AV81 -> 1915.9618 | ... BC81: =BB81 -> 1915.9618
B82: Итого | C82: =SUM(C81) -> 101.31772 | D82: =SUM(D81) -> 85.999872 | E82: =SUM(E81) -> 135.12472 | F82: =SUM(F81) -> 79.690879 | G82: =SUM(G81) -> 181.11764 | H82: =SUM(H81) -> 203.77735 | I82: =SUM(I81) -> 253.94777 | J82: =SUM(J81) -> 253.94777 | ... BC82: =SUM(BC81) -> 1915.9618
A85: РАСЧЕТ РАСХОДА НА УСЛУГИ ДИСПЕТЧЕРИЗАЦИИ
A87: Стоимость услуг | C87: 0.23350427 | D87: тенге/кВт | E87: Норматив на основе эксплуатации
A89: в тыс. тенге, если не указано иное
A90: № | B90: Наименование | C90: янв | D90: фев | E90: мар | F90: апр | G90: май | H90: июн | I90: июл | J90: авг | K90: сен | L90: окт | M90: ноя | N90: дек | O90: 2026 | P90: янв | Q90: фев | R90: мар | S90: апр | T90: май | U90: июн | V90: июл | W90: авг | X90: сен | Y90: окт | Z90: ноя | AA90: дек | AB90: 2027 | AC90: янв | AD90: фев | AE90: мар | AF90: апр | AG90: май | AH90: июн | AI90: июл | AJ90: авг | AK90: сен | AL90: окт | AM90: ноя | AN90: дек | AO90: 2028 | AP90: 2029 | AQ90: 2030 | AR90: 2031 | AS90: 2032 | AT90: 2033 | AU90: 2034 | AV90: 2035 | AW90: 2036 | AX90: 2037 | AY90: 2038 | AZ90: 2039 | BA90: 2040 | BB90: 2041 | BC90: 2042
A91: 1 | B91: Услуги диспетчеризации | C91: =($C$87*('Выручка'!E46)*1000)*(1+Panel!$B$43)*(1+Panel!$B$43) -> 403.80267 | D91: =($C$87*('Выручка'!F46)*1000)*(1+Panel!$B$43)*(1+Panel!$B$43)*(1+Panel!$B$43) -> 382.8554 | E91: =($C$87*('Выручка'!G46)*1000)*(1+Panel!$B$43)*(1+Panel!$B$43)*(1+Panel!$B$43) -> 601.55007 | F91: =($C$87*('Выручка'!H46)*1000)*(1+Panel!$B$43)*(1+Panel!$B$43)*(1+Panel!$B$43) -> 354.76893 | G91: =($C$87*('Выручка'!I46)*1000)*(1+Panel!$B$43)*(1+Panel!$B$43)*(1+Panel!$B$43) -> 806.30195 | H91: =($C$87*('Выручка'!J46)*1000)*(1+Panel!$B$43)*(1+Panel!$B$43)*(1+Panel!$B$43) -> 907.17877 | I91: =($C$87*('Выручка'!K46)*1000)*(1+Panel!$B$43)*(1+Panel!$B$43)*(1+Panel!$B$43) -> 1130.5281 | J91: =($C$87*('Выручка'!L46)*1000)*(1+Panel!$B$43)*(1+Panel!$B$43)*(1+Panel!$B$43) -> 1130.5281 | K91: =($C$87*('Выручка'!M46)*1000)*(1+Panel!$B$43)*(1+Panel!$B$43)*(1+Panel!$B$43) -> 934.05831 | ... N91: =($C$87*('Выручка'!P46)*1000)*(1+Panel!$B$43)*(1+Panel!$B$43)*(1+Panel!$B$43) -> 464.75496 | O91: =SUM(C91:N91) -> 8482.26 | P91: =(C91)*(1+Panel!$B$43) -> 451.04758 | Q91: =(D91)*(1+Panel!$B$43) -> 427.64948 | R91: =(E91)*(1+Panel!$B$43) -> 671.93142 | S91: =(F91)*(1+Panel!$B$43) -> 396.2769 | T91: =(G91)*(1+Panel!$B$43) -> 900.63928 | U91: =(H91)*(1+Panel!$B$43) -> 1013.3187 | V91: =(I91)*(1+Panel!$B$43) -> 1262.7999 | W91: =(J91)*(1+Panel!$B$43) -> 1262.7999 | ... AA91: =(N91)*(1+Panel!$B$43) -> 519.13129 | AB91: =SUM(P91:AA91) -> 9474.6844 | AC91: =(P91)*(1+Panel!$B$43) -> 503.82014 | AD91: =(Q91)*(1+Panel!$B$43) -> 477.68447 | AE91: =(R91)*(1+Panel!$B$43) -> 750.5474 | AF91: =(S91)*(1+Panel!$B$43) -> 442.6413 | AG91: =(T91)*(1+Panel!$B$43) -> 1006.0141 | AH91: =(U91)*(1+Panel!$B$43) -> 1131.877 | AI91: =(V91)*(1+Panel!$B$43) -> 1410.5475 | AJ91: =(W91)*(1+Panel!$B$43) -> 1410.5475 | ... AN91: =(AA91)*(1+Panel!$B$43) -> 579.86965 | AO91: =SUM(AC91:AN91) -> 10583.222 | AP91: =AO91*(1+Panel!$B$43) -> 11821.459 | AQ91: =AP91*(1+Panel!$B$43) -> 13204.57 | AR91: =AQ91*(1+Panel!$B$43) -> 14749.505 | AS91: =AR91*(1+Panel!$B$43) -> 16475.197 | AT91: =AS91*(1+Panel!$B$43) -> 18402.795 | AU91: =AT91*(1+Panel!$B$43) -> 20555.922 | AV91: =AU91*(1+Panel!$B$43) -> 22960.965 | AW91: =AV91*(1+Panel!$B$43) -> 25647.398 | ... BC91: =BB91*(1+Panel!$B$43) -> 49815.254
B92: Итого | C92: =SUM(C91) -> 403.80267 | D92: =SUM(D91) -> 382.8554 | E92: =SUM(E91) -> 601.55007 | F92: =SUM(F91) -> 354.76893 | G92: =SUM(G91) -> 806.30195 | H92: =SUM(H91) -> 907.17877 | I92: =SUM(I91) -> 1130.5281 | J92: =SUM(J91) -> 1130.5281 | ... BC92: =SUM(BC91) -> 49815.254
A95: Оперативно-техническое и диспетчерское обслуживание
B97: Норматив затрат | C97: =2000/(1+Panel!B26) -> 1724.1379 | D97: тыс.тенге/мес.
A99: в тыс. тенге, если не указано иное
A100: № | B100: Наименование | C100: янв | D100: фев | E100: мар | F100: апр | G100: май | H100: июн | I100: июл | J100: авг | K100: сен | L100: окт | M100: ноя | N100: дек | O100: 2026 | P100: янв | Q100: фев | R100: мар | S100: апр | T100: май | U100: июн | V100: июл | W100: авг | X100: сен | Y100: окт | Z100: ноя | AA100: дек | AB100: 2027 | AC100: янв | AD100: фев | AE100: мар | AF100: апр | AG100: май | AH100: июн | AI100: июл | AJ100: авг | AK100: сен | AL100: окт | AM100: ноя | AN100: дек | AO100: 2028 | AP100: 2029 | AQ100: 2030 | AR100: 2031 | AS100: 2032 | AT100: 2033 | AU100: 2034 | AV100: 2035 | AW100: 2036 | AX100: 2037 | AY100: 2038 | AZ100: 2039 | BA100: 2040 | BB100: 2041 | BC100: 2042
A101: 1 | B101: Оперативно-техническое и диспетчерское обслуживание | C101: =C97*(1+Panel!$B$43)*(1+Panel!$B$43) -> 2151.1879 | D101: =C101 -> 2151.1879 | E101: =D101 -> 2151.1879 | F101: =E101 -> 2151.1879 | G101: =F101 -> 2151.1879 | H101: =G101 -> 2151.1879 | I101: =H101 -> 2151.1879 | J101: =I101 -> 2151.1879 | K101: =J101 -> 2151.1879 | ... N101: =M101 -> 2151.1879 | O101: =SUM(C101:N101) -> 25814.255 | P101: =C101*(1+Panel!$B$43) -> 2402.8769 | Q101: =P101 -> 2402.8769 | R101: =Q101 -> 2402.8769 | S101: =R101 -> 2402.8769 | T101: =S101 -> 2402.8769 | U101: =T101 -> 2402.8769 | V101: =U101 -> 2402.8769 | W101: =V101 -> 2402.8769 | X101: =W101 -> 2402.8769 | ... AA101: =Z101 -> 2402.8769 | AB101: =SUM(P101:AA101) -> 28834.523 | AC101: =P101*(1+Panel!$B$43) -> 2684.0135 | AD101: =AC101 -> 2684.0135 | AE101: =AD101 -> 2684.0135 | AF101: =AE101 -> 2684.0135 | AG101: =AF101 -> 2684.0135 | AH101: =AG101 -> 2684.0135 | AI101: =AH101 -> 2684.0135 | AJ101: =AI101 -> 2684.0135 | AK101: =AJ101 -> 2684.0135 | ... AN101: =AM101 -> 2684.0135 | AO101: =SUM(AC101:AN101) -> 32208.162 | AP101: =AO101*(1+Panel!$B$43) -> 35976.517 | AQ101: =AP101*(1+Panel!$B$43) -> 40185.77 | AR101: =AQ101*(1+Panel!$B$43) -> 44887.505 | AS101: =AR101*(1+Panel!$B$43) -> 50139.343 | AT101: =AS101*(1+Panel!$B$43) -> 56005.646 | AU101: =AT101*(1+Panel!$B$43) -> 62558.307 | AV101: =AU101*(1+Panel!$B$43) -> 69877.628 | AW101: =AV101*(1+Panel!$B$43) -> 78053.311 | ... BC101: =BB101*(1+Panel!$B$43) -> 151603.9
B102: Итого | C102: =SUM(C101) -> 2151.1879 | D102: =SUM(D101) -> 2151.1879 | E102: =SUM(E101) -> 2151.1879 | F102: =SUM(F101) -> 2151.1879 | G102: =SUM(G101) -> 2151.1879 | H102: =SUM(H101) -> 2151.1879 | I102: =SUM(I101) -> 2151.1879 | J102: =SUM(J101) -> 2151.1879 | ... BC102: =SUM(BC101) -> 151603.9
A106: НЕПРЕДВИДЕННЫЕ РАСХОДЫ
B108: Норматив затрат | C108: 0.005
A110: в тыс. тенге, если не указано иное
A111: № | B111: Наименование | C111: янв | D111: фев | E111: мар | F111: апр | G111: май | H111: июн | I111: июл | J111: авг | K111: сен | L111: окт | M111: ноя | N111: дек | O111: 2026 | P111: янв | Q111: фев | R111: мар | S111: апр | T111: май | U111: июн | V111: июл | W111: авг | X111: сен | Y111: окт | Z111: ноя | AA111: дек | AB111: 2027 | AC111: янв | AD111: фев | AE111: мар | AF111: апр | AG111: май | AH111: июн | AI111: июл | AJ111: авг | AK111: сен | AL111: окт | AM111: ноя | AN111: дек | AO111: 2028 | AP111: 2029 | AQ111: 2030 | AR111: 2031 | AS111: 2032 | AT111: 2033 | AU111: 2034 | AV111: 2035 | AW111: 2036 | AX111: 2037 | AY111: 2038 | AZ111: 2039 | BA111: 2040 | BB111: 2041 | BC111: 2042
A112: 1 | B112: Непредвиденные расходы | C112: =$C$108*'Выручка'!C13 -> 145.0465 | D112: =$C$108*'Выручка'!D13 -> 123.11746 | E112: =$C$108*'Выручка'!E13 -> 193.44463 | F112: =$C$108*'Выручка'!F13 -> 114.08551 | G112: =$C$108*'Выручка'!G13 -> 259.28811 | H112: =$C$108*'Выручка'!H13 -> 291.72777 | I112: =$C$108*'Выручка'!I13 -> 363.55177 | J112: =$C$108*'Выручка'!J13 -> 363.55177 | ... BC112: =$C$108*'Выручка'!BC13 -> 12421.436
B113: Итого | C113: =SUM(C112) -> 145.0465 | D113: =SUM(D112) -> 123.11746 | E113: =SUM(E112) -> 193.44463 | F113: =SUM(F112) -> 114.08551 | G113: =SUM(G112) -> 259.28811 | H113: =SUM(H112) -> 291.72777 | I113: =SUM(I112) -> 363.55177 | J113: =SUM(J112) -> 363.55177 | ... BC113: =SUM(BC112) -> 12421.436
A116: РАСЧЕТ НАЛОГА НА ИМУЩЕСТВО
A118: Ставка налога на имущество | D118: 0.015
A120: в тыс. тенге, если не указано иное
A121: Год | B121: Месяц | C121: Остаточная стоимость на начало месяца | D121: Ежемесячные аморт. отч. по произв. зданию | E121: Приход произв. помещения | F121: Остаточная стоимость на конец месяца | G121: Среднегодовая остаточная стоимость | H121: Ежегодный налог на имущество
B122: 1 | C122: ='Инвестиции'!C11/(1+Panel!B26) -> 835539.26 | D122: =F31*('Инвестиции'!C11/SUM('Инвестиции'!C11:C14)) -> 4818.3344 | E122: 0 | F122: =C122-D122+E122 -> 830720.93
B123: 2 | C123: =F122 -> 830720.93 | D123: =D122 -> 4818.3344 | E123: 0 | F123: =C123-D123+E123 -> 825902.59
B124: 3 | C124: =F123 -> 825902.59 | D124: =D123 -> 4818.3344 | E124: 0 | F124: =C124-D124+E124 -> 821084.26
B125: 4 | C125: =F124 -> 821084.26 | D125: =D124 -> 4818.3344 | E125: 0 | F125: =C125-D125+E125 -> 816265.92
B126: 5 | C126: =F125 -> 816265.92 | D126: =D125 -> 4818.3344 | E126: 0 | F126: =C126-D126+E126 -> 811447.59
B127: 6 | C127: =F126 -> 811447.59 | D127: =D126 -> 4818.3344 | E127: 0 | F127: =C127-D127+E127 -> 806629.25
B128: 7 | C128: =F127 -> 806629.25 | D128: =D127 -> 4818.3344 | E128: 0 | F128: =C128-D128+E128 -> 801810.92
B129: 8 | C129: =F128 -> 801810.92 | D129: =D128 -> 4818.3344 | E129: 0 | F129: =C129-D129+E129 -> 796992.59
B130: 9 | C130: =F129 -> 796992.59 | D130: =D129 -> 4818.3344 | E130: 0 | F130: =C130-D130+E130 -> 792174.25
B131: 10 | C131: =F130 -> 792174.25 | D131: =D130 -> 4818.3344 | E131: 0 | F131: =C131-D131+E131 -> 787355.92
B132: 11 | C132: =F131 -> 787355.92 | D132: =D131 -> 4818.3344 | E132: 0 | F132: =C132-D132+E132 -> 782537.58
B133: 12 | C133: =F132 -> 782537.58 | D133: =D132 -> 4818.3344 | E133: 0 | F133: =C133-D133+E133 -> 777719.25
A134: 2026 | B134: 1 | C134: =F133 -> 777719.25 | D134: =D133 -> 4818.3344 | E134: 0 | F134: =C134-D134+E134 -> 772900.91 | G134: =SUM(C122:C134)/13 -> 806629.25 | H134: =G134*$D$118 -> 12099.439
B135: 2 | C135: =F134 -> 772900.91 | D135: =D134 -> 4818.3344 | E135: 0 | F135: =C135-D135+E135 -> 768082.58
B136: 3 | C136: =F135 -> 768082.58 | D136: =D135 -> 4818.3344 | E136: 0 | F136: =C136-D136+E136 -> 763264.24
B137: 4 | C137: =F136 -> 763264.24 | D137: =D136 -> 4818.3344 | E137: 0 | F137: =C137-D137+E137 -> 758445.91
B138: 5 | C138: =F137 -> 758445.91 | D138: =D137 -> 4818.3344 | E138: 0 | F138: =C138-D138+E138 -> 753627.58
B139: 6 | C139: =F138 -> 753627.58 | D139: =D138 -> 4818.3344 | E139: 0 | F139: =C139-D139+E139 -> 748809.24
B140: 7 | C140: =F139 -> 748809.24 | D140: =D139 -> 4818.3344 | E140: 0 | F140: =C140-D140+E140 -> 743990.91
B141: 8 | C141: =F140 -> 743990.91 | D141: =D140 -> 4818.3344 | E141: 0 | F141: =C141-D141+E141 -> 739172.57
B142: 9 | C142: =F141 -> 739172.57 | D142: =D141 -> 4818.3344 | E142: 0 | F142: =C142-D142+E142 -> 734354.24
B143: 10 | C143: =F142 -> 734354.24 | D143: =D142 -> 4818.3344 | E143: 0 | F143: =C143-D143+E143 -> 729535.9
B144: 11 | C144: =F143 -> 729535.9 | D144: =D143 -> 4818.3344 | E144: 0 | F144: =C144-D144+E144 -> 724717.57
...

Sheet Адм.затраты
A1: =Panel!A1
A2: =Panel!A2 -> Строительство ГЭС -5 МВТ
A4: АДМИНИСТРАТИВНЫЕ ИЗДЕРЖКИ
A6: в тыс.тенге, если не указано иное
A7: № | B7: Элементы затрат | C7: янв | D7: фев | E7: мар | F7: апр | G7: май | H7: июн | I7: июл | J7: авг | K7: сен | L7: окт | M7: ноя | N7: дек | O7: 2026 | P7: янв | Q7: фев | R7: мар | S7: апр | T7: май | U7: июн | V7: июл | W7: авг | X7: сен | Y7: окт | Z7: ноя | AA7: дек | AB7: 2027 | AC7: янв | AD7: фев | AE7: мар | AF7: апр | AG7: май | AH7: июн | AI7: июл | AJ7: авг | AK7: сен | AL7: окт | AM7: ноя | AN7: дек | AO7: 2028 | AP7: 2029 | AQ7: 2030 | AR7: 2031 | AS7: 2032 | AT7: 2033 | AU7: 2034 | AV7: 2035 | AW7: 2036 | AX7: 2037 | AY7: 2038 | AZ7: 2039 | BA7: 2040 | BB7: 2041 | BC7: 2042
A8: 1.1 | B8: Гос.пошлина | C8: 1.3708333 | D8: 1.3708333 | E8: 1.3708333 | F8: 1.3708333 | G8: 1.3708333 | H8: 1.3708333 | I8: 1.3708333 | J8: 1.3708333 | K8: 1.3708333 | L8: 1.3708333 | M8: 1.3708333 | N8: 1.3708333 | O8: =SUM(C8:N8) -> 16.45 | P8: =O8/12 -> 1.3708333 | Q8: =P8 -> 1.3708333 | R8: =Q8 -> 1.3708333 | S8: =R8 -> 1.3708333 | T8: =S8 -> 1.3708333 | U8: =T8 -> 1.3708333 | V8: =U8 -> 1.3708333 | W8: =V8 -> 1.3708333 | X8: =W8 -> 1.3708333 | ... AA8: =Z8 -> 1.3708333 | AB8: =SUM(P8:AA8) -> 16.45 | AC8: =AB8/12 -> 1.3708333 | AD8: =AC8 -> 1.3708333 | AE8: =AD8 -> 1.3708333 | AF8: =AE8 -> 1.3708333 | AG8: =AF8 -> 1.3708333 | AH8: =AG8 -> 1.3708333 | AI8: =AH8 -> 1.3708333 | AJ8: =AI8 -> 1.3708333 | AK8: =AJ8 -> 1.3708333 | ... AN8: =AM8 -> 1.3708333 | AO8: =SUM(AC8:AN8) -> 16.45 | AP8: =AO8 -> 16.45 | AQ8: =AP8 -> 16.45 | AR8: =AQ8 -> 16.45 | AS8: =AR8 -> 16.45 | AT8: =AS8 -> 16.45 | AU8: =AT8 -> 16.45 | AV8: =AU8 -> 16.45 | AW8: =AV8 -> 16.45 | ... BC8: =BB8 -> 16.45
A9: 1.2 | B9: Гос.регистрация | C9: 2.1744167 | D9: 2.1744167 | E9: 2.1744167 | F9: 2.1744167 | G9: 2.1744167 | H9: 2.1744167 | I9: 2.1744167 | J9: 2.1744167 | K9: 2.1744167 | L9: 2.1744167 | M9: 2.1744167 | N9: 2.1744167 | O9: =SUM(C9:N9) -> 26.093 | P9: =O9/12 -> 2.1744167 | Q9: =P9 -> 2.1744167 | R9: =Q9 -> 2.1744167 | S9: =R9 -> 2.1744167 | T9: =S9 -> 2.1744167 | U9: =T9 -> 2.1744167 | V9: =U9 -> 2.1744167 | W9: =V9 -> 2.1744167 | X9: =W9 -> 2.1744167 | ... AA9: =Z9 -> 2.1744167 | AB9: =SUM(P9:AA9) -> 26.093 | AC9: =AB9/12 -> 2.1744167 | AD9: =AC9 -> 2.1744167 | AE9: =AD9 -> 2.1744167 | AF9: =AE9 -> 2.1744167 | AG9: =AF9 -> 2.1744167 | AH9: =AG9 -> 2.1744167 | AI9: =AH9 -> 2.1744167 | AJ9: =AI9 -> 2.1744167 | AK9: =AJ9 -> 2.1744167 | ... AN9: =AM9 -> 2.1744167 | AO9: =SUM(AC9:AN9) -> 26.093 | AP9: =AO9 -> 26.093 | AQ9: =AP9 -> 26.093 | AR9: =AQ9 -> 26.093 | AS9: =AR9 -> 26.093 | AT9: =AS9 -> 26.093 | AU9: =AT9 -> 26.093 | AV9: =AU9 -> 26.093 | AW9: =AV9 -> 26.093 | ... BC9: =BB9 -> 26.093
A10: 1.3 | B10: Заправка картриджа | C10: 1.6666667 | D10: 1.6666667 | E10: 1.6666667 | F10: 1.6666667 | G10: 1.6666667 | H10: 1.6666667 | I10: 1.6666667 | J10: 1.6666667 | K10: 1.6666667 | L10: 1.6666667 | M10: 1.6666667 | N10: 1.6666667 | O10: =SUM(C10:N10) -> 20 | P10: =(O10/12)*(1+Panel!$B$43) -> 1.8616667 | Q10: =P10 -> 1.8616667 | R10: =Q10 -> 1.8616667 | S10: =R10 -> 1.8616667 | T10: =S10 -> 1.8616667 | U10: =T10 -> 1.8616667 | V10: =U10 -> 1.8616667 | W10: =V10 -> 1.8616667 | X10: =W10 -> 1.8616667 | ... AA10: =Z10 -> 1.8616667 | AB10: =SUM(P10:AA10) -> 22.34 | AC10: =(AB10/12)*(1+Panel!$B$43) -> 2.0794817 | AD10: =AC10 -> 2.0794817 | AE10: =AD10 -> 2.0794817 | AF10: =AE10 -> 2.0794817 | AG10: =AF10 -> 2.0794817 | AH10: =AG10 -> 2.0794817 | AI10: =AH10 -> 2.0794817 | AJ10: =AI10 -> 2.0794817 | AK10: =AJ10 -> 2.0794817 | ... AN10: =AM10 -> 2.0794817 | AO10: =SUM(AC10:AN10) -> 24.95378 | AP10: =(AO10)*(1+Panel!$B$43) -> 27.873372 | AQ10: =(AP10)*(1+Panel!$B$43) -> 31.134557 | AR10: =(AQ10)*(1+Panel!$B$43) -> 34.7773 | AS10: =(AR10)*(1+Panel!$B$43) -> 38.846244 | AT10: =(AS10)*(1+Panel!$B$43) -> 43.391255 | AU10: =(AT10)*(1+Panel!$B$43) -> 48.468031 | AV10: =(AU10)*(1+Panel!$B$43) -> 54.138791 | AW10: =(AV10)*(1+Panel!$B$43) -> 60.47303 | ... BC10: =(BB10)*(1+Panel!$B$43) -> 117.4575
A11: 1.4 | B11: Изготовление и цветная распечатка | C11: 0.27833333 | D11: 0.27833333 | E11: 0.27833333 | F11: 0.27833333 | G11: 0.27833333 | H11: 0.27833333 | I11: 0.27833333 | J11: 0.27833333 | K11: 0.27833333 | L11: 0.27833333 | M11: 0.27833333 | N11: 0.27833333 | O11: =SUM(C11:N11) -> 3.34 | P11: =(O11/12)*(1+Panel!$B$43) -> 0.31089833 | Q11: =P11 -> 0.31089833 | R11: =Q11 -> 0.31089833 | S11: =R11 -> 0.31089833 | T11: =S11 -> 0.31089833 | U11: =T11 -> 0.31089833 | V11: =U11 -> 0.31089833 | W11: =V11 -> 0.31089833 | X11: =W11 -> 0.31089833 | ... AA11: =Z11 -> 0.31089833 | AB11: =SUM(P11:AA11) -> 3.73078 | AC11: =(AB11/12)*(1+Panel!$B$43) -> 0.34727344 | AD11: =AC11 -> 0.34727344 | AE11: =AD11 -> 0.34727344 | AF11: =AE11 -> 0.34727344 | AG11: =AF11 -> 0.34727344 | AH11: =AG11 -> 0.34727344 | AI11: =AH11 -> 0.34727344 | AJ11: =AI11 -> 0.34727344 | AK11: =AJ11 -> 0.34727344 | ... AN11: =AM11 -> 0.34727344 | AO11: =SUM(AC11:AN11) -> 4.1672813 | AP11: =(AO11)*(1+Panel!$B$43) -> 4.6548532 | AQ11: =(AP11)*(1+Panel!$B$43) -> 5.199471 | AR11: =(AQ11)*(1+Panel!$B$43) -> 5.8078091 | AS11: =(AR11)*(1+Panel!$B$43) -> 6.4873228 | AT11: =(AS11)*(1+Panel!$B$43) -> 7.2463395 | AU11: =(AT11)*(1+Panel!$B$43) -> 8.0941612 | AV11: =(AU11)*(1+Panel!$B$43) -> 9.0411781 | AW11: =(AV11)*(1+Panel!$B$43) -> 10.098996 | ... BC11: =(BB11)*(1+Panel!$B$43) -> 19.615403
A12: 1.5 | B12: Канцелярские товары | C12: 5.1040408 | D12: 5.1040408 | E12: 5.1040408 | F12: 5.1040408 | G12: 5.1040408 | H12: 5.1040408 | I12: 5.1040408 | J12: 5.1040408 | K12: 5.1040408 | L12: 5.1040408 | M12: 5.1040408 | N12: 5.1040408 | O12: =SUM(C12:N12) -> 61.24849 | P12: =(O12/12)*(1+Panel!$B$43) -> 5.7012136 | Q12: =P12 -> 5.7012136 | R12: =Q12 -> 5.7012136 | S12: =R12 -> 5.7012136 | T12: =S12 -> 5.7012136 | U12: =T12 -> 5.7012136 | V12: =U12 -> 5.7012136 | W12: =V12 -> 5.7012136 | X12: =W12 -> 5.7012136 | ... AA12: =Z12 -> 5.7012136 | AB12: =SUM(P12:AA12) -> 68.414563 | AC12: =(AB12/12)*(1+Panel!$B$43) -> 6.3682556 | AD12: =AC12 -> 6.3682556 | AE12: =AD12 -> 6.3682556 | AF12: =AE12 -> 6.3682556 | AG12: =AF12 -> 6.3682556 | AH12: =AG12 -> 6.3682556 | AI12: =AH12 -> 6.3682556 | AJ12: =AI12 -> 6.3682556 | AK12: =AJ12 -> 6.3682556 | ... AN12: =AM12 -> 6.3682556 | AO12: =SUM(AC12:AN12) -> 76.419067 | AP12: =(AO12)*(1+Panel!$B$43) -> 85.360098 | AQ12: =(AP12)*(1+Panel!$B$43) -> 95.34723 | AR12: =(AQ12)*(1+Panel!$B$43) -> 106.50286 | AS12: =(AR12)*(1+Panel!$B$43) -> 118.96369 | AT12: =(AS12)*(1+Panel!$B$43) -> 132.88244 | AU12: =(AT12)*(1+Panel!$B$43) -> 148.42969 | AV12: =(AU12)*(1+Panel!$B$43) -> 165.79596 | AW12: =(AV12)*(1+Panel!$B$43) -> 185.19409 | ... BC12: =(BB12)*(1+Panel!$B$43) -> 359.70474
A13: 1.6 | B13: Налог на транспорт | C13: 0.52 | D13: 0.52 | E13: 0.52 | F13: 0.52 | G13: 0.52 | H13: 0.52 | I13: 0.52 | J13: 0.52 | K13: 0.52 | L13: 0.52 | M13: 0.52 | N13: 0.52 | O13: =SUM(C13:N13) -> 6.24 | P13: =O13/12 -> 0.52 | Q13: =P13 -> 0.52 | R13: =Q13 -> 0.52 | S13: =R13 -> 0.52 | T13: =S13 -> 0.52 | U13: =T13 -> 0.52 | V13: =U13 -> 0.52 | W13: =V13 -> 0.52 | X13: =W13 -> 0.52 | ... AA13: =Z13 -> 0.52 | AB13: =SUM(P13:AA13) -> 6.24 | AC13: =AB13/12 -> 0.52 | AD13: =AC13 -> 0.52 | AE13: =AD13 -> 0.52 | AF13: =AE13 -> 0.52 | AG13: =AF13 -> 0.52 | AH13: =AG13 -> 0.52 | AI13: =AH13 -> 0.52 | AJ13: =AI13 -> 0.52 | AK13: =AJ13 -> 0.52 | ... AN13: =AM13 -> 0.52 | AO13: =SUM(AC13:AN13) -> 6.24 | AP13: =AO13 -> 6.24 | AQ13: =AP13 -> 6.24 | AR13: =AQ13 -> 6.24 | AS13: =AR13 -> 6.24 | AT13: =AS13 -> 6.24 | AU13: =AT13 -> 6.24 | AV13: =AU13 -> 6.24 | AW13: =AV13 -> 6.24 | ... BC13: =BB13 -> 6.24
A14: 1.7 | B14: Отчисления ОСМС | C14: 11.111111 | D14: 11.111111 | E14: 11.111111 | F14: 11.111111 | G14: 11.111111 | H14: 11.111111 | I14: 11.111111 | J14: 11.111111 | K14: 11.111111 | L14: 11.111111 | M14: 11.111111 | N14: 11.111111 | O14: =SUM(C14:N14) -> 133.33333 | P14: =O14/12 -> 11.111111 | Q14: =P14 -> 11.111111 | R14: =Q14 -> 11.111111 | S14: =R14 -> 11.111111 | T14: =S14 -> 11.111111 | U14: =T14 -> 11.111111 | V14: =U14 -> 11.111111 | W14: =V14 -> 11.111111 | X14: =W14 -> 11.111111 | ... AA14: =Z14 -> 11.111111 | AB14: =SUM(P14:AA14) -> 133.33333 | AC14: =P48/1000 -> 22.222222 | AD14: =AC14 -> 22.222222 | AE14: =AD14 -> 22.222222 | AF14: =AE14 -> 22.222222 | AG14: =AF14 -> 22.222222 | AH14: =AG14 -> 22.222222 | AI14: =AH14 -> 22.222222 | AJ14: =AI14 -> 22.222222 | AK14: =AJ14 -> 22.222222 | ... AN14: =AM14 -> 22.222222 | AO14: =SUM(AC14:AN14) -> 266.66667 | AP14: =AO14 -> 266.66667 | AQ14: =AP14 -> 266.66667 | AR14: =AQ14 -> 266.66667 | AS14: =AR14 -> 266.66667 | AT14: =AS14 -> 266.66667 | AU14: =AT14 -> 266.66667 | AV14: =AU14 -> 266.66667 | AW14: =AV14 -> 266.66667 | ... BC14: =BB14 -> 266.66667
A15: 1.8 | B15: Оценка имущества | C15: 41.666667 | D15: 41.666667 | E15: 41.666667 | F15: 41.666667 | G15: 41.666667 | H15: 41.666667 | I15: 41.666667 | J15: 41.666667 | K15: 41.666667 | L15: 41.666667 | M15: 41.666667 | N15: 41.666667 | O15: =SUM(C15:N15) -> 500 | P15: =O15/12 -> 41.666667 | Q15: =P15 -> 41.666667 | R15: =Q15 -> 41.666667 | S15: =R15 -> 41.666667 | T15: =S15 -> 41.666667 | U15: =T15 -> 41.666667 | V15: =U15 -> 41.666667 | W15: =V15 -> 41.666667 | X15: =W15 -> 41.666667 | ... AA15: =Z15 -> 41.666667 | AB15: =SUM(P15:AA15) -> 500 | AC15: =AB15/12 -> 41.666667 | AD15: =AC15 -> 41.666667 | AE15: =AD15 -> 41.666667 | AF15: =AE15 -> 41.666667 | AG15: =AF15 -> 41.666667 | AH15: =AG15 -> 41.666667 | AI15: =AH15 -> 41.666667 | AJ15: =AI15 -> 41.666667 | AK15: =AJ15 -> 41.666667 | ... AN15: =AM15 -> 41.666667 | AO15: =SUM(AC15:AN15) -> 500 | AP15: =AO15 -> 500 | AQ15: =AP15 -> 500 | AR15: =AQ15 -> 500 | AS15: =AR15 -> 500 | AT15: =AS15 -> 500 | AU15: =AT15 -> 500 | AV15: =AU15 -> 500 | AW15: =AV15 -> 500 | ... BC15: =BB15 -> 500
A16: 1.9 | B16: Расходы по заработной плате | C16: 740.74074 | D16: 740.74074 | E16: 740.74074 | F16: 740.74074 | G16: 740.74074 | H16: 740.74074 | I16: 740.74074 | J16: 740.74074 | K16: 740.74074 | L16: 740.74074 | M16: 740.74074 | N16: 740.74074 | O16: =SUM(C16:N16) -> 8888.8889 | P16: =O16/12 -> 740.74074 | Q16: =P16 -> 740.74074 | R16: =Q16 -> 740.74074 | S16: =R16 -> 740.74074 | T16: =S16 -> 740.74074 | U16: =T16 -> 740.74074 | V16: =U16 -> 740.74074 | W16: =V16 -> 740.74074 | X16: =W16 -> 740.74074 | ... AA16: =Z16 -> 740.74074 | AB16: =SUM(P16:AA16) -> 8888.8889 | AC16: =AB16/12 -> 740.74074 | AD16: =AC16 -> 740.74074 | AE16: =AD16 -> 740.74074 | AF16: =AE16 -> 740.74074 | AG16: =AF16 -> 740.74074 | AH16: =AG16 -> 740.74074 | AI16: =AH16 -> 740.74074 | AJ16: =AI16 -> 740.74074 | AK16: =AJ16 -> 740.74074 | ... AN16: =AM16 -> 740.74074 | AO16: =SUM(AC16:AN16) -> 8888.8889 | AP16: =AO16 -> 8888.8889 | AQ16: =AP16 -> 8888.8889 | AR16: =AQ16 -> 8888.8889 | AS16: =AR16 -> 8888.8889 | AT16: =AS16 -> 8888.8889 | AU16: =AT16 -> 8888.8889 | AV16: =AU16 -> 8888.8889 | AW16: =AV16 -> 8888.8889 | ... BC16: =BB16 -> 8888.8889
A17: 1.10 | B17: Социальные отчисления | C17: 17.677178 | D17: 17.677178 | E17: 17.677178 | F17: 17.677178 | G17: 17.677178 | H17: 17.677178 | I17: 17.677178 | J17: 17.677178 | K17: 17.677178 | L17: 17.677178 | M17: 17.677178 | N17: 17.677178 | O17: =SUM(C17:N17) -> 212.12613 | P17: =O17/12 -> 17.677178 | Q17: =P17 -> 17.677178 | R17: =Q17 -> 17.677178 | S17: =R17 -> 17.677178 | T17: =S17 -> 17.677178 | U17: =T17 -> 17.677178 | V17: =U17 -> 17.677178 | W17: =V17 -> 17.677178 | X17: =W17 -> 17.677178 | ... AA17: =Z17 -> 17.677178 | AB17: =SUM(P17:AA17) -> 212.12613 | AC17: =AB17/12 -> 17.677178 | AD17: =AC17 -> 17.677178 | AE17: =AD17 -> 17.677178 | AF17: =AE17 -> 17.677178 | AG17: =AF17 -> 17.677178 | AH17: =AG17 -> 17.677178 | AI17: =AH17 -> 17.677178 | AJ17: =AI17 -> 17.677178 | AK17: =AJ17 -> 17.677178 | ... AN17: =AM17 -> 17.677178 | AO17: =SUM(AC17:AN17) -> 212.12613 | AP17: =AO17 -> 212.12613 | AQ17: =AP17 -> 212.12613 | AR17: =AQ17 -> 212.12613 | AS17: =AR17 -> 212.12613 | AT17: =AS17 -> 212.12613 | AU17: =AT17 -> 212.12613 | AV17: =AU17 -> 212.12613 | AW17: =AV17 -> 212.12613 | ... BC17: =BB17 -> 212.12613
A18: 1.11 | B18: Социальный налог | C18: 45.656156 | D18: 45.656156 | E18: 45.656156 | F18: 45.656156 | G18: 45.656156 | H18: 45.656156 | I18: 45.656156 | J18: 45.656156 | K18: 45.656156 | L18: 45.656156 | M18: 45.656156 | N18: 45.656156 | O18: =SUM(C18:N18) -> 547.87387 | P18: =O18/12 -> 45.656156 | Q18: =P18 -> 45.656156 | R18: =Q18 -> 45.656156 | S18: =R18 -> 45.656156 | T18: =S18 -> 45.656156 | U18: =T18 -> 45.656156 | V18: =U18 -> 45.656156 | W18: =V18 -> 45.656156 | X18: =W18 -> 45.656156 | ... AA18: =Z18 -> 45.656156 | AB18: =SUM(P18:AA18) -> 547.87387 | AC18: =AB18/12 -> 45.656156 | AD18: =AC18 -> 45.656156 | AE18: =AD18 -> 45.656156 | AF18: =AE18 -> 45.656156 | AG18: =AF18 -> 45.656156 | AH18: =AG18 -> 45.656156 | AI18: =AH18 -> 45.656156 | AJ18: =AI18 -> 45.656156 | AK18: =AJ18 -> 45.656156 | ... AN18: =AM18 -> 45.656156 | AO18: =SUM(AC18:AN18) -> 547.87387 | AP18: =AO18 -> 547.87387 | AQ18: =AP18 -> 547.87387 | AR18: =AQ18 -> 547.87387 | AS18: =AR18 -> 547.87387 | AT18: =AS18 -> 547.87387 | AU18: =AT18 -> 547.87387 | AV18: =AU18 -> 547.87387 | AW18: =AV18 -> 547.87387 | ... BC18: =BB18 -> 547.87387
A19: 1.12 | B19: Страхование | C19: 66.666667 | D19: 66.666667 | E19: 66.666667 | F19: 66.666667 | G19: 66.666667 | H19: 66.666667 | I19: 66.666667 | J19: 66.666667 | K19: 66.666667 | L19: 66.666667 | M19: 66.666667 | N19: 66.666667 | O19: =SUM(C19:N19) -> 800 | P19: =O19/12 -> 66.666667 | Q19: =P19 -> 66.666667 | R19: =Q19 -> 66.666667 | S19: =R19 -> 66.666667 | T19: =S19 -> 66.666667 | U19: =T19 -> 66.666667 | V19: =U19 -> 66.666667 | W19: =V19 -> 66.666667 | X19: =W19 -> 66.666667 | ... AA19: =Z19 -> 66.666667 | AB19: =SUM(P19:AA19) -> 800 | AC19: =AB19/12 -> 66.666667 | AD19: =AC19 -> 66.666667 | AE19: =AD19 -> 66.666667 | AF19: =AE19 -> 66.666667 | AG19: =AF19 -> 66.666667 | AH19: =AG19 -> 66.666667 | AI19: =AH19 -> 66.666667 | AJ19: =AI19 -> 66.666667 | AK19: =AJ19 -> 66.666667 | ... AN19: =AM19 -> 66.666667 | AO19: =SUM(AC19:AN19) -> 800 | AP19: =AO19 -> 800 | AQ19: =AP19 -> 800 | AR19: =AQ19 -> 800 | AS19: =AR19 -> 800 | AT19: =AS19 -> 800 | AU19: =AT19 -> 800 | AV19: =AU19 -> 800 | AW19: =AV19 -> 800 | ... BC19: =BB19 -> 800
A20: 1.13 | B20: Консалтинговые услуги | C20: 892.85714 | D20: 892.85714 | E20: 892.85714 | F20: 892.85714 | G20: 892.85714 | H20: 892.85714 | I20: 892.85714 | J20: 892.85714 | K20: 892.85714 | L20: 892.85714 | M20: 892.85714 | N20: 892.85714 | O20: =SUM(C20:N20) -> 10714.286 | P20: =(O20/12)*(1+Panel!$B$43) -> 997.32143 | Q20: =P20 -> 997.32143 | R20: =Q20 -> 997.32143 | S20: =R20 -> 997.32143 | T20: =S20 -> 997.32143 | U20: =T20 -> 997.32143 | V20: =U20 -> 997.32143 | W20: =V20 -> 997.32143 | X20: =W20 -> 997.32143 | ... AA20: =Z20 -> 997.32143 | AB20: =SUM(P20:AA20) -> 11967.857 | AC20: =(AB20/12)*(1+Panel!$B$43) -> 1114.008 | AD20: =AC20 -> 1114.008 | AE20: =AD20 -> 1114.008 | AF20: =AE20 -> 1114.008 | AG20: =AF20 -> 1114.008 | AH20: =AG20 -> 1114.008 | AI20: =AH20 -> 1114.008 | AJ20: =AI20 -> 1114.008 | AK20: =AJ20 -> 1114.008 | ... AN20: =AM20 -> 1114.008 | AO20: =SUM(AC20:AN20) -> 13368.096 | AP20: =(AO20)*(1+Panel!$B$43) -> 14932.164 | AQ20: =(AP20)*(1+Panel!$B$43) -> 16679.227 | AR20: =(AQ20)*(1+Panel!$B$43) -> 18630.696 | AS20: =(AR20)*(1+Panel!$B$43) -> 20810.488 | AT20: =(AS20)*(1+Panel!$B$43) -> 23245.315 | AU20: =(AT20)*(1+Panel!$B$43) -> 25965.017 | AV20: =(AU20)*(1+Panel!$B$43) -> 29002.924 | AW20: =(AV20)*(1+Panel!$B$43) -> 32396.266 | ... BC20: =(BB20)*(1+Panel!$B$43) -> 62923.663
A21: 1.14 | B21: Услуги банка | C21: 83.333333 | D21: 83.333333 | E21: 83.333333 | F21: 83.333333 | G21: 83.333333 | H21: 83.333333 | I21: 83.333333 | J21: 83.333333 | K21: 83.333333 | L21: 83.333333 | M21: 83.333333 | N21: 83.333333 | O21: =SUM(C21:N21) -> 1000 | P21: =(O21/12)*(1+Panel!$B$43) -> 93.083333 | Q21: =P21 -> 93.083333 | R21: =Q21 -> 93.083333 | S21: =R21 -> 93.083333 | T21: =S21 -> 93.083333 | U21: =T21 -> 93.083333 | V21: =U21 -> 93.083333 | W21: =V21 -> 93.083333 | X21: =W21 -> 93.083333 | ... AA21: =Z21 -> 93.083333 | AB21: =SUM(P21:AA21) -> 1117 | AC21: =(AB21/12)*(1+Panel!$B$43) -> 103.97408 | AD21: =AC21 -> 103.97408 | AE21: =AD21 -> 103.97408 | AF21: =AE21 -> 103.97408 | AG21: =AF21 -> 103.97408 | AH21: =AG21 -> 103.97408 | AI21: =AH21 -> 103.97408 | AJ21: =AI21 -> 103.97408 | AK21: =AJ21 -> 103.97408 | ... AN21: =AM21 -> 103.97408 | AO21: =SUM(AC21:AN21) -> 1247.689 | AP21: =(AO21)*(1+Panel!$B$43) -> 1393.6686 | AQ21: =(AP21)*(1+Panel!$B$43) -> 1556.7278 | AR21: =(AQ21)*(1+Panel!$B$43) -> 1738.865 | AS21: =(AR21)*(1+Panel!$B$43) -> 1942.3122 | AT21: =(AS21)*(1+Panel!$B$43) -> 2169.5627 | AU21: =(AT21)*(1+Panel!$B$43) -> 2423.4016 | AV21: =(AU21)*(1+Panel!$B$43) -> 2706.9396 | AW21: =(AV21)*(1+Panel!$B$43) -> 3023.6515 | ... BC21: =(BB21)*(1+Panel!$B$43) -> 5872.8752
A22: 1.15 | B22: Услуги сотовой связи | C22: 4.0117925 | D22: 4.0117925 | E22: 4.0117925 | F22: 4.0117925 | G22: 4.0117925 | H22: 4.0117925 | I22: 4.0117925 | J22: 4.0117925 | K22: 4.0117925 | L22: 4.0117925 | M22: 4.0117925 | N22: 4.0117925 | O22: =SUM(C22:N22) -> 48.14151 | P22: =(O22/12)*(1+Panel!$B$43) -> 4.4811722 | Q22: =P22 -> 4.4811722 | R22: =Q22 -> 4.4811722 | S22: =R22 -> 4.4811722 | T22: =S22 -> 4.4811722 | U22: =T22 -> 4.4811722 | V22: =U22 -> 4.4811722 | W22: =V22 -> 4.4811722 | X22: =W22 -> 4.4811722 | ... AA22: =Z22 -> 4.4811722 | AB22: =SUM(P22:AA22) -> 53.774067 | AC22: =(AB22/12)*(1+Panel!$B$43) -> 5.0054694 | AD22: =AC22 -> 5.0054694 | AE22: =AD22 -> 5.0054694 | AF22: =AE22 -> 5.0054694 | AG22: =AF22 -> 5.0054694 | AH22: =AG22 -> 5.0054694 | AI22: =AH22 -> 5.0054694 | AJ22: =AI22 -> 5.0054694 | AK22: =AJ22 -> 5.0054694 | ... AN22: =AM22 -> 5.0054694 | AO22: =SUM(AC22:AN22) -> 60.065632 | AP22: =(AO22)*(1+Panel!$B$43) -> 67.093311 | AQ22: =(AP22)*(1+Panel!$B$43) -> 74.943229 | AR22: =(AQ22)*(1+Panel!$B$43) -> 83.711587 | AS22: =(AR22)*(1+Panel!$B$43) -> 93.505842 | AT22: =(AS22)*(1+Panel!$B$43) -> 104.44603 | AU22: =(AT22)*(1+Panel!$B$43) -> 116.66621 | AV22: =(AU22)*(1+Panel!$B$43) -> 130.31616 | AW22: =(AV22)*(1+Panel!$B$43) -> 145.56315 | ... BC22: =(BB22)*(1+Panel!$B$43) -> 282.72908
A23: 1.16 | B23: Аренда | C23: 89.285714 | D23: 89.285714 | E23: 89.285714 | F23: 89.285714 | G23: 89.285714 | H23: 89.285714 | I23: 89.285714 | J23: 89.285714 | K23: 89.285714 | L23: 89.285714 | M23: 89.285714 | N23: 89.285714 | O23: =SUM(C23:N23) -> 1071.4286 | P23: =(O23/12)*(1+Panel!$B$43) -> 99.732143 | Q23: =P23 -> 99.732143 | R23: =Q23 -> 99.732143 | S23: =R23 -> 99.732143 | T23: =S23 -> 99.732143 | U23: =T23 -> 99.732143 | V23: =U23 -> 99.732143 | W23: =V23 -> 99.732143 | X23: =W23 -> 99.732143 | ... AA23: =Z23 -> 99.732143 | AB23: =SUM(P23:AA23) -> 1196.7857 | AC23: =(AB23/12)*(1+Panel!$B$43) -> 111.4008 | AD23: =AC23 -> 111.4008 | AE23: =AD23 -> 111.4008 | AF23: =AE23 -> 111.4008 | AG23: =AF23 -> 111.4008 | AH23: =AG23 -> 111.4008 | AI23: =AH23 -> 111.4008 | AJ23: =AI23 -> 111.4008 | AK23: =AJ23 -> 111.4008 | ... AN23: =AM23 -> 111.4008 | AO23: =SUM(AC23:AN23) -> 1336.8096 | AP23: =(AO23)*(1+Panel!$B$43) -> 1493.2164 | AQ23: =(AP23)*(1+Panel!$B$43) -> 1667.9227 | AR23: =(AQ23)*(1+Panel!$B$43) -> 1863.0696 | AS23: =(AR23)*(1+Panel!$B$43) -> 2081.0488 | AT23: =(AS23)*(1+Panel!$B$43) -> 2324.5315 | AU23: =(AT23)*(1+Panel!$B$43) -> 2596.5017 | AV23: =(AU23)*(1+Panel!$B$43) -> 2900.2924 | AW23: =(AV23)*(1+Panel!$B$43) -> 3239.6266 | ... BC23: =(BB23)*(1+Panel!$B$43) -> 6292.3663
B24: Итого | C24: =SUM(C8:C23) -> 2004.1208 | D24: =SUM(D8:D23) -> 2004.1208 | E24: =SUM(E8:E23) -> 2004.1208 | F24: =SUM(F8:F23) -> 2004.1208 | G24: =SUM(G8:G23) -> 2004.1208 | H24: =SUM(H8:H23) -> 2004.1208 | I24: =SUM(I8:I23) -> 2004.1208 | J24: =SUM(J8:J23) -> 2004.1208 | ... BC24: =SUM(BC8:BC23) -> 87132.749
A27: РАСЧЕТ ЕЖЕМЕСЯЧНОГО ФОНДА ОПЛАТЫ ТРУДА АДМИНИСТРАТИВНОГО ПЕРСОНАЛА,
A28: СОЦИАЛЬНОГО НАЛОГА, ОБЯЗАТЕЛЬНЫХ СОЦ. ОТЧИСЛЕНИЙ И ОСОР
A30: Исходные данные (согласно Налогового Кодекса РК 2026г.):
A32: Минимальная заработная плата | C32: =Panel!B30 -> 85000 | D32: тенге | F32: .
A33: Месячный расчетный показатель | C33: =Panel!B31 -> 4325 | D33: тенге
A34: Ставка социального налога | C34: =Panel!B32 -> 0.06
A35: Ставка социального страхования | C35: =Panel!B33 -> 0.05
A36: Минимальный размер соц.отч. | C36: =Panel!B34 -> 4250 | D36: тенге
A37: Максимальный размер соц.отч. | C37: =Panel!B35 -> 29750 | D37: тенге
A38: Минимальный размер соц.налога | C38: =Panel!B36 -> 5100 | D38: тенге
A39: Ставка взносов на ОСМС в 2018-2019 гг. | C39: =Panel!B39 -> 0.015
A40: Ставка взносов на ОСМС в 2026-2027 гг. | C40: =Panel!B40 -> 0.02
A41: Ставка взносов на ОСМС в 2028 г. и далее | C41: =Panel!B41 -> 0.03
A43: в тенге если не указано иное
A44: № п\п | B44: Наименование | C44: Ежемесячный фонд оплаты труда | I44: Социальные выплаты | L44: Отчисления за работника | N44: ОСМС-2018-2019 | O44: ОСМС-2026-2027 | P44: ОСМС-2028-далее | Q44: ЗП на руки
C45: Кол-во | D45: Ед.изм. | E45: Кол-во смен | F45: Всего, чел. | G45: Оклад | H45: Итого ФОТ: | I45: Соц. налог | J45: ГФСС | K45: Итого: | L45: Пенс.отч | M45: ИПН
A46: 1.1 | B46: Генеральный директор | C46: 1 | D46: чел. | E46: 1 | F46: =C46*E46 -> 1 | G46: =400000/0.81 -> 493827.16 | H46: =F46*G46 -> 493827.16 | I46: =IF((90%*G46*$C$34)<($C$38),($C$38),((90%*G46)*$C$34))*F46-J46 -> 4444.4444 | J46: =IF((G46*90%*$C$35)<($C$36),($C$36),IF((G46*90%*$C$35)>($C$37),($C$37),(G46*90%*$C$35)))*F46 -> 22222.222 | K46: =SUM(I46,J46) -> 26666.667 | L46: =H46*10% -> 49382.716 | M46: =(G46*90%-$C$34)*10%*F46 -> 44444.438 | N46: =H46*$C$39 -> 7407.4074 | O46: =H46*$C$40 -> 9876.5432 | P46: =H46*$C$41 -> 14814.815 | Q46: =H46-L46-M46 -> 400000.01
A47: 1.2 | B47: Технический директор | C47: 1 | D47: чел. | E47: 1 | F47: =C47*E47 -> 1 | G47: =200000/0.81 -> 246913.58 | H47: =F47*G47 -> 246913.58 | I47: =IF((90%*G47*$C$34)<($C$38),($C$38),((90%*G47)*$C$34))*F47-J47 -> 2222.2222 | J47: =IF((G47*90%*$C$35)<($C$36),($C$36),IF((G47*90%*$C$35)>($C$37),($C$37),(G47*90%*$C$35)))*F47 -> 11111.111 | K47: =SUM(I47,J47) -> 13333.333 | L47: =H47*10% -> 24691.358 | M47: =(G47*90%-$C$34)*10%*F47 -> 22222.216 | N47: =H47*$C$39 -> 3703.7037 | O47: =H47*$C$40 -> 4938.2716 | P47: =H47*$C$41 -> 7407.4074 | Q47: =H47-L47-M47 -> 200000.01
B48: Итого | C48: =SUM(C46:C47) -> 2 | H48: =SUM(H46:H47) -> 740740.74 | I48: =SUM(I46:I47) -> 6666.6667 | J48: =SUM(J46:J47) -> 33333.333 | K48: =SUM(K46:K47) -> 40000 | L48: =SUM(L46:L47) -> 74074.074 | M48: =SUM(M46:M47) -> 66666.655 | N48: =SUM(N46:N47) -> 11111.111 | O48: =SUM(O46:O47) -> 14814.815 | ... Q48: =SUM(Q46:Q47) -> 600000.01

Sheet Займ
A1: =Panel!A1
A2: =Panel!A2 -> Строительство ГЭС -5 МВТ
A4: ФИНАНСОВЫЕ ИЗДЕРЖКИ
A6: РАСЧЕТ ГРАФИКА ПОГАШЕНИЯ ЗАЙМА
A8: Ставка на первые три года | C8: =C9*60% -> 0.084
A9: Ставка на последующий период | C9: 0.14
A10: Срок | C10: 81 | D10: мес.
A12: в тыс. тенге, если не указано иное
A13: Год | B13: Мес | C13: Сумма осн.долга на начало месяца | D13: Сумма транша полученного | E13: Выплата осн долга | F13: Выплата осн долга | G13: Начисление вознаграждения | H13: Сумма осн.долга на конец месяца | I13: Выплата вознаграждения | J13: Выплата вознаграждения | K13: Ежемесячный платеж
A14: 2026 | B14: 1 | D14: ='Займ 776'!D14+'Займ 1 578'!D14 -> 228834.58 | E14: ='Займ 776'!E14+'Займ 1 578'!E14 -> 0 | F14: ='Займ 776'!F14+'Займ 1 578'!F14 -> 0 | G14: ='Займ 776'!G14+'Займ 1 578'!G14 -> 0 | H14: ='Займ 776'!H14+'Займ 1 578'!H14 -> 228834.58 | I14: ='Займ 776'!I14+'Займ 1 578'!I14 -> 0 | J14: ='Займ 776'!J14+'Займ 1 578'!J14 -> 0 | K14: ='Займ 776'!K14+'Займ 1 578'!K14 -> 0
B15: 2 | D15: ='Займ 776'!D15+'Займ 1 578'!D15 -> 193338.77 | E15: ='Займ 776'!E15+'Займ 1 578'!E15 -> 0 | F15: ='Займ 776'!F15+'Займ 1 578'!F15 -> 0 | G15: ='Займ 776'!G15+'Займ 1 578'!G15 -> 0 | H15: ='Займ 776'!H15+'Займ 1 578'!H15 -> 422173.35 | I15: ='Займ 776'!I15+'Займ 1 578'!I15 -> 0 | J15: ='Займ 776'!J15+'Займ 1 578'!J15 -> 0 | K15: ='Займ 776'!K15+'Займ 1 578'!K15 -> 0
B16: 3 | D16: ='Займ 776'!D16+'Займ 1 578'!D16 -> 193338.77 | E16: ='Займ 776'!E16+'Займ 1 578'!E16 -> 0 | F16: ='Займ 776'!F16+'Займ 1 578'!F16 -> 0 | G16: ='Займ 776'!G16+'Займ 1 578'!G16 -> 0 | H16: ='Займ 776'!H16+'Займ 1 578'!H16 -> 615512.13 | I16: ='Займ 776'!I16+'Займ 1 578'!I16 -> 0 | J16: ='Займ 776'!J16+'Займ 1 578'!J16 -> 0 | K16: ='Займ 776'!K16+'Займ 1 578'!K16 -> 0
B17: 4 | D17: ='Займ 776'!D17+'Займ 1 578'!D17 -> 193338.77 | E17: ='Займ 776'!E17+'Займ 1 578'!E17 -> 0 | F17: ='Займ 776'!F17+'Займ 1 578'!F17 -> 0 | G17: ='Займ 776'!G17+'Займ 1 578'!G17 -> 4718.2969 | H17: ='Займ 776'!H17+'Займ 1 578'!H17 -> 808850.9 | I17: ='Займ 776'!I17+'Займ 1 578'!I17 -> 4718.2969 | J17: ='Займ 776'!J17+'Займ 1 578'!J17 -> 4718.2969 | K17: ='Займ 776'!K17+'Займ 1 578'!K17 -> 4718.2969
B18: 5 | D18: ='Займ 776'!D18+'Займ 1 578'!D18 -> 193338.77 | E18: ='Займ 776'!E18+'Займ 1 578'!E18 -> 0 | F18: ='Займ 776'!F18+'Займ 1 578'!F18 -> 0 | G18: ='Займ 776'!G18+'Займ 1 578'!G18 -> 5846.1064 | H18: ='Займ 776'!H18+'Займ 1 578'!H18 -> 1002189.7 | I18: ='Займ 776'!I18+'Займ 1 578'!I18 -> 5846.1064 | J18: ='Займ 776'!J18+'Займ 1 578'!J18 -> 5846.1064 | K18: ='Займ 776'!K18+'Займ 1 578'!K18 -> 5846.1064
B19: 6 | D19: ='Займ 776'!D19+'Займ 1 578'!D19 -> 193338.77 | E19: ='Займ 776'!E19+'Займ 1 578'!E19 -> 0 | F19: ='Займ 776'!F19+'Займ 1 578'!F19 -> 0 | G19: ='Займ 776'!G19+'Займ 1 578'!G19 -> 6973.916 | H19: ='Займ 776'!H19+'Займ 1 578'!H19 -> 1195528.4 | I19: ='Займ 776'!I19+'Займ 1 578'!I19 -> 6973.916 | J19: ='Займ 776'!J19+'Займ 1 578'!J19 -> 6973.916 | K19: ='Займ 776'!K19+'Займ 1 578'!K19 -> 6973.916
B20: 7 | D20: ='Займ 776'!D20+'Займ 1 578'!D20 -> 193338.77 | E20: ='Займ 776'!E20+'Займ 1 578'!E20 -> 0 | F20: ='Займ 776'!F20+'Займ 1 578'!F20 -> 0 | G20: ='Займ 776'!G20+'Займ 1 578'!G20 -> 8101.7255 | H20: ='Займ 776'!H20+'Займ 1 578'!H20 -> 1388867.2 | I20: ='Займ 776'!I20+'Займ 1 578'!I20 -> 8101.7255 | J20: ='Займ 776'!J20+'Займ 1 578'!J20 -> 8101.7255 | K20: ='Займ 776'!K20+'Займ 1 578'!K20 -> 8101.7255
B21: 8 | D21: ='Займ 776'!D21+'Займ 1 578'!D21 -> 193338.77 | E21: ='Займ 776'!E21+'Займ 1 578'!E21 -> 0 | F21: ='Займ 776'!F21+'Займ 1 578'!F21 -> 0 | G21: ='Займ 776'!G21+'Займ 1 578'!G21 -> 9229.535 | H21: ='Займ 776'!H21+'Займ 1 578'!H21 -> 1582206 | I21: ='Займ 776'!I21+'Займ 1 578'!I21 -> 9229.535 | J21: ='Займ 776'!J21+'Займ 1 578'!J21 -> 9229.535 | K21: ='Займ 776'!K21+'Займ 1 578'!K21 -> 9229.535
B22: 9 | D22: ='Займ 776'!D22+'Займ 1 578'!D22 -> 193338.77 | E22: ='Займ 776'!E22+'Займ 1 578'!E22 -> 0 | F22: ='Займ 776'!F22+'Займ 1 578'!F22 -> 0 | G22: ='Займ 776'!G22+'Займ 1 578'!G22 -> 10357.344 | H22: ='Займ 776'!H22+'Займ 1 578'!H22 -> 1775544.8 | I22: ='Займ 776'!I22+'Займ 1 578'!I22 -> 10357.344 | J22: ='Займ 776'!J22+'Займ 1 578'!J22 -> 10357.344 | K22: ='Займ 776'!K22+'Займ 1 578'!K22 -> 10357.344
B23: 10 | D23: ='Займ 776'!D23+'Займ 1 578'!D23 -> 193338.77 | E23: ='Займ 776'!E23+'Займ 1 578'!E23 -> 0 | F23: ='Займ 776'!F23+'Займ 1 578'!F23 -> 0 | G23: ='Займ 776'!G23+'Займ 1 578'!G23 -> 11485.154 | H23: ='Займ 776'!H23+'Займ 1 578'!H23 -> 1968883.5 | I23: ='Займ 776'!I23+'Займ 1 578'!I23 -> 11485.154 | J23: ='Займ 776'!J23+'Займ 1 578'!J23 -> 11485.154 | K23: ='Займ 776'!K23+'Займ 1 578'!K23 -> 11485.154
B24: 11 | D24: ='Займ 776'!D24+'Займ 1 578'!D24 -> 193338.77 | E24: ='Займ 776'!E24+'Займ 1 578'!E24 -> 0 | F24: ='Займ 776'!F24+'Займ 1 578'!F24 -> 0 | G24: ='Займ 776'!G24+'Займ 1 578'!G24 -> 12612.964 | H24: ='Займ 776'!H24+'Займ 1 578'!H24 -> 2162222.3 | I24: ='Займ 776'!I24+'Займ 1 578'!I24 -> 12612.964 | J24: ='Займ 776'!J24+'Займ 1 578'!J24 -> 12612.964 | K24: ='Займ 776'!K24+'Займ 1 578'!K24 -> 12612.964
B25: 12 | D25: ='Займ 776'!D25+'Займ 1 578'!D25 -> 193338.77 | E25: ='Займ 776'!E25+'Займ 1 578'!E25 -> 0 | F25: ='Займ 776'!F25+'Займ 1 578'!F25 -> 0 | G25: ='Займ 776'!G25+'Займ 1 578'!G25 -> 13740.773 | H25: ='Займ 776'!H25+'Займ 1 578'!H25 -> 2355561.1 | I25: ='Займ 776'!I25+'Займ 1 578'!I25 -> 13740.773 | J25: ='Займ 776'!J25+'Займ 1 578'!J25 -> 13740.773 | K25: ='Займ 776'!K25+'Займ 1 578'!K25 -> 13740.773
A26: 2027 | B26: 1 | D26: ='Займ 776'!D26+'Займ 1 578'!D26 -> 0 | E26: ='Займ 776'!E26+'Займ 1 578'!E26 -> 0 | F26: ='Займ 776'!F26+'Займ 1 578'!F26 -> 0 | G26: ='Займ 776'!G26+'Займ 1 578'!G26 -> 13740.773 | H26: ='Займ 776'!H26+'Займ 1 578'!H26 -> 2355561.1 | I26: ='Займ 776'!I26+'Займ 1 578'!I26 -> 13740.773 | J26: ='Займ 776'!J26+'Займ 1 578'!J26 -> 0 | K26: ='Займ 776'!K26+'Займ 1 578'!K26 -> 13740.773
B27: 2 | D27: ='Займ 776'!D27+'Займ 1 578'!D27 -> 0 | E27: ='Займ 776'!E27+'Займ 1 578'!E27 -> 0 | F27: ='Займ 776'!F27+'Займ 1 578'!F27 -> 0 | G27: ='Займ 776'!G27+'Займ 1 578'!G27 -> 13740.773 | H27: ='Займ 776'!H27+'Займ 1 578'!H27 -> 2355561.1 | I27: ='Займ 776'!I27+'Займ 1 578'!I27 -> 13740.773 | J27: ='Займ 776'!J27+'Займ 1 578'!J27 -> 0 | K27: ='Займ 776'!K27+'Займ 1 578'!K27 -> 13740.773
B28: 3 | D28: ='Займ 776'!D28+'Займ 1 578'!D28 -> 0 | E28: ='Займ 776'!E28+'Займ 1 578'!E28 -> 0 | F28: ='Займ 776'!F28+'Займ 1 578'!F28 -> 0 | G28: ='Займ 776'!G28+'Займ 1 578'!G28 -> 13740.773 | H28: ='Займ 776'!H28+'Займ 1 578'!H28 -> 2355561.1 | I28: ='Займ 776'!I28+'Займ 1 578'!I28 -> 13740.773 | J28: ='Займ 776'!J28+'Займ 1 578'!J28 -> 0 | K28: ='Займ 776'!K28+'Займ 1 578'!K28 -> 13740.773
B29: 4 | D29: ='Займ 776'!D29+'Займ 1 578'!D29 -> 0 | E29: ='Займ 776'!E29+'Займ 1 578'!E29 -> 22832.838 | F29: ='Займ 776'!F29+'Займ 1 578'!F29 -> 0 | G29: ='Займ 776'!G29+'Займ 1 578'!G29 -> 13740.773 | H29: ='Займ 776'!H29+'Займ 1 578'!H29 -> 2332728.3 | I29: ='Займ 776'!I29+'Займ 1 578'!I29 -> 13740.773 | J29: ='Займ 776'!J29+'Займ 1 578'!J29 -> 0 | K29: ='Займ 776'!K29+'Займ 1 578'!K29 -> 36573.611
B30: 5 | D30: ='Займ 776'!D30+'Займ 1 578'!D30 -> 0 | E30: ='Займ 776'!E30+'Займ 1 578'!E30 -> 22966.029 | F30: ='Займ 776'!F30+'Займ 1 578'!F30 -> 0 | G30: ='Займ 776'!G30+'Займ 1 578'!G30 -> 13607.582 | H30: ='Займ 776'!H30+'Займ 1 578'!H30 -> 2309762.2 | I30: ='Займ 776'!I30+'Займ 1 578'!I30 -> 13607.582 | J30: ='Займ 776'!J30+'Займ 1 578'!J30 -> 0 | K30: ='Займ 776'!K30+'Займ 1 578'!K30 -> 36573.611
B31: 6 | D31: ='Займ 776'!D31+'Займ 1 578'!D31 -> 0 | E31: ='Займ 776'!E31+'Займ 1 578'!E31 -> 23099.998 | F31: ='Займ 776'!F31+'Займ 1 578'!F31 -> 0 | G31: ='Займ 776'!G31+'Займ 1 578'!G31 -> 13473.613 | H31: ='Займ 776'!H31+'Займ 1 578'!H31 -> 2286662.2 | I31: ='Займ 776'!I31+'Займ 1 578'!I31 -> 13473.613 | J31: ='Займ 776'!J31+'Займ 1 578'!J31 -> 0 | K31: ='Займ 776'!K31+'Займ 1 578'!K31 -> 36573.611
B32: 7 | D32: ='Займ 776'!D32+'Займ 1 578'!D32 -> 0 | E32: ='Займ 776'!E32+'Займ 1 578'!E32 -> 23234.748 | F32: ='Займ 776'!F32+'Займ 1 578'!F32 -> 24541.565 | G32: ='Займ 776'!G32+'Займ 1 578'!G32 -> 13338.863 | H32: ='Займ 776'!H32+'Займ 1 578'!H32 -> 2263427.5 | I32: ='Займ 776'!I32+'Займ 1 578'!I32 -> 13338.863 | J32: ='Займ 776'!J32+'Займ 1 578'!J32 -> 18669.997 | K32: ='Займ 776'!K32+'Займ 1 578'!K32 -> 36573.611 | M32: Фактическая выплата в 2026 | N32: 0.7
B33: 8 | D33: ='Займ 776'!D33+'Займ 1 578'!D33 -> 0 | E33: ='Займ 776'!E33+'Займ 1 578'!E33 -> 23370.284 | F33: ='Займ 776'!F33+'Займ 1 578'!F33 -> 24541.565 | G33: ='Займ 776'!G33+'Займ 1 578'!G33 -> 13203.327 | H33: ='Займ 776'!H33+'Займ 1 578'!H33 -> 2240057.2 | I33: ='Займ 776'!I33+'Займ 1 578'!I33 -> 13203.327 | J33: ='Займ 776'!J33+'Займ 1 578'!J33 -> 18669.997 | K33: ='Займ 776'!K33+'Займ 1 578'!K33 -> 36573.611 | M33: Фактическая выплата в 2027 | N33: 0.7
B34: 9 | D34: ='Займ 776'!D34+'Займ 1 578'!D34 -> 0 | E34: ='Займ 776'!E34+'Займ 1 578'!E34 -> 23506.611 | F34: ='Займ 776'!F34+'Займ 1 578'!F34 -> 24541.565 | G34: ='Займ 776'!G34+'Займ 1 578'!G34 -> 13067 | H34: ='Займ 776'!H34+'Займ 1 578'!H34 -> 2216550.6 | I34: ='Займ 776'!I34+'Займ 1 578'!I34 -> 13067 | J34: ='Займ 776'!J34+'Займ 1 578'!J34 -> 18669.997 | K34: ='Займ 776'!K34+'Займ 1 578'!K34 -> 36573.611 | M34: Фактическая выплата в 2028 | N34: 0.7
B35: 10 | D35: ='Займ 776'!D35+'Займ 1 578'!D35 -> 0 | E35: ='Займ 776'!E35+'Займ 1 578'!E35 -> 23643.732 | F35: ='Займ 776'!F35+'Займ 1 578'!F35 -> 24541.565 | G35: ='Займ 776'!G35+'Займ 1 578'!G35 -> 12929.878 | H35: ='Займ 776'!H35+'Займ 1 578'!H35 -> 2192906.9 | I35: ='Займ 776'!I35+'Займ 1 578'!I35 -> 12929.878 | J35: ='Займ 776'!J35+'Займ 1 578'!J35 -> 18669.997 | K35: ='Займ 776'!K35+'Займ 1 578'!K35 -> 36573.611
B36: 11 | D36: ='Займ 776'!D36+'Займ 1 578'!D36 -> 0 | E36: ='Займ 776'!E36+'Займ 1 578'!E36 -> 23781.654 | F36: ='Займ 776'!F36+'Займ 1 578'!F36 -> 24541.565 | G36: ='Займ 776'!G36+'Займ 1 578'!G36 -> 12791.957 | H36: ='Займ 776'!H36+'Займ 1 578'!H36 -> 2169125.2 | I36: ='Займ 776'!I36+'Займ 1 578'!I36 -> 12791.957 | J36: ='Займ 776'!J36+'Займ 1 578'!J36 -> 18669.997 | K36: ='Займ 776'!K36+'Займ 1 578'!K36 -> 36573.611
B37: 12 | D37: ='Займ 776'!D37+'Займ 1 578'!D37 -> 0 | E37: ='Займ 776'!E37+'Займ 1 578'!E37 -> 23920.381 | F37: ='Займ 776'!F37+'Займ 1 578'!F37 -> 24541.565 | G37: ='Займ 776'!G37+'Займ 1 578'!G37 -> 12653.23 | H37: ='Займ 776'!H37+'Займ 1 578'!H37 -> 2145204.8 | I37: ='Займ 776'!I37+'Займ 1 578'!I37 -> 12653.23 | J37: ='Займ 776'!J37+'Займ 1 578'!J37 -> 18669.997 | K37: ='Займ 776'!K37+'Займ 1 578'!K37 -> 36573.611
A38: 2028 | B38: 1 | D38: ='Займ 776'!D38+'Займ 1 578'!D38 -> 0 | E38: ='Займ 776'!E38+'Займ 1 578'!E38 -> 24059.916 | F38: ='Займ 776'!F38+'Займ 1 578'!F38 -> 0 | G38: ='Займ 776'!G38+'Займ 1 578'!G38 -> 12513.695 | H38: ='Займ 776'!H38+'Займ 1 578'!H38 -> 2121144.9 | I38: ='Займ 776'!I38+'Займ 1 578'!I38 -> 12513.695 | J38: ='Займ 776'!J38+'Займ 1 578'!J38 -> 0 | K38: ='Займ 776'!K38+'Займ 1 578'!K38 -> 36573.611
B39: 2 | D39: ='Займ 776'!D39+'Займ 1 578'!D39 -> 0 | E39: ='Займ 776'!E39+'Займ 1 578'!E39 -> 24200.266 | F39: ='Займ 776'!F39+'Займ 1 578'!F39 -> 0 | G39: ='Займ 776'!G39+'Займ 1 578'!G39 -> 12373.345 | H39: ='Займ 776'!H39+'Займ 1 578'!H39 -> 2096944.6 | I39: ='Займ 776'!I39+'Займ 1 578'!I39 -> 12373.345 | J39: ='Займ 776'!J39+'Займ 1 578'!J39 -> 0 | K39: ='Займ 776'!K39+'Займ 1 578'!K39 -> 36573.611
B40: 3 | D40: ='Займ 776'!D40+'Займ 1 578'!D40 -> 0 | E40: ='Займ 776'!E40+'Займ 1 578'!E40 -> 24341.434 | F40: ='Займ 776'!F40+'Займ 1 578'!F40 -> 0 | G40: ='Займ 776'!G40+'Займ 1 578'!G40 -> 12232.177 | H40: ='Займ 776'!H40+'Займ 1 578'!H40 -> 2072603.2 | I40: ='Займ 776'!I40+'Займ 1 578'!I40 -> 12232.177 | J40: ='Займ 776'!J40+'Займ 1 578'!J40 -> 0 | K40: ='Займ 776'!K40+'Займ 1 578'!K40 -> 36573.611
B41: 4 | D41: ='Займ 776'!D41+'Займ 1 578'!D41 -> 0 | E41: ='Займ 776'!E41+'Займ 1 578'!E41 -> 24483.426 | F41: ='Займ 776'!F41+'Займ 1 578'!F41 -> 0 | G41: ='Займ 776'!G41+'Займ 1 578'!G41 -> 12090.185 | H41: ='Займ 776'!H41+'Займ 1 578'!H41 -> 2048119.8 | I41: ='Займ 776'!I41+'Займ 1 578'!I41 -> 12090.185 | J41: ='Займ 776'!J41+'Займ 1 578'!J41 -> 0 | K41: ='Займ 776'!K41+'Займ 1 578'!K41 -> 36573.611
B42: 5 | D42: ='Займ 776'!D42+'Займ 1 578'!D42 -> 0 | E42: ='Займ 776'!E42+'Займ 1 578'!E42 -> 24626.245 | F42: ='Займ 776'!F42+'Займ 1 578'!F42 -> 0 | G42: ='Займ 776'!G42+'Займ 1 578'!G42 -> 11947.365 | H42: ='Займ 776'!H42+'Займ 1 578'!H42 -> 2023493.5 | I42: ='Займ 776'!I42+'Займ 1 578'!I42 -> 11947.365 | J42: ='Займ 776'!J42+'Займ 1 578'!J42 -> 0 | K42: ='Займ 776'!K42+'Займ 1 578'!K42 -> 36573.611
B43: 6 | D43: ='Займ 776'!D43+'Займ 1 578'!D43 -> 0 | E43: ='Займ 776'!E43+'Займ 1 578'!E43 -> 24769.899 | F43: ='Займ 776'!F43+'Займ 1 578'!F43 -> 0 | G43: ='Займ 776'!G43+'Займ 1 578'!G43 -> 11803.712 | H43: ='Займ 776'!H43+'Займ 1 578'!H43 -> 1998723.6 | I43: ='Займ 776'!I43+'Займ 1 578'!I43 -> 11803.712 | J43: ='Займ 776'!J43+'Займ 1 578'!J43 -> 0 | K43: ='Займ 776'!K43+'Займ 1 578'!K43 -> 36573.611
B44: 7 | D44: ='Займ 776'!D44+'Займ 1 578'!D44 -> 0 | E44: ='Займ 776'!E44+'Займ 1 578'!E44 -> 24914.39 | F44: ='Займ 776'!F44+'Займ 1 578'!F44 -> 34785.866 | G44: ='Займ 776'!G44+'Займ 1 578'!G44 -> 11659.221 | H44: ='Займ 776'!H44+'Займ 1 578'!H44 -> 1973809.2 | I44: ='Займ 776'!I44+'Займ 1 578'!I44 -> 11659.221 | J44: ='Займ 776'!J44+'Займ 1 578'!J44 -> 16417.19 | K44: ='Займ 776'!K44+'Займ 1 578'!K44 -> 36573.611
B45: 8 | D45: ='Займ 776'!D45+'Займ 1 578'!D45 -> 0 | E45: ='Займ 776'!E45+'Займ 1 578'!E45 -> 25059.724 | F45: ='Займ 776'!F45+'Займ 1 578'!F45 -> 34785.866 | G45: ='Займ 776'!G45+'Займ 1 578'!G45 -> 11513.887 | H45: ='Займ 776'!H45+'Займ 1 578'!H45 -> 1948749.5 | I45: ='Займ 776'!I45+'Займ 1 578'!I45 -> 11513.887 | J45: ='Займ 776'!J45+'Займ 1 578'!J45 -> 16417.19 | K45: ='Займ 776'!K45+'Займ 1 578'!K45 -> 36573.611
B46: 9 | D46: ='Займ 776'!D46+'Займ 1 578'!D46 -> 0 | E46: ='Займ 776'!E46+'Займ 1 578'!E46 -> 25205.905 | F46: ='Займ 776'!F46+'Займ 1 578'!F46 -> 34785.866 | G46: ='Займ 776'!G46+'Займ 1 578'!G46 -> 11367.706 | H46: ='Займ 776'!H46+'Займ 1 578'!H46 -> 1923543.6 | I46: ='Займ 776'!I46+'Займ 1 578'!I46 -> 11367.706 | J46: ='Займ 776'!J46+'Займ 1 578'!J46 -> 16417.19 | K46: ='Займ 776'!K46+'Займ 1 578'!K46 -> 36573.611
B47: 10 | D47: ='Займ 776'!D47+'Займ 1 578'!D47 -> 0 | E47: ='Займ 776'!E47+'Займ 1 578'!E47 -> 25352.94 | F47: ='Займ 776'!F47+'Займ 1 578'!F47 -> 34785.866 | G47: ='Займ 776'!G47+'Займ 1 578'!G47 -> 11220.671 | H47: ='Займ 776'!H47+'Займ 1 578'!H47 -> 1898190.7 | I47: ='Займ 776'!I47+'Займ 1 578'!I47 -> 11220.671 | J47: ='Займ 776'!J47+'Займ 1 578'!J47 -> 16417.19 | K47: ='Займ 776'!K47+'Займ 1 578'!K47 -> 36573.611
B48: 11 | D48: ='Займ 776'!D48+'Займ 1 578'!D48 -> 0 | E48: ='Займ 776'!E48+'Займ 1 578'!E48 -> 25500.832 | F48: ='Займ 776'!F48+'Займ 1 578'!F48 -> 34785.866 | G48: ='Займ 776'!G48+'Займ 1 578'!G48 -> 11072.779 | H48: ='Займ 776'!H48+'Займ 1 578'!H48 -> 1872689.8 | I48: ='Займ 776'!I48+'Займ 1 578'!I48 -> 11072.779 | J48: ='Займ 776'!J48+'Займ 1 578'!J48 -> 16417.19 | K48: ='Займ 776'!K48+'Займ 1 578'!K48 -> 36573.611
B49: 12 | D49: ='Займ 776'!D49+'Займ 1 578'!D49 -> 0 | E49: ='Займ 776'!E49+'Займ 1 578'!E49 -> 25649.587 | F49: ='Займ 776'!F49+'Займ 1 578'!F49 -> 34785.866 | G49: ='Займ 776'!G49+'Займ 1 578'!G49 -> 10924.024 | H49: ='Займ 776'!H49+'Займ 1 578'!H49 -> 1847040.3 | I49: ='Займ 776'!I49+'Займ 1 578'!I49 -> 10924.024 | J49: ='Займ 776'!J49+'Займ 1 578'!J49 -> 16417.19 | K49: ='Займ 776'!K49+'Займ 1 578'!K49 -> 36573.611
A50: 2029 | B50: 1 | D50: ='Займ 776'!D50+'Займ 1 578'!D50 -> 0 | E50: ='Займ 776'!E50+'Займ 1 578'!E50 -> 25799.209 | F50: ='Займ 776'!F50+'Займ 1 578'!F50 -> 0 | G50: ='Займ 776'!G50+'Займ 1 578'!G50 -> 10774.401 | H50: ='Займ 776'!H50+'Займ 1 578'!H50 -> 1821241 | I50: ='Займ 776'!I50+'Займ 1 578'!I50 -> 10774.401 | J50: ='Займ 776'!J50+'Займ 1 578'!J50 -> 0 | K50: ='Займ 776'!K50+'Займ 1 578'!K50 -> 36573.611
B51: 2 | D51: ='Займ 776'!D51+'Займ 1 578'!D51 -> 0 | E51: ='Займ 776'!E51+'Займ 1 578'!E51 -> 25949.705 | F51: ='Займ 776'!F51+'Займ 1 578'!F51 -> 0 | G51: ='Займ 776'!G51+'Займ 1 578'!G51 -> 10623.906 | H51: ='Займ 776'!H51+'Займ 1 578'!H51 -> 1795291.3 | I51: ='Займ 776'!I51+'Займ 1 578'!I51 -> 10623.906 | J51: ='Займ 776'!J51+'Займ 1 578'!J51 -> 0 | K51: ='Займ 776'!K51+'Займ 1 578'!K51 -> 36573.611
B52: 3 | D52: ='Займ 776'!D52+'Займ 1 578'!D52 -> 0 | E52: ='Займ 776'!E52+'Займ 1 578'!E52 -> 26101.078 | F52: ='Займ 776'!F52+'Займ 1 578'!F52 -> 0 | G52: ='Займ 776'!G52+'Займ 1 578'!G52 -> 10472.533 | H52: ='Займ 776'!H52+'Займ 1 578'!H52 -> 1769190.3 | I52: ='Займ 776'!I52+'Займ 1 578'!I52 -> 10472.533 | J52: ='Займ 776'!J52+'Займ 1 578'!J52 -> 0 | K52: ='Займ 776'!K52+'Займ 1 578'!K52 -> 36573.611
B53: 4 | D53: ='Займ 776'!D53+'Займ 1 578'!D53 -> 0 | E53: ='Займ 776'!E53+'Займ 1 578'!E53 -> 26253.334 | F53: ='Займ 776'!F53+'Займ 1 578'!F53 -> 0 | G53: ='Займ 776'!G53+'Займ 1 578'!G53 -> 10320.277 | H53: ='Займ 776'!H53+'Займ 1 578'!H53 -> 1742936.9 | I53: ='Займ 776'!I53+'Займ 1 578'!I53 -> 10320.277 | J53: ='Займ 776'!J53+'Займ 1 578'!J53 -> 0 | K53: ='Займ 776'!K53+'Займ 1 578'!K53 -> 36573.611
B54: 5 | D54: ='Займ 776'!D54+'Займ 1 578'!D54 -> 0 | E54: ='Займ 776'!E54+'Займ 1 578'!E54 -> 26406.479 | F54: ='Займ 776'!F54+'Займ 1 578'!F54 -> 0 | G54: ='Займ 776'!G54+'Займ 1 578'!G54 -> 10167.132 | H54: ='Займ 776'!H54+'Займ 1 578'!H54 -> 1716530.5 | I54: ='Займ 776'!I54+'Займ 1 578'!I54 -> 10167.132 | J54: ='Займ 776'!J54+'Займ 1 578'!J54 -> 0 | K54: ='Займ 776'!K54+'Займ 1 578'!K54 -> 36573.611
B55: 6 | D55: ='Займ 776'!D55+'Займ 1 578'!D55 -> 0 | E55: ='Займ 776'!E55+'Займ 1 578'!E55 -> 26560.517 | F55: ='Займ 776'!F55+'Займ 1 578'!F55 -> 0 | G55: ='Займ 776'!G55+'Займ 1 578'!G55 -> 10013.094 | H55: ='Займ 776'!H55+'Займ 1 578'!H55 -> 1689969.9 | I55: ='Займ 776'!I55+'Займ 1 578'!I55 -> 10013.094 | J55: ='Займ 776'!J55+'Займ 1 578'!J55 -> 0 | K55: ='Займ 776'!K55+'Займ 1 578'!K55 -> 36573.611
B56: 7 | D56: ='Займ 776'!D56+'Займ 1 578'!D56 -> 0 | E56: ='Займ 776'!E56+'Займ 1 578'!E56 -> 26715.453 | F56: ='Займ 776'!F56+'Займ 1 578'!F56 -> 37300.539 | G56: ='Займ 776'!G56+'Займ 1 578'!G56 -> 9858.158 | H56: ='Займ 776'!H56+'Займ 1 578'!H56 -> 1663254.5 | I56: ='Займ 776'!I56+'Займ 1 578'!I56 -> 9858.158 | J56: ='Займ 776'!J56+'Займ 1 578'!J56 -> 13902.517 | K56: ='Займ 776'!K56+'Займ 1 578'!K56 -> 36573.611
B57: 8 | D57: ='Займ 776'!D57+'Займ 1 578'!D57 -> 0 | E57: ='Займ 776'!E57+'Займ 1 578'!E57 -> 26871.293 | F57: ='Займ 776'!F57+'Займ 1 578'!F57 -> 37300.539 | G57: ='Займ 776'!G57+'Займ 1 578'!G57 -> 9702.3178 | H57: ='Займ 776'!H57+'Займ 1 578'!H57 -> 1636383.2 | I57: ='Займ 776'!I57+'Займ 1 578'!I57 -> 9702.3178 | J57: ='Займ 776'!J57+'Займ 1 578'!J57 -> 13902.517 | K57: ='Займ 776'!K57+'Займ 1 578'!K57 -> 36573.611
B58: 9 | D58: ='Займ 776'!D58+'Займ 1 578'!D58 -> 0 | E58: ='Займ 776'!E58+'Займ 1 578'!E58 -> 27028.042 | F58: ='Займ 776'!F58+'Займ 1 578'!F58 -> 37300.539 | G58: ='Займ 776'!G58+'Займ 1 578'!G58 -> 9545.5686 | H58: ='Займ 776'!H58+'Займ 1 578'!H58 -> 1609355.1 | I58: ='Займ 776'!I58+'Займ 1 578'!I58 -> 9545.5686 | J58: ='Займ 776'!J58+'Займ 1 578'!J58 -> 13902.517 | K58: ='Займ 776'!K58+'Займ 1 578'!K58 -> 36573.611
B59: 10 | D59: ='Займ 776'!D59+'Займ 1 578'!D59 -> 0 | E59: ='Займ 776'!E59+'Займ 1 578'!E59 -> 27185.706 | F59: ='Займ 776'!F59+'Займ 1 578'!F59 -> 37300.539 | G59: ='Займ 776'!G59+'Займ 1 578'!G59 -> 9387.905 | H59: ='Займ 776'!H59+'Займ 1 578'!H59 -> 1582169.4 | I59: ='Займ 776'!I59+'Займ 1 578'!I59 -> 9387.905 | J59: ='Займ 776'!J59+'Займ 1 578'!J59 -> 13902.517 | K59: ='Займ 776'!K59+'Займ 1 578'!K59 -> 36573.611
B60: 11 | D60: ='Займ 776'!D60+'Займ 1 578'!D60 -> 0 | E60: ='Займ 776'!E60+'Займ 1 578'!E60 -> 27344.289 | F60: ='Займ 776'!F60+'Займ 1 578'!F60 -> 37300.539 | G60: ='Займ 776'!G60+'Займ 1 578'!G60 -> 9229.3217 | H60: ='Займ 776'!H60+'Займ 1 578'!H60 -> 1554825.2 | I60: ='Займ 776'!I60+'Займ 1 578'!I60 -> 9229.3217 | J60: ='Займ 776'!J60+'Займ 1 578'!J60 -> 13902.517 | K60: ='Займ 776'!K60+'Займ 1 578'!K60 -> 36573.611
B61: 12 | D61: ='Займ 776'!D61+'Займ 1 578'!D61 -> 0 | E61: ='Займ 776'!E61+'Займ 1 578'!E61 -> 27503.797 | F61: ='Займ 776'!F61+'Займ 1 578'!F61 -> 37300.539 | G61: ='Займ 776'!G61+'Займ 1 578'!G61 -> 9069.8134 | H61: ='Займ 776'!H61+'Займ 1 578'!H61 -> 1527321.4 | I61: ='Займ 776'!I61+'Займ 1 578'!I61 -> 9069.8134 | J61: ='Займ 776'!J61+'Займ 1 578'!J61 -> 13902.517 | K61: ='Займ 776'!K61+'Займ 1 578'!K61 -> 36573.611
A62: 2030 | B62: 1 | D62: ='Займ 776'!D62+'Займ 1 578'!D62 -> 0 | E62: ='Займ 776'!E62+'Займ 1 578'!E62 -> 27664.236 | F62: ='Займ 776'!F62+'Займ 1 578'!F62 -> 0 | G62: ='Займ 776'!G62+'Займ 1 578'!G62 -> 8909.3746 | H62: ='Займ 776'!H62+'Займ 1 578'!H62 -> 1499657.1 | I62: ='Займ 776'!I62+'Займ 1 578'!I62 -> 8909.3746 | J62: ='Займ 776'!J62+'Займ 1 578'!J62 -> 0 | K62: ='Займ 776'!K62+'Займ 1 578'!K62 -> 36573.611
B63: 2 | D63: ='Займ 776'!D63+'Займ 1 578'!D63 -> 0 | E63: ='Займ 776'!E63+'Займ 1 578'!E63 -> 27825.611 | F63: ='Займ 776'!F63+'Займ 1 578'!F63 -> 0 | G63: ='Займ 776'!G63+'Займ 1 578'!G63 -> 8747.9999 | H63: ='Займ 776'!H63+'Займ 1 578'!H63 -> 1471831.5 | I63: ='Займ 776'!I63+'Займ 1 578'!I63 -> 8747.9999 | J63: ='Займ 776'!J63+'Займ 1 578'!J63 -> 0 | K63: ='Займ 776'!K63+'Займ 1 578'!K63 -> 36573.611
B64: 3 | D64: ='Займ 776'!D64+'Займ 1 578'!D64 -> 0 | E64: ='Займ 776'!E64+'Займ 1 578'!E64 -> 27987.927 | F64: ='Займ 776'!F64+'Займ 1 578'!F64 -> 0 | G64: ='Займ 776'!G64+'Займ 1 578'!G64 -> 8585.6838 | H64: ='Займ 776'!H64+'Займ 1 578'!H64 -> 1443843.6 | I64: ='Займ 776'!I64+'Займ 1 578'!I64 -> 8585.6838 | J64: ='Займ 776'!J64+'Займ 1 578'!J64 -> 0 | K64: ='Займ 776'!K64+'Займ 1 578'!K64 -> 36573.611
B65: 4 | D65: ='Займ 776'!D65+'Займ 1 578'!D65 -> 0 | E65: ='Займ 776'!E65+'Займ 1 578'!E65 -> 28151.19 | F65: ='Займ 776'!F65+'Займ 1 578'!F65 -> 0 | G65: ='Займ 776'!G65+'Займ 1 578'!G65 -> 8422.4209 | H65: ='Займ 776'!H65+'Займ 1 578'!H65 -> 1415692.4 | I65: ='Займ 776'!I65+'Займ 1 578'!I65 -> 8422.4209 | J65: ='Займ 776'!J65+'Займ 1 578'!J65 -> 0 | K65: ='Займ 776'!K65+'Займ 1 578'!K65 -> 36573.611
B66: 5 | D66: ='Займ 776'!D66+'Займ 1 578'!D66 -> 0 | E66: ='Займ 776'!E66+'Займ 1 578'!E66 -> 28315.405 | F66: ='Займ 776'!F66+'Займ 1 578'!F66 -> 0 | G66: ='Займ 776'!G66+'Займ 1 578'!G66 -> 8258.2056 | H66: ='Займ 776'!H66+'Займ 1 578'!H66 -> 1387377 | I66: ='Займ 776'!I66+'Займ 1 578'!I66 -> 8258.2056 | J66: ='Займ 776'!J66+'Займ 1 578'!J66 -> 0 | K66: ='Займ 776'!K66+'Займ 1 578'!K66 -> 36573.611
B67: 6 | D67: ='Займ 776'!D67+'Займ 1 578'!D67 -> 0 | E67: ='Займ 776'!E67+'Займ 1 578'!E67 -> 28480.578 | F67: ='Займ 776'!F67+'Займ 1 578'!F67 -> 0 | G67: ='Займ 776'!G67+'Займ 1 578'!G67 -> 8093.0324 | H67: ='Займ 776'!H67+'Займ 1 578'!H67 -> 1358896.4 | I67: ='Займ 776'!I67+'Займ 1 578'!I67 -> 8093.0324 | J67: ='Займ 776'!J67+'Займ 1 578'!J67 -> 0 | K67: ='Займ 776'!K67+'Займ 1 578'!K67 -> 36573.611
B68: 7 | D68: ='Займ 776'!D68+'Займ 1 578'!D68 -> 0 | E68: ='Займ 776'!E68+'Займ 1 578'!E68 -> 28646.715 | F68: ='Займ 776'!F68+'Займ 1 578'!F68 -> 67656.382 | G68: ='Займ 776'!G68+'Займ 1 578'!G68 -> 7926.8957 | H68: ='Займ 776'!H68+'Займ 1 578'!H68 -> 1330249.7 | I68: ='Займ 776'!I68+'Займ 1 578'!I68 -> 7926.8957 | J68: ='Займ 776'!J68+'Займ 1 578'!J68 -> 24010.081 | K68: ='Займ 776'!K68+'Займ 1 578'!K68 -> 36573.611
B69: 8 | D69: ='Займ 776'!D69+'Займ 1 578'!D69 -> 0 | E69: ='Займ 776'!E69+'Займ 1 578'!E69 -> 28813.821 | F69: ='Займ 776'!F69+'Займ 1 578'!F69 -> 67656.382 | G69: ='Займ 776'!G69+'Займ 1 578'!G69 -> 7759.7899 | H69: ='Займ 776'!H69+'Займ 1 578'!H69 -> 1301435.9 | I69: ='Займ 776'!I69+'Займ 1 578'!I69 -> 7759.7899 | J69: ='Займ 776'!J69+'Займ 1 578'!J69 -> 24010.081 | K69: ='Займ 776'!K69+'Займ 1 578'!K69 -> 36573.611
B70: 9 | D70: ='Займ 776'!D70+'Займ 1 578'!D70 -> 0 | E70: ='Займ 776'!E70+'Займ 1 578'!E70 -> 28981.902 | F70: ='Займ 776'!F70+'Займ 1 578'!F70 -> 67656.382 | G70: ='Займ 776'!G70+'Займ 1 578'!G70 -> 7591.7092 | H70: ='Займ 776'!H70+'Займ 1 578'!H70 -> 1272454 | I70: ='Займ 776'!I70+'Займ 1 578'!I70 -> 7591.7092 | J70: ='Займ 776'!J70+'Займ 1 578'!J70 -> 24010.081 | K70: ='Займ 776'!K70+'Займ 1 578'!K70 -> 36573.611
B71: 10 | D71: ='Займ 776'!D71+'Займ 1 578'!D71 -> 0 | E71: ='Займ 776'!E71+'Займ 1 578'!E71 -> 29150.963 | F71: ='Займ 776'!F71+'Займ 1 578'!F71 -> 67656.382 | G71: ='Займ 776'!G71+'Займ 1 578'!G71 -> 7422.6482 | H71: ='Займ 776'!H71+'Займ 1 578'!H71 -> 1243303 | I71: ='Займ 776'!I71+'Займ 1 578'!I71 -> 7422.6482 | J71: ='Займ 776'!J71+'Займ 1 578'!J71 -> 24010.081 | K71: ='Займ 776'!K71+'Займ 1 578'!K71 -> 36573.611
B72: 11 | D72: ='Займ 776'!D72+'Займ 1 578'!D72 -> 0 | E72: ='Займ 776'!E72+'Займ 1 578'!E72 -> 29321.01 | F72: ='Займ 776'!F72+'Займ 1 578'!F72 -> 67656.382 | G72: ='Займ 776'!G72+'Займ 1 578'!G72 -> 7252.6009 | H72: ='Займ 776'!H72+'Займ 1 578'!H72 -> 1213982 | I72: ='Займ 776'!I72+'Займ 1 578'!I72 -> 7252.6009 | J72: ='Займ 776'!J72+'Займ 1 578'!J72 -> 24010.081 | K72: ='Займ 776'!K72+'Займ 1 578'!K72 -> 36573.611
B73: 12 | D73: ='Займ 776'!D73+'Займ 1 578'!D73 -> 0 | E73: ='Займ 776'!E73+'Займ 1 578'!E73 -> 29492.049 | F73: ='Займ 776'!F73+'Займ 1 578'!F73 -> 67656.382 | G73: ='Займ 776'!G73+'Займ 1 578'!G73 -> 7081.5616 | H73: ='Займ 776'!H73+'Займ 1 578'!H73 -> 1184489.9 | I73: ='Займ 776'!I73+'Займ 1 578'!I73 -> 7081.5616 | J73: ='Займ 776'!J73+'Займ 1 578'!J73 -> 24010.081 | K73: ='Займ 776'!K73+'Займ 1 578'!K73 -> 36573.611
A74: 2031 | B74: 1 | D74: ='Займ 776'!D74+'Займ 1 578'!D74 -> 0 | E74: ='Займ 776'!E74+'Займ 1 578'!E74 -> 29664.086 | F74: ='Займ 776'!F74+'Займ 1 578'!F74 -> 0 | G74: ='Займ 776'!G74+'Займ 1 578'!G74 -> 15447.64 | H74: ='Займ 776'!H74+'Займ 1 578'!H74 -> 1154825.9 | I74: ='Займ 776'!I74+'Займ 1 578'!I74 -> 15447.64 | J74: ='Займ 776'!J74+'Займ 1 578'!J74 -> 0 | K74: ='Займ 776'!K74+'Займ 1 578'!K74 -> 45111.726
B75: 2 | D75: ='Займ 776'!D75+'Займ 1 578'!D75 -> 0 | E75: ='Займ 776'!E75+'Займ 1 578'!E75 -> 29837.127 | F75: ='Займ 776'!F75+'Займ 1 578'!F75 -> 0 | G75: ='Займ 776'!G75+'Займ 1 578'!G75 -> 15274.6 | H75: ='Займ 776'!H75+'Займ 1 578'!H75 -> 1124988.7 | I75: ='Займ 776'!I75+'Займ 1 578'!I75 -> 15274.6 | J75: ='Займ 776'!J75+'Займ 1 578'!J75 -> 0 | K75: ='Займ 776'!K75+'Займ 1 578'!K75 -> 45111.726
B76: 3 | D76: ='Займ 776'!D76+'Займ 1 578'!D76 -> 0 | E76: ='Займ 776'!E76+'Займ 1 578'!E76 -> 30011.177 | F76: ='Займ 776'!F76+'Займ 1 578'!F76 -> 0 | G76: ='Займ 776'!G76+'Займ 1 578'!G76 -> 15100.55 | H76: ='Займ 776'!H76+'Займ 1 578'!H76 -> 1094977.6 | I76: ='Займ 776'!I76+'Займ 1 578'!I76 -> 15100.55 | J76: ='Займ 776'!J76+'Займ 1 578'!J76 -> 0 | K76: ='Займ 776'!K76+'Займ 1 578'!K76 -> 45111.726
B77: 4 | D77: ='Займ 776'!D77+'Займ 1 578'!D77 -> 0 | E77: ='Займ 776'!E77+'Займ 1 578'!E77 -> 30186.242 | F77: ='Займ 776'!F77+'Займ 1 578'!F77 -> 0 | G77: ='Займ 776'!G77+'Займ 1 578'!G77 -> 14925.484 | H77: ='Займ 776'!H77+'Займ 1 578'!H77 -> 1064791.3 | I77: ='Займ 776'!I77+'Займ 1 578'!I77 -> 14925.484 | J77: ='Займ 776'!J77+'Займ 1 578'!J77 -> 0 | K77: ='Займ 776'!K77+'Займ 1 578'!K77 -> 45111.726
B78: 5 | D78: ='Займ 776'!D78+'Займ 1 578'!D78 -> 0 | E78: ='Займ 776'!E78+'Займ 1 578'!E78 -> 30362.328 | F78: ='Займ 776'!F78+'Займ 1 578'!F78 -> 0 | G78: ='Займ 776'!G78+'Займ 1 578'!G78 -> 14749.398 | H78: ='Займ 776'!H78+'Займ 1 578'!H78 -> 1034429 | I78: ='Займ 776'!I78+'Займ 1 578'!I78 -> 14749.398 | J78: ='Займ 776'!J78+'Займ 1 578'!J78 -> 0 | K78: ='Займ 776'!K78+'Займ 1 578'!K78 -> 45111.726
B79: 6 | D79: ='Займ 776'!D79+'Займ 1 578'!D79 -> 0 | E79: ='Займ 776'!E79+'Займ 1 578'!E79 -> 30539.442 | F79: ='Займ 776'!F79+'Займ 1 578'!F79 -> 0 | G79: ='Займ 776'!G79+'Займ 1 578'!G79 -> 14572.284 | H79: ='Займ 776'!H79+'Займ 1 578'!H79 -> 1003889.5 | I79: ='Займ 776'!I79+'Займ 1 578'!I79 -> 14572.284 | J79: ='Займ 776'!J79+'Займ 1 578'!J79 -> 0 | K79: ='Займ 776'!K79+'Займ 1 578'!K79 -> 45111.726
B80: 7 | D80: ='Займ 776'!D80+'Займ 1 578'!D80 -> 0 | E80: ='Займ 776'!E80+'Займ 1 578'!E80 -> 30717.589 | F80: ='Займ 776'!F80+'Займ 1 578'!F80 -> 76177.348 | G80: ='Займ 776'!G80+'Займ 1 578'!G80 -> 14394.138 | H80: ='Займ 776'!H80+'Займ 1 578'!H80 -> 973171.96 | I80: ='Займ 776'!I80+'Займ 1 578'!I80 -> 14394.138 | J80: ='Займ 776'!J80+'Займ 1 578'!J80 -> 35990.271 | K80: ='Займ 776'!K80+'Займ 1 578'!K80 -> 45111.726
B81: 8 | D81: ='Займ 776'!D81+'Займ 1 578'!D81 -> 0 | E81: ='Займ 776'!E81+'Займ 1 578'!E81 -> 30896.774 | F81: ='Займ 776'!F81+'Займ 1 578'!F81 -> 76177.348 | G81: ='Займ 776'!G81+'Займ 1 578'!G81 -> 14214.952 | H81: ='Займ 776'!H81+'Займ 1 578'!H81 -> 942275.18 | I81: ='Займ 776'!I81+'Займ 1 578'!I81 -> 14214.952 | J81: ='Займ 776'!J81+'Займ 1 578'!J81 -> 35990.271 | K81: ='Займ 776'!K81+'Займ 1 578'!K81 -> 45111.726
B82: 9 | D82: ='Займ 776'!D82+'Займ 1 578'!D82 -> 0 | E82: ='Займ 776'!E82+'Займ 1 578'!E82 -> 31077.006 | F82: ='Займ 776'!F82+'Займ 1 578'!F82 -> 76177.348 | G82: ='Займ 776'!G82+'Займ 1 578'!G82 -> 14034.721 | H82: ='Займ 776'!H82+'Займ 1 578'!H82 -> 911198.18 | I82: ='Займ 776'!I82+'Займ 1 578'!I82 -> 14034.721 | J82: ='Займ 776'!J82+'Займ 1 578'!J82 -> 35990.271 | K82: ='Займ 776'!K82+'Займ 1 578'!K82 -> 45111.726
B83: 10 | D83: ='Займ 776'!D83+'Займ 1 578'!D83 -> 0 | E83: ='Займ 776'!E83+'Займ 1 578'!E83 -> 31258.288 | F83: ='Займ 776'!F83+'Займ 1 578'!F83 -> 76177.348 | G83: ='Займ 776'!G83+'Займ 1 578'!G83 -> 13853.438 | H83: ='Займ 776'!H83+'Займ 1 578'!H83 -> 879939.89 | I83: ='Займ 776'!I83+'Займ 1 578'!I83 -> 13853.438 | J83: ='Займ 776'!J83+'Займ 1 578'!J83 -> 35990.271 | K83: ='Займ 776'!K83+'Займ 1 578'!K83 -> 45111.726
B84: 11 | D84: ='Займ 776'!D84+'Займ 1 578'!D84 -> 0 | E84: ='Займ 776'!E84+'Займ 1 578'!E84 -> 31440.628 | F84: ='Займ 776'!F84+'Займ 1 578'!F84 -> 76177.348 | G84: ='Займ 776'!G84+'Займ 1 578'!G84 -> 13671.098 | H84: ='Займ 776'!H84+'Займ 1 578'!H84 -> 848499.26 | I84: ='Займ 776'!I84+'Займ 1 578'!I84 -> 13671.098 | J84: ='Займ 776'!J84+'Займ 1 578'!J84 -> 35990.271 | K84: ='Займ 776'!K84+'Займ 1 578'!K84 -> 45111.726
B85: 12 | D85: ='Займ 776'!D85+'Займ 1 578'!D85 -> 0 | E85: ='Займ 776'!E85+'Займ 1 578'!E85 -> 31624.032 | F85: ='Займ 776'!F85+'Займ 1 578'!F85 -> 76177.348 | G85: ='Займ 776'!G85+'Займ 1 578'!G85 -> 13487.694 | H85: ='Займ 776'!H85+'Займ 1 578'!H85 -> 816875.23 | I85: ='Займ 776'!I85+'Займ 1 578'!I85 -> 13487.694 | J85: ='Займ 776'!J85+'Займ 1 578'!J85 -> 35990.271 | K85: ='Займ 776'!K85+'Займ 1 578'!K85 -> 45111.726
A86: 2032 | B86: 1 | D86: ='Займ 776'!D86+'Займ 1 578'!D86 -> 0 | E86: ='Займ 776'!E86+'Займ 1 578'!E86 -> 31808.505 | F86: ='Займ 776'!F86+'Займ 1 578'!F86 -> 0 | G86: ='Займ 776'!G86+'Займ 1 578'!G86 -> 13303.221 | H86: ='Займ 776'!H86+'Займ 1 578'!H86 -> 785066.72 | I86: ='Займ 776'!I86+'Займ 1 578'!I86 -> 13303.221 | J86: ='Займ 776'!J86+'Займ 1 578'!J86 -> 0 | K86: ='Займ 776'!K86+'Займ 1 578'!K86 -> 45111.726
B87: 2 | D87: ='Займ 776'!D87+'Займ 1 578'!D87 -> 0 | E87: ='Займ 776'!E87+'Займ 1 578'!E87 -> 31994.055 | F87: ='Займ 776'!F87+'Займ 1 578'!F87 -> 0 | G87: ='Займ 776'!G87+'Займ 1 578'!G87 -> 13117.671 | H87: ='Займ 776'!H87+'Займ 1 578'!H87 -> 753072.67 | I87: ='Займ 776'!I87+'Займ 1 578'!I87 -> 13117.671 | J87: ='Займ 776'!J87+'Займ 1 578'!J87 -> 0 | K87: ='Займ 776'!K87+'Займ 1 578'!K87 -> 45111.726
B88: 3 | D88: ='Займ 776'!D88+'Займ 1 578'!D88 -> 0 | E88: ='Займ 776'!E88+'Займ 1 578'!E88 -> 32180.687 | F88: ='Займ 776'!F88+'Займ 1 578'!F88 -> 0 | G88: ='Займ 776'!G88+'Займ 1 578'!G88 -> 12931.039 | H88: ='Займ 776'!H88+'Займ 1 578'!H88 -> 720891.98 | I88: ='Займ 776'!I88+'Займ 1 578'!I88 -> 12931.039 | J88: ='Займ 776'!J88+'Займ 1 578'!J88 -> 0 | K88: ='Займ 776'!K88+'Займ 1 578'!K88 -> 45111.726
B89: 4 | D89: ='Займ 776'!D89+'Займ 1 578'!D89 -> 0 | E89: ='Займ 776'!E89+'Займ 1 578'!E89 -> 32368.408 | F89: ='Займ 776'!F89+'Займ 1 578'!F89 -> 0 | G89: ='Займ 776'!G89+'Займ 1 578'!G89 -> 12743.319 | H89: ='Займ 776'!H89+'Займ 1 578'!H89 -> 688523.58 | I89: ='Займ 776'!I89+'Займ 1 578'!I89 -> 12743.319 | J89: ='Займ 776'!J89+'Займ 1 578'!J89 -> 0 | K89: ='Займ 776'!K89+'Займ 1 578'!K89 -> 45111.726
B90: 5 | D90: ='Займ 776'!D90+'Займ 1 578'!D90 -> 0 | E90: ='Займ 776'!E90+'Займ 1 578'!E90 -> 32557.223 | F90: ='Займ 776'!F90+'Займ 1 578'!F90 -> 0 | G90: ='Займ 776'!G90+'Займ 1 578'!G90 -> 12554.503 | H90: ='Займ 776'!H90+'Займ 1 578'!H90 -> 655966.35 | I90: ='Займ 776'!I90+'Займ 1 578'!I90 -> 12554.503 | J90: ='Займ 776'!J90+'Займ 1 578'!J90 -> 0 | K90: ='Займ 776'!K90+'Займ 1 578'!K90 -> 45111.726
B91: 6 | D91: ='Займ 776'!D91+'Займ 1 578'!D91 -> 0 | E91: ='Займ 776'!E91+'Займ 1 578'!E91 -> 32747.14 | F91: ='Займ 776'!F91+'Займ 1 578'!F91 -> 0 | G91: ='Займ 776'!G91+'Займ 1 578'!G91 -> 12364.586 | H91: ='Займ 776'!H91+'Займ 1 578'!H91 -> 623219.21 | I91: ='Займ 776'!I91+'Займ 1 578'!I91 -> 12364.586 | J91: ='Займ 776'!J91+'Займ 1 578'!J91 -> 0 | K91: ='Займ 776'!K91+'Займ 1 578'!K91 -> 45111.726
B92: 7 | D92: ='Займ 776'!D92+'Займ 1 578'!D92 -> 0 | E92: ='Займ 776'!E92+'Займ 1 578'!E92 -> 32938.165 | F92: ='Займ 776'!F92+'Займ 1 578'!F92 -> 81684.214 | G92: ='Займ 776'!G92+'Займ 1 578'!G92 -> 12173.561 | H92: ='Займ 776'!H92+'Займ 1 578'!H92 -> 590281.05 | I92: ='Займ 776'!I92+'Займ 1 578'!I92 -> 12173.561 | J92: ='Займ 776'!J92+'Займ 1 578'!J92 -> 30483.405 | K92: ='Займ 776'!K92+'Займ 1 578'!K92 -> 45111.726
B93: 8 | D93: ='Займ 776'!D93+'Займ 1 578'!D93 -> 0 | E93: ='Займ 776'!E93+'Займ 1 578'!E93 -> 33130.305 | F93: ='Займ 776'!F93+'Займ 1 578'!F93 -> 81684.214 | G93: ='Займ 776'!G93+'Займ 1 578'!G93 -> 11981.422 | H93: ='Займ 776'!H93+'Займ 1 578'!H93 -> 557150.74 | I93: ='Займ 776'!I93+'Займ 1 578'!I93 -> 11981.422 | J93: ='Займ 776'!J93+'Займ 1 578'!J93 -> 30483.405 | K93: ='Займ 776'!K93+'Займ 1 578'!K93 -> 45111.726
B94: 9 | D94: ='Займ 776'!D94+'Займ 1 578'!D94 -> 0 | E94: ='Займ 776'!E94+'Займ 1 578'!E94 -> 33323.565 | F94: ='Займ 776'!F94+'Займ 1 578'!F94 -> 81684.214 | G94: ='Займ 776'!G94+'Займ 1 578'!G94 -> 11788.161 | H94: ='Займ 776'!H94+'Займ 1 578'!H94 -> 523827.18 | I94: ='Займ 776'!I94+'Займ 1 578'!I94 -> 11788.161 | J94: ='Займ 776'!J94+'Займ 1 578'!J94 -> 30483.405 | K94: ='Займ 776'!K94+'Займ 1 578'!K94 -> 45111.726
B95: 10 | D95: ='Займ 776'!D95+'Займ 1 578'!D95 -> 0 | E95: ='Займ 776'!E95+'Займ 1 578'!E95 -> 33517.952 | F95: ='Займ 776'!F95+'Займ 1 578'!F95 -> 81684.214 | G95: ='Займ 776'!G95+'Займ 1 578'!G95 -> 11593.774 | H95: ='Займ 776'!H95+'Займ 1 578'!H95 -> 490309.22 | I95: ='Займ 776'!I95+'Займ 1 578'!I95 -> 11593.774 | J95: ='Займ 776'!J95+'Займ 1 578'!J95 -> 30483.405 | K95: ='Займ 776'!K95+'Займ 1 578'!K95 -> 45111.726
B96: 11 | D96: ='Займ 776'!D96+'Займ 1 578'!D96 -> 0 | E96: ='Займ 776'!E96+'Займ 1 578'!E96 -> 33713.474 | F96: ='Займ 776'!F96+'Займ 1 578'!F96 -> 81684.214 | G96: ='Займ 776'!G96+'Займ 1 578'!G96 -> 11398.253 | H96: ='Займ 776'!H96+'Займ 1 578'!H96 -> 456595.75 | I96: ='Займ 776'!I96+'Займ 1 578'!I96 -> 11398.253 | J96: ='Займ 776'!J96+'Займ 1 578'!J96 -> 30483.405 | K96: ='Займ 776'!K96+'Займ 1 578'!K96 -> 45111.726
B97: 12 | D97: ='Займ 776'!D97+'Займ 1 578'!D97 -> 0 | E97: ='Займ 776'!E97+'Займ 1 578'!E97 -> 33910.136 | F97: ='Займ 776'!F97+'Займ 1 578'!F97 -> 81684.214 | G97: ='Займ 776'!G97+'Займ 1 578'!G97 -> 11201.591 | H97: ='Займ 776'!H97+'Займ 1 578'!H97 -> 422685.61 | I97: ='Займ 776'!I97+'Займ 1 578'!I97 -> 11201.591 | J97: ='Займ 776'!J97+'Займ 1 578'!J97 -> 30483.405 | K97: ='Займ 776'!K97+'Займ 1 578'!K97 -> 45111.726
A98: 2033 | B98: 1 | D98: ='Займ 776'!D98+'Займ 1 578'!D98 -> 0 | E98: ='Займ 776'!E98+'Займ 1 578'!E98 -> 34107.945 | F98: ='Займ 776'!F98+'Займ 1 578'!F98 -> 0 | G98: ='Займ 776'!G98+'Займ 1 578'!G98 -> 11003.781 | H98: ='Займ 776'!H98+'Займ 1 578'!H98 -> 388577.67 | I98: ='Займ 776'!I98+'Займ 1 578'!I98 -> 11003.781 | J98: ='Займ 776'!J98+'Займ 1 578'!J98 -> 0 | K98: ='Займ 776'!K98+'Займ 1 578'!K98 -> 45111.726
B99: 2 | D99: ='Займ 776'!D99+'Займ 1 578'!D99 -> 0 | E99: ='Займ 776'!E99+'Займ 1 578'!E99 -> 34306.908 | F99: ='Займ 776'!F99+'Займ 1 578'!F99 -> 0 | G99: ='Займ 776'!G99+'Займ 1 578'!G99 -> 10804.818 | H99: ='Займ 776'!H99+'Займ 1 578'!H99 -> 354270.76 | I99: ='Займ 776'!I99+'Займ 1 578'!I99 -> 10804.818 | J99: ='Займ 776'!J99+'Займ 1 578'!J99 -> 0 | K99: ='Займ 776'!K99+'Займ 1 578'!K99 -> 45111.726
B100: 3 | D100: ='Займ 776'!D100+'Займ 1 578'!D100 -> 0 | E100: ='Займ 776'!E100+'Займ 1 578'!E100 -> 34507.031 | F100: ='Займ 776'!F100+'Займ 1 578'!F100 -> 0 | G100: ='Займ 776'!G100+'Займ 1 578'!G100 -> 10604.695 | H100: ='Займ 776'!H100+'Займ 1 578'!H100 -> 319763.73 | I100: ='Займ 776'!I100+'Займ 1 578'!I100 -> 10604.695 | J100: ='Займ 776'!J100+'Займ 1 578'!J100 -> 0 | K100: ='Займ 776'!K100+'Займ 1 578'!K100 -> 45111.726
B101: 4 | D101: ='Займ 776'!D101+'Займ 1 578'!D101 -> 0 | E101: ='Займ 776'!E101+'Займ 1 578'!E101 -> 34708.322 | F101: ='Займ 776'!F101+'Займ 1 578'!F101 -> 0 | G101: ='Займ 776'!G101+'Займ 1 578'!G101 -> 10403.404 | H101: ='Займ 776'!H101+'Займ 1 578'!H101 -> 285055.41 | I101: ='Займ 776'!I101+'Займ 1 578'!I101 -> 10403.404 | J101: ='Займ 776'!J101+'Займ 1 578'!J101 -> 0 | K101: ='Займ 776'!K101+'Займ 1 578'!K101 -> 45111.726
B102: 5 | D102: ='Займ 776'!D102+'Займ 1 578'!D102 -> 0 | E102: ='Займ 776'!E102+'Займ 1 578'!E102 -> 34910.788 | F102: ='Займ 776'!F102+'Займ 1 578'!F102 -> 0 | G102: ='Займ 776'!G102+'Займ 1 578'!G102 -> 10200.939 | H102: ='Займ 776'!H102+'Займ 1 578'!H102 -> 250144.62 | I102: ='Займ 776'!I102+'Займ 1 578'!I102 -> 10200.939 | J102: ='Займ 776'!J102+'Займ 1 578'!J102 -> 0 | K102: ='Займ 776'!K102+'Займ 1 578'!K102 -> 45111.726
B103: 6 | D103: ='Займ 776'!D103+'Займ 1 578'!D103 -> 0 | E103: ='Займ 776'!E103+'Займ 1 578'!E103 -> 35114.434 | F103: ='Займ 776'!F103+'Займ 1 578'!F103 -> 0 | G103: ='Займ 776'!G103+'Займ 1 578'!G103 -> 9997.2924 | H103: ='Займ 776'!H103+'Займ 1 578'!H103 -> 215030.19 | I103: ='Займ 776'!I103+'Займ 1 578'!I103 -> 9997.2924 | J103: ='Займ 776'!J103+'Займ 1 578'!J103 -> 0 | K103: ='Займ 776'!K103+'Займ 1 578'!K103 -> 45111.726
B104: 7 | D104: ='Займ 776'!D104+'Займ 1 578'!D104 -> 0 | E104: ='Займ 776'!E104+'Займ 1 578'!E104 -> 35319.268 | F104: ='Займ 776'!F104+'Займ 1 578'!F104 -> 70447.602 | G104: ='Займ 776'!G104+'Займ 1 578'!G104 -> 9792.4582 | H104: ='Займ 776'!H104+'Займ 1 578'!H104 -> 179710.92 | I104: ='Займ 776'!I104+'Займ 1 578'!I104 -> 9792.4582 | J104: ='Займ 776'!J104+'Займ 1 578'!J104 -> 19775.85 | K104: ='Займ 776'!K104+'Займ 1 578'!K104 -> 45111.726
...

Sheet Займ 776
A1: =Panel!A1
A2: =Panel!A2 -> Строительство ГЭС -5 МВТ
A4: ФИНАНСОВЫЕ ИЗДЕРЖКИ
A6: РАСЧЕТ ГРАФИКА ПОГАШЕНИЯ ЗАЙМА | E6: ='Инвестиции'!$G$20 -> 0.32976674
A8: Ставка на первые три года | C8: =C9*50% -> 0.07
A9: Ставка на последующий период | C9: 0.14
A10: Срок | C10: 81 | D10: мес.
A12: в тыс. тенге, если не указано иное
A13: Год | B13: Мес | C13: Сумма осн.долга на начало месяца | D13: Сумма транша полученного | E13: Выплата осн долга | F13: Выплата осн долга | G13: Начисление вознаграждения | H13: Сумма осн.долга на конец месяца | I13: Выплата вознаграждения | J13: Выплата вознаграждения | K13: Ежемесячный платеж
A14: 2026 | B14: 1 | D14: =('A-0'!O22)*('Инвестиции'!$G$20) -> 75462.034 | H14: =D14 -> 75462.034 | I14: =G14
B15: 2 | D15: =('A-0'!P22)*('Инвестиции'!$G$20) -> 63756.698 | E15: =(1+$C$8/12)*E14 -> 0 | H15: =H14+D15 -> 139218.73 | I15: =G15
B16: 3 | D16: =('A-0'!Q22)*('Инвестиции'!$G$20) -> 63756.698 | E16: =(1+$C$8/12)*E15 -> 0 | H16: =H15+D16 -> 202975.43 | I16: =G16
B17: 4 | D17: =('A-0'!R22)*('Инвестиции'!$G$20) -> 63756.698 | E17: =(1+$C$8/12)*E16 -> 0 | G17: =H17*$C$8/12 -> 1555.9374 | H17: =H16+D17 -> 266732.13 | I17: =G17 -> 1555.9374 | J17: =I17 -> 1555.9374 | K17: =I17 -> 1555.9374
B18: 5 | D18: =('A-0'!S22)*('Инвестиции'!$G$20) -> 63756.698 | E18: =(1+$C$8/12)*E17 -> 0 | G18: =H18*$C$8/12 -> 1927.8515 | H18: =H17+D18 -> 330488.83 | I18: =G18 -> 1927.8515 | J18: =I18 -> 1927.8515 | K18: =I18 -> 1927.8515
B19: 6 | D19: =('A-0'!T22)*('Инвестиции'!$G$20) -> 63756.698 | E19: =(1+$C$8/12)*E18 -> 0 | G19: =H19*$C$8/12 -> 2299.7656 | H19: =H18+D19 -> 394245.53 | I19: =G19 -> 2299.7656 | J19: =I19 -> 2299.7656 | K19: =I19 -> 2299.7656
B20: 7 | D20: =('A-0'!U22)*('Инвестиции'!$G$20) -> 63756.698 | E20: =(1+$C$8/12)*E19 -> 0 | G20: =H20*$C$8/12 -> 2671.6796 | H20: =H19+D20 -> 458002.22 | I20: =G20 -> 2671.6796 | J20: =I20 -> 2671.6796 | K20: =I20 -> 2671.6796
B21: 8 | D21: =('A-0'!V22)*('Инвестиции'!$G$20) -> 63756.698 | E21: =(1+$C$8/12)*E20 -> 0 | G21: =H21*$C$8/12 -> 3043.5937 | H21: =H20+D21 -> 521758.92 | I21: =G21 -> 3043.5937 | J21: =I21 -> 3043.5937 | K21: =I21 -> 3043.5937
B22: 9 | D22: =('A-0'!W22)*('Инвестиции'!$G$20) -> 63756.698 | E22: =(1+$C$8/12)*E21 -> 0 | G22: =H22*$C$8/12 -> 3415.5078 | H22: =H21+D22 -> 585515.62 | I22: =G22 -> 3415.5078 | J22: =I22 -> 3415.5078 | K22: =I22 -> 3415.5078
B23: 10 | D23: =('A-0'!X22)*('Инвестиции'!$G$20) -> 63756.698 | E23: =(1+$C$8/12)*E22 -> 0 | G23: =H23*$C$8/12 -> 3787.4219 | H23: =H22+D23 -> 649272.32 | I23: =G23 -> 3787.4219 | J23: =I23 -> 3787.4219 | K23: =I23 -> 3787.4219
B24: 11 | D24: =('A-0'!Y22)*('Инвестиции'!$G$20) -> 63756.698 | E24: =(1+$C$8/12)*E23 -> 0 | G24: =H24*$C$8/12 -> 4159.3359 | H24: =H23+D24 -> 713029.02 | I24: =G24 -> 4159.3359 | J24: =I24 -> 4159.3359 | K24: =I24 -> 4159.3359
B25: 12 | D25: =('A-0'!Z22)*('Инвестиции'!$G$20) -> 63756.698 | E25: =(1+$C$8/12)*E24 -> 0 | G25: =H25*$C$8/12 -> 4531.25 | H25: =H24+D25 -> 776785.71 | I25: =G25 -> 4531.25 | J25: =I25 -> 4531.25 | K25: =I25 -> 4531.25
A26: 2027 | B26: 1 | E26: =(1+$C$8/12)*E25 -> 0 | G26: =H26*$C$8/12 -> 4531.25 | H26: =H25-E26 -> 776785.71 | I26: =G26 -> 4531.25 | K26: =I26 -> 4531.25
B27: 2 | E27: =(1+$C$8/12)*E26 -> 0 | G27: =H27*$C$8/12 -> 4531.25 | H27: =H26-E27 -> 776785.71 | I27: =G27 -> 4531.25 | K27: =I27 -> 4531.25
B28: 3 | G28: =H28*$C$8/12 -> 4531.25 | H28: =H27-E28 -> 776785.71 | I28: =G28 -> 4531.25 | K28: =I28 -> 4531.25
B29: 4 | E29: =K29*((1+$C$8/12)^(-C10)) -> 7529.5106 | G29: =K29-E29 -> 4531.25 | H29: =H28-E29 -> 769256.2 | I29: =G29 -> 4531.25 | K29: =($C$8/12)/(1-(1+$C$8/12)^(-$C$10))*$H$27 -> 12060.761
B30: 5 | E30: =(1+$C$8/12)*E29 -> 7573.4327 | G30: =K30-E30 -> 4487.3279 | H30: =H29-E30 -> 761682.77 | I30: =G30 -> 4487.3279 | K30: =($C$8/12)/(1-(1+$C$8/12)^(-$C$10))*$H$27 -> 12060.761
B31: 6 | E31: =(1+$C$8/12)*E30 -> 7617.6111 | G31: =K31-E31 -> 4443.1495 | H31: =H30-E31 -> 754065.16 | I31: =G31 -> 4443.1495 | K31: =($C$8/12)/(1-(1+$C$8/12)^(-$C$10))*$H$27 -> 12060.761
B32: 7 | E32: =(1+$C$8/12)*E31 -> 7662.0472 | F32: =SUM(E29:E37)/6*N32 -> 8092.9921 | G32: =K32-E32 -> 4398.7134 | H32: =H31-E32 -> 746403.11 | I32: =G32 -> 4398.7134 | J32: =SUM(I26:I37)/6*N32 -> 6156.744 | K32: =($C$8/12)/(1-(1+$C$8/12)^(-$C$10))*$H$27 -> 12060.761 | M32: Фактическая выплата в 2026 | N32: 0.7
B33: 8 | E33: =(1+$C$8/12)*E32 -> 7706.7424 | F33: =F32 -> 8092.9921 | G33: =K33-E33 -> 4354.0182 | H33: =H32-E33 -> 738696.37 | I33: =G33 -> 4354.0182 | J33: =J32 -> 6156.744 | K33: =($C$8/12)/(1-(1+$C$8/12)^(-$C$10))*$H$27 -> 12060.761 | M33: Фактическая выплата в 2027 | N33: 0.7
B34: 9 | E34: =(1+$C$8/12)*E33 -> 7751.6984 | F34: =F33 -> 8092.9921 | G34: =K34-E34 -> 4309.0622 | H34: =H33-E34 -> 730944.67 | I34: =G34 -> 4309.0622 | J34: =J33 -> 6156.744 | K34: =($C$8/12)/(1-(1+$C$8/12)^(-$C$10))*$H$27 -> 12060.761 | M34: Фактическая выплата в 2028 | N34: 0.7
B35: 10 | E35: =(1+$C$8/12)*E34 -> 7796.9167 | F35: =F34 -> 8092.9921 | G35: =K35-E35 -> 4263.8439 | H35: =H34-E35 -> 723147.76 | I35: =G35 -> 4263.8439 | J35: =J34 -> 6156.744 | K35: =($C$8/12)/(1-(1+$C$8/12)^(-$C$10))*$H$27 -> 12060.761
B36: 11 | E36: =(1+$C$8/12)*E35 -> 7842.3987 | F36: =F35 -> 8092.9921 | G36: =K36-E36 -> 4218.3619 | H36: =H35-E36 -> 715305.36 | I36: =G36 -> 4218.3619 | J36: =J35 -> 6156.744 | K36: =($C$8/12)/(1-(1+$C$8/12)^(-$C$10))*$H$27 -> 12060.761
B37: 12 | E37: =(1+$C$8/12)*E36 -> 7888.146 | F37: =F36 -> 8092.9921 | G37: =K37-E37 -> 4172.6146 | H37: =H36-E37 -> 707417.21 | I37: =G37 -> 4172.6146 | J37: =J36 -> 6156.744 | K37: =($C$8/12)/(1-(1+$C$8/12)^(-$C$10))*$H$27 -> 12060.761
A38: 2028 | B38: 1 | E38: =(1+$C$8/12)*E37 -> 7934.1602 | G38: =K38-E38 -> 4126.6004 | H38: =H37-E38 -> 699483.05 | I38: =G38 -> 4126.6004 | K38: =($C$8/12)/(1-(1+$C$8/12)^(-$C$10))*$H$27 -> 12060.761
B39: 2 | E39: =(1+$C$8/12)*E38 -> 7980.4428 | G39: =K39-E39 -> 4080.3178 | H39: =H38-E39 -> 691502.61 | I39: =G39 -> 4080.3178 | K39: =($C$8/12)/(1-(1+$C$8/12)^(-$C$10))*$H$27 -> 12060.761
B40: 3 | E40: =(1+$C$8/12)*E39 -> 8026.9954 | G40: =K40-E40 -> 4033.7652 | H40: =H39-E40 -> 683475.61 | I40: =G40 -> 4033.7652 | K40: =($C$8/12)/(1-(1+$C$8/12)^(-$C$10))*$H$27 -> 12060.761
B41: 4 | E41: =(1+$C$8/12)*E40 -> 8073.8195 | G41: =K41-E41 -> 3986.9411 | H41: =H40-E41 -> 675401.79 | I41: =G41 -> 3986.9411 | K41: =($C$8/12)/(1-(1+$C$8/12)^(-$C$10))*$H$27 -> 12060.761
B42: 5 | E42: =(1+$C$8/12)*E41 -> 8120.9168 | G42: =K42-E42 -> 3939.8438 | H42: =H41-E42 -> 667280.88 | I42: =G42 -> 3939.8438 | K42: =($C$8/12)/(1-(1+$C$8/12)^(-$C$10))*$H$27 -> 12060.761
B43: 6 | E43: =(1+$C$8/12)*E42 -> 8168.2888 | G43: =K43-E43 -> 3892.4718 | H43: =H42-E43 -> 659112.59 | I43: =G43 -> 3892.4718 | K43: =($C$8/12)/(1-(1+$C$8/12)^(-$C$10))*$H$27 -> 12060.761
B44: 7 | E44: =(1+$C$8/12)*E43 -> 8215.9372 | F44: =SUM(E38:E49)/6*N33 -> 11471.222 | G44: =K44-E44 -> 3844.8234 | H44: =H43-E44 -> 650896.65 | I44: =G44 -> 3844.8234 | J44: =SUM(I38:I49)/6*N33 -> 5413.8432 | K44: =($C$8/12)/(1-(1+$C$8/12)^(-$C$10))*$H$27 -> 12060.761
B45: 8 | E45: =(1+$C$8/12)*E44 -> 8263.8635 | F45: =F44 -> 11471.222 | G45: =K45-E45 -> 3796.8971 | H45: =H44-E45 -> 642632.79 | I45: =G45 -> 3796.8971 | J45: =J44 -> 5413.8432 | K45: =($C$8/12)/(1-(1+$C$8/12)^(-$C$10))*$H$27 -> 12060.761
B46: 9 | E46: =(1+$C$8/12)*E45 -> 8312.0693 | F46: =F45 -> 11471.222 | G46: =K46-E46 -> 3748.6913 | H46: =H45-E46 -> 634320.72 | I46: =G46 -> 3748.6913 | J46: =J45 -> 5413.8432 | K46: =($C$8/12)/(1-(1+$C$8/12)^(-$C$10))*$H$27 -> 12060.761
B47: 10 | E47: =(1+$C$8/12)*E46 -> 8360.5564 | F47: =F46 -> 11471.222 | G47: =K47-E47 -> 3700.2042 | H47: =H46-E47 -> 625960.16 | I47: =G47 -> 3700.2042 | J47: =J46 -> 5413.8432 | K47: =($C$8/12)/(1-(1+$C$8/12)^(-$C$10))*$H$27 -> 12060.761
B48: 11 | E48: =(1+$C$8/12)*E47 -> 8409.3263 | F48: =F47 -> 11471.222 | G48: =K48-E48 -> 3651.4343 | H48: =H47-E48 -> 617550.83 | I48: =G48 -> 3651.4343 | J48: =J47 -> 5413.8432 | K48: =($C$8/12)/(1-(1+$C$8/12)^(-$C$10))*$H$27 -> 12060.761
B49: 12 | E49: =(1+$C$8/12)*E48 -> 8458.3807 | F49: =F48 -> 11471.222 | G49: =K49-E49 -> 3602.3799 | H49: =H48-E49 -> 609092.45 | I49: =G49 -> 3602.3799 | J49: =J48 -> 5413.8432 | K49: =($C$8/12)/(1-(1+$C$8/12)^(-$C$10))*$H$27 -> 12060.761
A50: 2029 | B50: 1 | E50: =(1+$C$8/12)*E49 -> 8507.7213 | G50: =K50-E50 -> 3553.0393 | H50: =H49-E50 -> 600584.73 | I50: =G50 -> 3553.0393 | K50: =($C$8/12)/(1-(1+$C$8/12)^(-$C$10))*$H$27 -> 12060.761
B51: 2 | E51: =(1+$C$8/12)*E50 -> 8557.3497 | G51: =K51-E51 -> 3503.4109 | H51: =H50-E51 -> 592027.38 | I51: =G51 -> 3503.4109 | K51: =($C$8/12)/(1-(1+$C$8/12)^(-$C$10))*$H$27 -> 12060.761
B52: 3 | E52: =(1+$C$8/12)*E51 -> 8607.2675 | G52: =K52-E52 -> 3453.4931 | H52: =H51-E52 -> 583420.11 | I52: =G52 -> 3453.4931 | K52: =($C$8/12)/(1-(1+$C$8/12)^(-$C$10))*$H$27 -> 12060.761
B53: 4 | E53: =(1+$C$8/12)*E52 -> 8657.4766 | G53: =K53-E53 -> 3403.284 | H53: =H52-E53 -> 574762.64 | I53: =G53 -> 3403.284 | K53: =($C$8/12)/(1-(1+$C$8/12)^(-$C$10))*$H$27 -> 12060.761
B54: 5 | E54: =(1+$C$8/12)*E53 -> 8707.9785 | G54: =K54-E54 -> 3352.7821 | H54: =H53-E54 -> 566054.66 | I54: =G54 -> 3352.7821 | K54: =($C$8/12)/(1-(1+$C$8/12)^(-$C$10))*$H$27 -> 12060.761
B55: 6 | E55: =(1+$C$8/12)*E54 -> 8758.7751 | G55: =K55-E55 -> 3301.9855 | H55: =H54-E55 -> 557295.88 | I55: =G55 -> 3301.9855 | K55: =($C$8/12)/(1-(1+$C$8/12)^(-$C$10))*$H$27 -> 12060.761
B56: 7 | E56: =(1+$C$8/12)*E55 -> 8809.8679 | F56: =SUM(E50:E61)/6*N34 -> 12300.477 | G56: =K56-E56 -> 3250.8927 | H56: =H55-E56 -> 548486.02 | I56: =G56 -> 3250.8927 | J56: =SUM(I50:I61)/6*N34 -> 4584.5876 | K56: =($C$8/12)/(1-(1+$C$8/12)^(-$C$10))*$H$27 -> 12060.761
B57: 8 | E57: =(1+$C$8/12)*E56 -> 8861.2588 | F57: =F56 -> 12300.477 | G57: =K57-E57 -> 3199.5018 | H57: =H56-E57 -> 539624.76 | I57: =G57 -> 3199.5018 | J57: =J56 -> 4584.5876 | K57: =($C$8/12)/(1-(1+$C$8/12)^(-$C$10))*$H$27 -> 12060.761
B58: 9 | E58: =(1+$C$8/12)*E57 -> 8912.9495 | F58: =F57 -> 12300.477 | G58: =K58-E58 -> 3147.8111 | H58: =H57-E58 -> 530711.81 | I58: =G58 -> 3147.8111 | J58: =J57 -> 4584.5876 | K58: =($C$8/12)/(1-(1+$C$8/12)^(-$C$10))*$H$27 -> 12060.761
B59: 10 | E59: =(1+$C$8/12)*E58 -> 8964.9417 | F59: =F58 -> 12300.477 | G59: =K59-E59 -> 3095.8189 | H59: =H58-E59 -> 521746.87 | I59: =G59 -> 3095.8189 | J59: =J58 -> 4584.5876 | K59: =($C$8/12)/(1-(1+$C$8/12)^(-$C$10))*$H$27 -> 12060.761
B60: 11 | E60: =(1+$C$8/12)*E59 -> 9017.2372 | F60: =F59 -> 12300.477 | G60: =K60-E60 -> 3043.5234 | H60: =H59-E60 -> 512729.63 | I60: =G60 -> 3043.5234 | J60: =J59 -> 4584.5876 | K60: =($C$8/12)/(1-(1+$C$8/12)^(-$C$10))*$H$27 -> 12060.761
B61: 12 | E61: =(1+$C$8/12)*E60 -> 9069.8378 | F61: =F60 -> 12300.477 | G61: =K61-E61 -> 2990.9228 | H61: =H60-E61 -> 503659.79 | I61: =G61 -> 2990.9228 | J61: =J60 -> 4584.5876 | K61: =($C$8/12)/(1-(1+$C$8/12)^(-$C$10))*$H$27 -> 12060.761
A62: 2030 | B62: 1 | E62: =(1+$C$8/12)*E61 -> 9122.7451 | G62: =K62-E62 -> 2938.0155 | H62: =H61-E62 -> 494537.05 | I62: =G62 -> 2938.0155 | K62: =($C$8/12)/(1-(1+$C$8/12)^(-$C$10))*$H$27 -> 12060.761
B63: 2 | E63: =(1+$C$8/12)*E62 -> 9175.9612 | G63: =K63-E63 -> 2884.7994 | H63: =H62-E63 -> 485361.09 | I63: =G63 -> 2884.7994 | K63: =($C$8/12)/(1-(1+$C$8/12)^(-$C$10))*$H$27 -> 12060.761
B64: 3 | E64: =(1+$C$8/12)*E63 -> 9229.4876 | G64: =K64-E64 -> 2831.273 | H64: =H63-E64 -> 476131.6 | I64: =G64 -> 2831.273 | K64: =($C$8/12)/(1-(1+$C$8/12)^(-$C$10))*$H$27 -> 12060.761
B65: 4 | E65: =(1+$C$8/12)*E64 -> 9283.3263 | G65: =K65-E65 -> 2777.4343 | H65: =H64-E65 -> 466848.27 | I65: =G65 -> 2777.4343 | K65: =($C$8/12)/(1-(1+$C$8/12)^(-$C$10))*$H$27 -> 12060.761
B66: 5 | E66: =(1+$C$8/12)*E65 -> 9337.479 | G66: =K66-E66 -> 2723.2816 | H66: =H65-E66 -> 457510.79 | I66: =G66 -> 2723.2816 | K66: =($C$8/12)/(1-(1+$C$8/12)^(-$C$10))*$H$27 -> 12060.761
B67: 6 | E67: =(1+$C$8/12)*E66 -> 9391.9476 | G67: =K67-E67 -> 2668.813 | H67: =H66-E67 -> 448118.84 | I67: =G67 -> 2668.813 | K67: =($C$8/12)/(1-(1+$C$8/12)^(-$C$10))*$H$27 -> 12060.761
B68: 7 | E68: =(1+$C$8/12)*E67 -> 9446.734 | F68: =SUM(E62:E73)/6+SUM(E26:E37)/6*(100%-N32) -> 22310.825 | G68: =K68-E68 -> 2614.0266 | H68: =H67-E68 -> 438672.11 | I68: =G68 -> 2614.0266 | J68: =SUM(I62:I73)/6+SUM(I26:I37)/6*(100%-N32) -> 7917.7262 | K68: =($C$8/12)/(1-(1+$C$8/12)^(-$C$10))*$H$27 -> 12060.761
B69: 8 | E69: =(1+$C$8/12)*E68 -> 9501.84 | F69: =F68 -> 22310.825 | G69: =K69-E69 -> 2558.9206 | H69: =H68-E69 -> 429170.27 | I69: =G69 -> 2558.9206 | J69: =J68 -> 7917.7262 | K69: =($C$8/12)/(1-(1+$C$8/12)^(-$C$10))*$H$27 -> 12060.761
B70: 9 | E70: =(1+$C$8/12)*E69 -> 9557.2674 | F70: =F69 -> 22310.825 | G70: =K70-E70 -> 2503.4932 | H70: =H69-E70 -> 419613 | I70: =G70 -> 2503.4932 | J70: =J69 -> 7917.7262 | K70: =($C$8/12)/(1-(1+$C$8/12)^(-$C$10))*$H$27 -> 12060.761
B71: 10 | E71: =(1+$C$8/12)*E70 -> 9613.0181 | F71: =F70 -> 22310.825 | G71: =K71-E71 -> 2447.7425 | H71: =H70-E71 -> 409999.99 | I71: =G71 -> 2447.7425 | J71: =J70 -> 7917.7262 | K71: =($C$8/12)/(1-(1+$C$8/12)^(-$C$10))*$H$27 -> 12060.761
B72: 11 | E72: =(1+$C$8/12)*E71 -> 9669.094 | F72: =F71 -> 22310.825 | G72: =K72-E72 -> 2391.6666 | H72: =H71-E72 -> 400330.89 | I72: =G72 -> 2391.6666 | J72: =J71 -> 7917.7262 | K72: =($C$8/12)/(1-(1+$C$8/12)^(-$C$10))*$H$27 -> 12060.761
B73: 12 | E73: =(1+$C$8/12)*E72 -> 9725.4971 | F73: =F72 -> 22310.825 | G73: =K73-E73 -> 2335.2635 | H73: =H72-E73 -> 390605.39 | I73: =G73 -> 2335.2635 | J73: =J72 -> 7917.7262 | K73: =($C$8/12)/(1-(1+$C$8/12)^(-$C$10))*$H$27 -> 12060.761
A74: 2031 | B74: 1 | E74: =(1+$C$8/12)*E73 -> 9782.2291 | G74: =K74-E74 -> 5094.118 | H74: =H73-E74 -> 380823.17 | I74: =G74 -> 5094.118 | K74: =($C$9/12)/(1-(1+$C$9/12)^(-$C$10))*$H$27 -> 14876.347
B75: 2 | E75: =(1+$C$8/12)*E74 -> 9839.2921 | G75: =K75-E75 -> 5037.055 | H75: =H74-E75 -> 370983.87 | I75: =G75 -> 5037.055 | K75: =($C$9/12)/(1-(1+$C$9/12)^(-$C$10))*$H$27 -> 14876.347
B76: 3 | E76: =(1+$C$8/12)*E75 -> 9896.688 | G76: =K76-E76 -> 4979.6591 | H76: =H75-E76 -> 361087.19 | I76: =G76 -> 4979.6591 | K76: =($C$9/12)/(1-(1+$C$9/12)^(-$C$10))*$H$27 -> 14876.347
B77: 4 | E77: =(1+$C$8/12)*E76 -> 9954.4187 | G77: =K77-E77 -> 4921.9284 | H77: =H76-E77 -> 351132.77 | I77: =G77 -> 4921.9284 | K77: =($C$9/12)/(1-(1+$C$9/12)^(-$C$10))*$H$27 -> 14876.347
B78: 5 | E78: =(1+$C$8/12)*E77 -> 10012.486 | G78: =K78-E78 -> 4863.861 | H78: =H77-E78 -> 341120.28 | I78: =G78 -> 4863.861 | K78: =($C$9/12)/(1-(1+$C$9/12)^(-$C$10))*$H$27 -> 14876.347
B79: 6 | E79: =(1+$C$8/12)*E78 -> 10070.892 | G79: =K79-E79 -> 4805.4548 | H79: =H78-E79 -> 331049.39 | I79: =G79 -> 4805.4548 | K79: =($C$9/12)/(1-(1+$C$9/12)^(-$C$10))*$H$27 -> 14876.347
B80: 7 | E80: =(1+$C$8/12)*E79 -> 10129.639 | F80: =SUM(E74:E85)/6+SUM(E38:E49)/6*(100%-N33) -> 25120.756 | G80: =K80-E80 -> 4746.708 | H80: =H79-E80 -> 320919.75 | I80: =G80 -> 4746.708 | J80: =SUM(I74:I85)/6+SUM(I38:I49)/6*(100%-N33) -> 11868.395 | K80: =($C$9/12)/(1-(1+$C$9/12)^(-$C$10))*$H$27 -> 14876.347
B81: 8 | E81: =(1+$C$8/12)*E80 -> 10188.729 | F81: =F80 -> 25120.756 | G81: =K81-E81 -> 4687.6184 | H81: =H80-E81 -> 310731.02 | I81: =G81 -> 4687.6184 | J81: =J80 -> 11868.395 | K81: =($C$9/12)/(1-(1+$C$9/12)^(-$C$10))*$H$27 -> 14876.347
B82: 9 | E82: =(1+$C$8/12)*E81 -> 10248.163 | F82: =F81 -> 25120.756 | G82: =K82-E82 -> 4628.1841 | H82: =H81-E82 -> 300482.86 | I82: =G82 -> 4628.1841 | J82: =J81 -> 11868.395 | K82: =($C$9/12)/(1-(1+$C$9/12)^(-$C$10))*$H$27 -> 14876.347
B83: 10 | E83: =(1+$C$8/12)*E82 -> 10307.944 | F83: =F82 -> 25120.756 | G83: =K83-E83 -> 4568.4032 | H83: =H82-E83 -> 290174.91 | I83: =G83 -> 4568.4032 | J83: =J82 -> 11868.395 | K83: =($C$9/12)/(1-(1+$C$9/12)^(-$C$10))*$H$27 -> 14876.347
B84: 11 | E84: =(1+$C$8/12)*E83 -> 10368.074 | F84: =F83 -> 25120.756 | G84: =K84-E84 -> 4508.2735 | H84: =H83-E84 -> 279806.84 | I84: =G84 -> 4508.2735 | J84: =J83 -> 11868.395 | K84: =($C$9/12)/(1-(1+$C$9/12)^(-$C$10))*$H$27 -> 14876.347
B85: 12 | E85: =(1+$C$8/12)*E84 -> 10428.554 | F85: =F84 -> 25120.756 | G85: =K85-E85 -> 4447.7931 | H85: =H84-E85 -> 269378.29 | I85: =G85 -> 4447.7931 | J85: =J84 -> 11868.395 | K85: =($C$9/12)/(1-(1+$C$9/12)^(-$C$10))*$H$27 -> 14876.347
A86: 2032 | B86: 1 | E86: =(1+$C$8/12)*E85 -> 10489.387 | G86: =K86-E86 -> 4386.9599 | H86: =H85-E86 -> 258888.9 | I86: =G86 -> 4386.9599 | K86: =($C$9/12)/(1-(1+$C$9/12)^(-$C$10))*$H$27 -> 14876.347
B87: 2 | E87: =(1+$C$8/12)*E86 -> 10550.575 | G87: =K87-E87 -> 4325.7718 | H87: =H86-E87 -> 248338.32 | I87: =G87 -> 4325.7718 | K87: =($C$9/12)/(1-(1+$C$9/12)^(-$C$10))*$H$27 -> 14876.347
B88: 3 | E88: =(1+$C$8/12)*E87 -> 10612.12 | G88: =K88-E88 -> 4264.2267 | H88: =H87-E88 -> 237726.2 | I88: =G88 -> 4264.2267 | K88: =($C$9/12)/(1-(1+$C$9/12)^(-$C$10))*$H$27 -> 14876.347
B89: 4 | E89: =(1+$C$8/12)*E88 -> 10674.024 | G89: =K89-E89 -> 4202.3227 | H89: =H88-E89 -> 227052.18 | I89: =G89 -> 4202.3227 | K89: =($C$9/12)/(1-(1+$C$9/12)^(-$C$10))*$H$27 -> 14876.347
B90: 5 | E90: =(1+$C$8/12)*E89 -> 10736.29 | G90: =K90-E90 -> 4140.0576 | H90: =H89-E90 -> 216315.89 | I90: =G90 -> 4140.0576 | K90: =($C$9/12)/(1-(1+$C$9/12)^(-$C$10))*$H$27 -> 14876.347
B91: 6 | E91: =(1+$C$8/12)*E90 -> 10798.918 | G91: =K91-E91 -> 4077.4292 | H91: =H90-E91 -> 205516.97 | I91: =G91 -> 4077.4292 | K91: =($C$9/12)/(1-(1+$C$9/12)^(-$C$10))*$H$27 -> 14876.347
B92: 7 | E92: =(1+$C$8/12)*E91 -> 10861.912 | F92: =SUM(E86:E97)/6+SUM(E50:E61)/6*(100%-N34) -> 26936.737 | G92: =K92-E92 -> 4014.4355 | H92: =H91-E92 -> 194655.06 | I92: =G92 -> 4014.4355 | J92: =SUM(I86:I97)/6+SUM(I50:I61)/6*(100%-N34) -> 10052.413 | K92: =($C$9/12)/(1-(1+$C$9/12)^(-$C$10))*$H$27 -> 14876.347
B93: 8 | E93: =(1+$C$8/12)*E92 -> 10925.273 | F93: =F92 -> 26936.737 | G93: =K93-E93 -> 3951.0744 | H93: =H92-E93 -> 183729.79 | I93: =G93 -> 3951.0744 | J93: =J92 -> 10052.413 | K93: =($C$9/12)/(1-(1+$C$9/12)^(-$C$10))*$H$27 -> 14876.347
B94: 9 | E94: =(1+$C$8/12)*E93 -> 10989.004 | F94: =F93 -> 26936.737 | G94: =K94-E94 -> 3887.3436 | H94: =H93-E94 -> 172740.78 | I94: =G94 -> 3887.3436 | J94: =J93 -> 10052.413 | K94: =($C$9/12)/(1-(1+$C$9/12)^(-$C$10))*$H$27 -> 14876.347
B95: 10 | E95: =(1+$C$8/12)*E94 -> 11053.106 | F95: =F94 -> 26936.737 | G95: =K95-E95 -> 3823.2411 | H95: =H94-E95 -> 161687.68 | I95: =G95 -> 3823.2411 | J95: =J94 -> 10052.413 | K95: =($C$9/12)/(1-(1+$C$9/12)^(-$C$10))*$H$27 -> 14876.347
B96: 11 | E96: =(1+$C$8/12)*E95 -> 11117.582 | F96: =F95 -> 26936.737 | G96: =K96-E96 -> 3758.7646 | H96: =H95-E96 -> 150570.09 | I96: =G96 -> 3758.7646 | J96: =J95 -> 10052.413 | K96: =($C$9/12)/(1-(1+$C$9/12)^(-$C$10))*$H$27 -> 14876.347
B97: 12 | E97: =(1+$C$8/12)*E96 -> 11182.435 | F97: =F96 -> 26936.737 | G97: =K97-E97 -> 3693.9121 | H97: =H96-E97 -> 139387.66 | I97: =G97 -> 3693.9121 | J97: =J96 -> 10052.413 | K97: =($C$9/12)/(1-(1+$C$9/12)^(-$C$10))*$H$27 -> 14876.347
A98: 2033 | B98: 1 | E98: =(1+$C$8/12)*E97 -> 11247.666 | G98: =K98-E98 -> 3628.6812 | H98: =H97-E98 -> 128139.99 | I98: =G98 -> 3628.6812 | K98: =($C$9/12)/(1-(1+$C$9/12)^(-$C$10))*$H$27 -> 14876.347
B99: 2 | E99: =(1+$C$8/12)*E98 -> 11313.277 | G99: =K99-E99 -> 3563.0698 | H99: =H98-E99 -> 116826.72 | I99: =G99 -> 3563.0698 | K99: =($C$9/12)/(1-(1+$C$9/12)^(-$C$10))*$H$27 -> 14876.347
B100: 3 | E100: =(1+$C$8/12)*E99 -> 11379.271 | G100: =K100-E100 -> 3497.0757 | H100: =H99-E100 -> 105447.44 | I100: =G100 -> 3497.0757 | K100: =($C$9/12)/(1-(1+$C$9/12)^(-$C$10))*$H$27 -> 14876.347
B101: 4 | E101: =(1+$C$8/12)*E100 -> 11445.651 | G101: =K101-E101 -> 3430.6966 | H101: =H100-E101 -> 94001.794 | I101: =G101 -> 3430.6966 | K101: =($C$9/12)/(1-(1+$C$9/12)^(-$C$10))*$H$27 -> 14876.347
B102: 5 | E102: =(1+$C$8/12)*E101 -> 11512.417 | G102: =K102-E102 -> 3363.9303 | H102: =H101-E102 -> 82489.377 | I102: =G102 -> 3363.9303 | K102: =($C$9/12)/(1-(1+$C$9/12)^(-$C$10))*$H$27 -> 14876.347
B103: 6 | E103: =(1+$C$8/12)*E102 -> 11579.573 | G103: =K103-E103 -> 3296.7746 | H103: =H102-E103 -> 70909.805 | I103: =G103 -> 3296.7746 | K103: =($C$9/12)/(1-(1+$C$9/12)^(-$C$10))*$H$27 -> 14876.347
B104: 7 | E104: =(1+$C$8/12)*E103 -> 11647.12 | F104: =SUM(E98:E109)/6 -> 23231.277 | G104: =K104-E104 -> 3229.227 | H104: =H103-E104 -> 59262.685 | I104: =G104 -> 3229.227 | J104: =SUM(I98:I109)/6 -> 6521.4177 | K104: =($C$9/12)/(1-(1+$C$9/12)^(-$C$10))*$H$27 -> 14876.347
...

Sheet Займ 1 578
A1: =Panel!A1
A2: =Panel!A2 -> Строительство ГЭС -5 МВТ
A4: ФИНАНСОВЫЕ ИЗДЕРЖКИ
A6: РАСЧЕТ ГРАФИКА ПОГАШЕНИЯ ЗАЙМА
A8: Ставка на первые три года | C8: 0.07
A9: Ставка на последующий период | C9: 0.14
A10: Срок | C10: 81 | D10: мес.
A12: в тыс. тенге, если не указано иное
A13: Год | B13: Мес | C13: Сумма осн.долга на начало месяца | D13: Сумма транша полученного | E13: Выплата осн долга | F13: Выплата осн долга | G13: Начисление вознаграждения | H13: Сумма осн.долга на конец месяца | I13: Выплата вознаграждения | J13: Выплата вознаграждения | K13: Ежемесячный платеж
A14: 2026 | B14: 1 | D14: =('A-0'!O22)*('Инвестиции'!$G$19) -> 153372.55 | H14: =D14 -> 153372.55 | I14: =G14
B15: 2 | D15: =('A-0'!P22)*('Инвестиции'!$G$19) -> 129582.08 | E15: =(1+$C$8/12)*E14 -> 0 | H15: =H14+D15 -> 282954.62 | I15: =G15
B16: 3 | D16: =('A-0'!Q22)*('Инвестиции'!$G$19) -> 129582.08 | E16: =(1+$C$8/12)*E15 -> 0 | H16: =H15+D16 -> 412536.7 | I16: =G16
B17: 4 | D17: =('A-0'!R22)*('Инвестиции'!$G$19) -> 129582.08 | E17: =(1+$C$8/12)*E16 -> 0 | G17: =H17*$C$8/12 -> 3162.3595 | H17: =H16+D17 -> 542118.77 | I17: =G17 -> 3162.3595 | J17: =I17 -> 3162.3595 | K17: =I17 -> 3162.3595
B18: 5 | D18: =('A-0'!S22)*('Инвестиции'!$G$19) -> 129582.08 | E18: =(1+$C$8/12)*E17 -> 0 | G18: =H18*$C$8/12 -> 3918.255 | H18: =H17+D18 -> 671700.85 | I18: =G18 -> 3918.255 | J18: =I18 -> 3918.255 | K18: =I18 -> 3918.255
B19: 6 | D19: =('A-0'!T22)*('Инвестиции'!$G$19) -> 129582.08 | E19: =(1+$C$8/12)*E18 -> 0 | G19: =H19*$C$8/12 -> 4674.1504 | H19: =H18+D19 -> 801282.92 | I19: =G19 -> 4674.1504 | J19: =I19 -> 4674.1504 | K19: =I19 -> 4674.1504
B20: 7 | D20: =('A-0'!U22)*('Инвестиции'!$G$19) -> 129582.08 | E20: =(1+$C$8/12)*E19 -> 0 | G20: =H20*$C$8/12 -> 5430.0458 | H20: =H19+D20 -> 930865 | I20: =G20 -> 5430.0458 | J20: =I20 -> 5430.0458 | K20: =I20 -> 5430.0458
B21: 8 | D21: =('A-0'!V22)*('Инвестиции'!$G$19) -> 129582.08 | E21: =(1+$C$8/12)*E20 -> 0 | G21: =H21*$C$8/12 -> 6185.9413 | H21: =H20+D21 -> 1060447.1 | I21: =G21 -> 6185.9413 | J21: =I21 -> 6185.9413 | K21: =I21 -> 6185.9413
B22: 9 | D22: =('A-0'!W22)*('Инвестиции'!$G$19) -> 129582.08 | E22: =(1+$C$8/12)*E21 -> 0 | G22: =H22*$C$8/12 -> 6941.8367 | H22: =H21+D22 -> 1190029.2 | I22: =G22 -> 6941.8367 | J22: =I22 -> 6941.8367 | K22: =I22 -> 6941.8367
B23: 10 | D23: =('A-0'!X22)*('Инвестиции'!$G$19) -> 129582.08 | E23: =(1+$C$8/12)*E22 -> 0 | G23: =H23*$C$8/12 -> 7697.7322 | H23: =H22+D23 -> 1319611.2 | I23: =G23 -> 7697.7322 | J23: =I23 -> 7697.7322 | K23: =I23 -> 7697.7322
B24: 11 | D24: =('A-0'!Y22)*('Инвестиции'!$G$19) -> 129582.08 | E24: =(1+$C$8/12)*E23 -> 0 | G24: =H24*$C$8/12 -> 8453.6276 | H24: =H23+D24 -> 1449193.3 | I24: =G24 -> 8453.6276 | J24: =I24 -> 8453.6276 | K24: =I24 -> 8453.6276
B25: 12 | D25: =('A-0'!Z22)*('Инвестиции'!$G$19) -> 129582.08 | E25: =(1+$C$8/12)*E24 -> 0 | G25: =H25*$C$8/12 -> 9209.523 | H25: =H24+D25 -> 1578775.4 | I25: =G25 -> 9209.523 | J25: =I25 -> 9209.523 | K25: =I25 -> 9209.523
A26: 2027 | B26: 1 | E26: =(1+$C$8/12)*E25 -> 0 | G26: =H26*$C$8/12 -> 9209.523 | H26: =H25-E26 -> 1578775.4 | I26: =G26 -> 9209.523 | K26: =I26 -> 9209.523
B27: 2 | E27: =(1+$C$8/12)*E26 -> 0 | G27: =H27*$C$8/12 -> 9209.523 | H27: =H26-E27 -> 1578775.4 | I27: =G27 -> 9209.523 | K27: =I27 -> 9209.523
B28: 3 | G28: =H28*$C$8/12 -> 9209.523 | H28: =H27-E28 -> 1578775.4 | I28: =G28 -> 9209.523 | K28: =I28 -> 9209.523
B29: 4 | E29: =K29*((1+$C$8/12)^(-C10)) -> 15303.327 | G29: =K29-E29 -> 9209.523 | H29: =H28-E29 -> 1563472.1 | I29: =G29 -> 9209.523 | K29: =($C$8/12)/(1-(1+$C$8/12)^(-$C$10))*$H$27 -> 24512.85
B30: 5 | E30: =(1+$C$8/12)*E29 -> 15392.597 | G30: =K30-E30 -> 9120.2536 | H30: =H29-E30 -> 1548079.5 | I30: =G30 -> 9120.2536 | K30: =($C$8/12)/(1-(1+$C$8/12)^(-$C$10))*$H$27 -> 24512.85
B31: 6 | E31: =(1+$C$8/12)*E30 -> 15482.387 | G31: =K31-E31 -> 9030.4635 | H31: =H30-E31 -> 1532597.1 | I31: =G31 -> 9030.4635 | K31: =($C$8/12)/(1-(1+$C$8/12)^(-$C$10))*$H$27 -> 24512.85
B32: 7 | E32: =(1+$C$8/12)*E31 -> 15572.701 | F32: =SUM(E29:E37)/6*N32 -> 16448.573 | G32: =K32-E32 -> 8940.1496 | H32: =H31-E32 -> 1517024.4 | I32: =G32 -> 8940.1496 | J32: =SUM(I26:I37)/6*N32 -> 12513.253 | K32: =($C$8/12)/(1-(1+$C$8/12)^(-$C$10))*$H$27 -> 24512.85 | M32: Фактическая выплата в 2026 | N32: 0.7
B33: 8 | E33: =(1+$C$8/12)*E32 -> 15663.541 | F33: =F32 -> 16448.573 | G33: =K33-E33 -> 8849.3088 | H33: =H32-E33 -> 1501360.8 | I33: =G33 -> 8849.3088 | J33: =J32 -> 12513.253 | K33: =($C$8/12)/(1-(1+$C$8/12)^(-$C$10))*$H$27 -> 24512.85 | M33: Фактическая выплата в 2027 | N33: 0.7
B34: 9 | E34: =(1+$C$8/12)*E33 -> 15754.912 | F34: =F33 -> 16448.573 | G34: =K34-E34 -> 8757.9382 | H34: =H33-E34 -> 1485605.9 | I34: =G34 -> 8757.9382 | J34: =J33 -> 12513.253 | K34: =($C$8/12)/(1-(1+$C$8/12)^(-$C$10))*$H$27 -> 24512.85 | M34: Фактическая выплата в 2028 | N34: 0.7
B35: 10 | E35: =(1+$C$8/12)*E34 -> 15846.816 | F35: =F34 -> 16448.573 | G35: =K35-E35 -> 8666.0345 | H35: =H34-E35 -> 1469759.1 | I35: =G35 -> 8666.0345 | J35: =J34 -> 12513.253 | K35: =($C$8/12)/(1-(1+$C$8/12)^(-$C$10))*$H$27 -> 24512.85
B36: 11 | E36: =(1+$C$8/12)*E35 -> 15939.256 | F36: =F35 -> 16448.573 | G36: =K36-E36 -> 8573.5947 | H36: =H35-E36 -> 1453819.8 | I36: =G36 -> 8573.5947 | J36: =J35 -> 12513.253 | K36: =($C$8/12)/(1-(1+$C$8/12)^(-$C$10))*$H$27 -> 24512.85
B37: 12 | E37: =(1+$C$8/12)*E36 -> 16032.235 | F37: =F36 -> 16448.573 | G37: =K37-E37 -> 8480.6158 | H37: =H36-E37 -> 1437787.6 | I37: =G37 -> 8480.6158 | J37: =J36 -> 12513.253 | K37: =($C$8/12)/(1-(1+$C$8/12)^(-$C$10))*$H$27 -> 24512.85
A38: 2028 | B38: 1 | E38: =(1+$C$8/12)*E37 -> 16125.756 | G38: =K38-E38 -> 8387.0944 | H38: =H37-E38 -> 1421661.9 | I38: =G38 -> 8387.0944 | K38: =($C$8/12)/(1-(1+$C$8/12)^(-$C$10))*$H$27 -> 24512.85
B39: 2 | E39: =(1+$C$8/12)*E38 -> 16219.823 | G39: =K39-E39 -> 8293.0275 | H39: =H38-E39 -> 1405442 | I39: =G39 -> 8293.0275 | K39: =($C$8/12)/(1-(1+$C$8/12)^(-$C$10))*$H$27 -> 24512.85
B40: 3 | E40: =(1+$C$8/12)*E39 -> 16314.438 | G40: =K40-E40 -> 8198.4118 | H40: =H39-E40 -> 1389127.6 | I40: =G40 -> 8198.4118 | K40: =($C$8/12)/(1-(1+$C$8/12)^(-$C$10))*$H$27 -> 24512.85
B41: 4 | E41: =(1+$C$8/12)*E40 -> 16409.606 | G41: =K41-E41 -> 8103.2443 | H41: =H40-E41 -> 1372718 | I41: =G41 -> 8103.2443 | K41: =($C$8/12)/(1-(1+$C$8/12)^(-$C$10))*$H$27 -> 24512.85
B42: 5 | E42: =(1+$C$8/12)*E41 -> 16505.329 | G42: =K42-E42 -> 8007.5216 | H42: =H41-E42 -> 1356212.7 | I42: =G42 -> 8007.5216 | K42: =($C$8/12)/(1-(1+$C$8/12)^(-$C$10))*$H$27 -> 24512.85
B43: 6 | E43: =(1+$C$8/12)*E42 -> 16601.61 | G43: =K43-E43 -> 7911.2405 | H43: =H42-E43 -> 1339611 | I43: =G43 -> 7911.2405 | K43: =($C$8/12)/(1-(1+$C$8/12)^(-$C$10))*$H$27 -> 24512.85
B44: 7 | E44: =(1+$C$8/12)*E43 -> 16698.452 | F44: =SUM(E38:E49)/6*N33 -> 23314.644 | G44: =K44-E44 -> 7814.3978 | H44: =H43-E44 -> 1322912.6 | I44: =G44 -> 7814.3978 | J44: =SUM(I38:I49)/6*N33 -> 11003.346 | K44: =($C$8/12)/(1-(1+$C$8/12)^(-$C$10))*$H$27 -> 24512.85
B45: 8 | E45: =(1+$C$8/12)*E44 -> 16795.86 | F45: =F44 -> 23314.644 | G45: =K45-E45 -> 7716.9901 | H45: =H44-E45 -> 1306116.7 | I45: =G45 -> 7716.9901 | J45: =J44 -> 11003.346 | K45: =($C$8/12)/(1-(1+$C$8/12)^(-$C$10))*$H$27 -> 24512.85
B46: 9 | E46: =(1+$C$8/12)*E45 -> 16893.836 | F46: =F45 -> 23314.644 | G46: =K46-E46 -> 7619.0143 | H46: =H45-E46 -> 1289222.9 | I46: =G46 -> 7619.0143 | J46: =J45 -> 11003.346 | K46: =($C$8/12)/(1-(1+$C$8/12)^(-$C$10))*$H$27 -> 24512.85
B47: 10 | E47: =(1+$C$8/12)*E46 -> 16992.383 | F47: =F46 -> 23314.644 | G47: =K47-E47 -> 7520.4669 | H47: =H46-E47 -> 1272230.5 | I47: =G47 -> 7520.4669 | J47: =J46 -> 11003.346 | K47: =($C$8/12)/(1-(1+$C$8/12)^(-$C$10))*$H$27 -> 24512.85
B48: 11 | E48: =(1+$C$8/12)*E47 -> 17091.506 | F48: =F47 -> 23314.644 | G48: =K48-E48 -> 7421.3447 | H48: =H47-E48 -> 1255139 | I48: =G48 -> 7421.3447 | J48: =J47 -> 11003.346 | K48: =($C$8/12)/(1-(1+$C$8/12)^(-$C$10))*$H$27 -> 24512.85
B49: 12 | E49: =(1+$C$8/12)*E48 -> 17191.206 | F49: =F48 -> 23314.644 | G49: =K49-E49 -> 7321.6442 | H49: =H48-E49 -> 1237947.8 | I49: =G49 -> 7321.6442 | J49: =J48 -> 11003.346 | K49: =($C$8/12)/(1-(1+$C$8/12)^(-$C$10))*$H$27 -> 24512.85
A50: 2029 | B50: 1 | E50: =(1+$C$8/12)*E49 -> 17291.488 | G50: =K50-E50 -> 7221.3622 | H50: =H49-E50 -> 1220656.3 | I50: =G50 -> 7221.3622 | K50: =($C$8/12)/(1-(1+$C$8/12)^(-$C$10))*$H$27 -> 24512.85
B51: 2 | E51: =(1+$C$8/12)*E50 -> 17392.355 | G51: =K51-E51 -> 7120.4952 | H51: =H50-E51 -> 1203264 | I51: =G51 -> 7120.4952 | K51: =($C$8/12)/(1-(1+$C$8/12)^(-$C$10))*$H$27 -> 24512.85
B52: 3 | E52: =(1+$C$8/12)*E51 -> 17493.81 | G52: =K52-E52 -> 7019.0398 | H52: =H51-E52 -> 1185770.2 | I52: =G52 -> 7019.0398 | K52: =($C$8/12)/(1-(1+$C$8/12)^(-$C$10))*$H$27 -> 24512.85
B53: 4 | E53: =(1+$C$8/12)*E52 -> 17595.858 | G53: =K53-E53 -> 6916.9925 | H53: =H52-E53 -> 1168174.3 | I53: =G53 -> 6916.9925 | K53: =($C$8/12)/(1-(1+$C$8/12)^(-$C$10))*$H$27 -> 24512.85
B54: 5 | E54: =(1+$C$8/12)*E53 -> 17698.5 | G54: =K54-E54 -> 6814.35 | H54: =H53-E54 -> 1150475.8 | I54: =G54 -> 6814.35 | K54: =($C$8/12)/(1-(1+$C$8/12)^(-$C$10))*$H$27 -> 24512.85
B55: 6 | E55: =(1+$C$8/12)*E54 -> 17801.741 | G55: =K55-E55 -> 6711.1088 | H55: =H54-E55 -> 1132674.1 | I55: =G55 -> 6711.1088 | K55: =($C$8/12)/(1-(1+$C$8/12)^(-$C$10))*$H$27 -> 24512.85
B56: 7 | E56: =(1+$C$8/12)*E55 -> 17905.585 | F56: =SUM(E50:E61)/6*N34 -> 25000.061 | G56: =K56-E56 -> 6607.2653 | H56: =H55-E56 -> 1114768.5 | I56: =G56 -> 6607.2653 | J56: =SUM(I50:I61)/6*N34 -> 9317.929 | K56: =($C$8/12)/(1-(1+$C$8/12)^(-$C$10))*$H$27 -> 24512.85
B57: 8 | E57: =(1+$C$8/12)*E56 -> 18010.034 | F57: =F56 -> 25000.061 | G57: =K57-E57 -> 6502.8161 | H57: =H56-E57 -> 1096758.4 | I57: =G57 -> 6502.8161 | J57: =J56 -> 9317.929 | K57: =($C$8/12)/(1-(1+$C$8/12)^(-$C$10))*$H$27 -> 24512.85
B58: 9 | E58: =(1+$C$8/12)*E57 -> 18115.093 | F58: =F57 -> 25000.061 | G58: =K58-E58 -> 6397.7575 | H58: =H57-E58 -> 1078643.3 | I58: =G58 -> 6397.7575 | J58: =J57 -> 9317.929 | K58: =($C$8/12)/(1-(1+$C$8/12)^(-$C$10))*$H$27 -> 24512.85
B59: 10 | E59: =(1+$C$8/12)*E58 -> 18220.764 | F59: =F58 -> 25000.061 | G59: =K59-E59 -> 6292.0861 | H59: =H58-E59 -> 1060422.6 | I59: =G59 -> 6292.0861 | J59: =J58 -> 9317.929 | K59: =($C$8/12)/(1-(1+$C$8/12)^(-$C$10))*$H$27 -> 24512.85
B60: 11 | E60: =(1+$C$8/12)*E59 -> 18327.052 | F60: =F59 -> 25000.061 | G60: =K60-E60 -> 6185.7984 | H60: =H59-E60 -> 1042095.5 | I60: =G60 -> 6185.7984 | J60: =J59 -> 9317.929 | K60: =($C$8/12)/(1-(1+$C$8/12)^(-$C$10))*$H$27 -> 24512.85
B61: 12 | E61: =(1+$C$8/12)*E60 -> 18433.96 | F61: =F60 -> 25000.061 | G61: =K61-E61 -> 6078.8906 | H61: =H60-E61 -> 1023661.6 | I61: =G61 -> 6078.8906 | J61: =J60 -> 9317.929 | K61: =($C$8/12)/(1-(1+$C$8/12)^(-$C$10))*$H$27 -> 24512.85
A62: 2030 | B62: 1 | E62: =(1+$C$8/12)*E61 -> 18541.491 | G62: =K62-E62 -> 5971.3591 | H62: =H61-E62 -> 1005120.1 | I62: =G62 -> 5971.3591 | K62: =($C$8/12)/(1-(1+$C$8/12)^(-$C$10))*$H$27 -> 24512.85
B63: 2 | E63: =(1+$C$8/12)*E62 -> 18649.65 | G63: =K63-E63 -> 5863.2004 | H63: =H62-E63 -> 986470.42 | I63: =G63 -> 5863.2004 | K63: =($C$8/12)/(1-(1+$C$8/12)^(-$C$10))*$H$27 -> 24512.85
B64: 3 | E64: =(1+$C$8/12)*E63 -> 18758.439 | G64: =K64-E64 -> 5754.4108 | H64: =H63-E64 -> 967711.98 | I64: =G64 -> 5754.4108 | K64: =($C$8/12)/(1-(1+$C$8/12)^(-$C$10))*$H$27 -> 24512.85
B65: 4 | E65: =(1+$C$8/12)*E64 -> 18867.864 | G65: =K65-E65 -> 5644.9866 | H65: =H64-E65 -> 948844.12 | I65: =G65 -> 5644.9866 | K65: =($C$8/12)/(1-(1+$C$8/12)^(-$C$10))*$H$27 -> 24512.85
B66: 5 | E66: =(1+$C$8/12)*E65 -> 18977.926 | G66: =K66-E66 -> 5534.924 | H66: =H65-E66 -> 929866.19 | I66: =G66 -> 5534.924 | K66: =($C$8/12)/(1-(1+$C$8/12)^(-$C$10))*$H$27 -> 24512.85
B67: 6 | E67: =(1+$C$8/12)*E66 -> 19088.631 | G67: =K67-E67 -> 5424.2195 | H67: =H66-E67 -> 910777.56 | I67: =G67 -> 5424.2195 | K67: =($C$8/12)/(1-(1+$C$8/12)^(-$C$10))*$H$27 -> 24512.85
B68: 7 | E68: =(1+$C$8/12)*E67 -> 19199.981 | F68: =SUM(E62:E73)/6+SUM(E26:E37)/6*(100%-N32) -> 45345.557 | G68: =K68-E68 -> 5312.8691 | H68: =H67-E68 -> 891577.58 | I68: =G68 -> 5312.8691 | J68: =SUM(I62:I73)/6+SUM(I26:I37)/6*(100%-N32) -> 16092.355 | K68: =($C$8/12)/(1-(1+$C$8/12)^(-$C$10))*$H$27 -> 24512.85
B69: 8 | E69: =(1+$C$8/12)*E68 -> 19311.981 | F69: =F68 -> 45345.557 | G69: =K69-E69 -> 5200.8692 | H69: =H68-E69 -> 872265.6 | I69: =G69 -> 5200.8692 | J69: =J68 -> 16092.355 | K69: =($C$8/12)/(1-(1+$C$8/12)^(-$C$10))*$H$27 -> 24512.85
B70: 9 | E70: =(1+$C$8/12)*E69 -> 19424.634 | F70: =F69 -> 45345.557 | G70: =K70-E70 -> 5088.216 | H70: =H69-E70 -> 852840.97 | I70: =G70 -> 5088.216 | J70: =J69 -> 16092.355 | K70: =($C$8/12)/(1-(1+$C$8/12)^(-$C$10))*$H$27 -> 24512.85
B71: 10 | E71: =(1+$C$8/12)*E70 -> 19537.945 | F71: =F70 -> 45345.557 | G71: =K71-E71 -> 4974.9056 | H71: =H70-E71 -> 833303.02 | I71: =G71 -> 4974.9056 | J71: =J70 -> 16092.355 | K71: =($C$8/12)/(1-(1+$C$8/12)^(-$C$10))*$H$27 -> 24512.85
B72: 11 | E72: =(1+$C$8/12)*E71 -> 19651.916 | F72: =F71 -> 45345.557 | G72: =K72-E72 -> 4860.9343 | H72: =H71-E72 -> 813651.11 | I72: =G72 -> 4860.9343 | J72: =J71 -> 16092.355 | K72: =($C$8/12)/(1-(1+$C$8/12)^(-$C$10))*$H$27 -> 24512.85
B73: 12 | E73: =(1+$C$8/12)*E72 -> 19766.552 | F73: =F72 -> 45345.557 | G73: =K73-E73 -> 4746.2981 | H73: =H72-E73 -> 793884.55 | I73: =G73 -> 4746.2981 | J73: =J72 -> 16092.355 | K73: =($C$8/12)/(1-(1+$C$8/12)^(-$C$10))*$H$27 -> 24512.85
A74: 2031 | B74: 1 | E74: =(1+$C$8/12)*E73 -> 19881.857 | G74: =K74-E74 -> 10353.522 | H74: =H73-E74 -> 774002.7 | I74: =G74 -> 10353.522 | K74: =($C$9/12)/(1-(1+$C$9/12)^(-$C$10))*$H$27 -> 30235.379
B75: 2 | E75: =(1+$C$8/12)*E74 -> 19997.835 | G75: =K75-E75 -> 10237.545 | H75: =H74-E75 -> 754004.86 | I75: =G75 -> 10237.545 | K75: =($C$9/12)/(1-(1+$C$9/12)^(-$C$10))*$H$27 -> 30235.379
B76: 3 | E76: =(1+$C$8/12)*E75 -> 20114.489 | G76: =K76-E76 -> 10120.891 | H76: =H75-E76 -> 733890.37 | I76: =G76 -> 10120.891 | K76: =($C$9/12)/(1-(1+$C$9/12)^(-$C$10))*$H$27 -> 30235.379
B77: 4 | E77: =(1+$C$8/12)*E76 -> 20231.823 | G77: =K77-E77 -> 10003.556 | H77: =H76-E77 -> 713658.55 | I77: =G77 -> 10003.556 | K77: =($C$9/12)/(1-(1+$C$9/12)^(-$C$10))*$H$27 -> 30235.379
B78: 5 | E78: =(1+$C$8/12)*E77 -> 20349.842 | G78: =K78-E78 -> 9885.5371 | H78: =H77-E78 -> 693308.71 | I78: =G78 -> 9885.5371 | K78: =($C$9/12)/(1-(1+$C$9/12)^(-$C$10))*$H$27 -> 30235.379
B79: 6 | E79: =(1+$C$8/12)*E78 -> 20468.549 | G79: =K79-E79 -> 9766.8297 | H79: =H78-E79 -> 672840.16 | I79: =G79 -> 9766.8297 | K79: =($C$9/12)/(1-(1+$C$9/12)^(-$C$10))*$H$27 -> 30235.379
B80: 7 | E80: =(1+$C$8/12)*E79 -> 20587.949 | F80: =SUM(E74:E85)/6+SUM(E38:E49)/6*(100%-N33) -> 51056.592 | G80: =K80-E80 -> 9647.4298 | H80: =H79-E80 -> 652252.21 | I80: =G80 -> 9647.4298 | J80: =SUM(I74:I85)/6+SUM(I38:I49)/6*(100%-N33) -> 24121.877 | K80: =($C$9/12)/(1-(1+$C$9/12)^(-$C$10))*$H$27 -> 30235.379
B81: 8 | E81: =(1+$C$8/12)*E80 -> 20708.046 | F81: =F80 -> 51056.592 | G81: =K81-E81 -> 9527.3334 | H81: =H80-E81 -> 631544.16 | I81: =G81 -> 9527.3334 | J81: =J80 -> 24121.877 | K81: =($C$9/12)/(1-(1+$C$9/12)^(-$C$10))*$H$27 -> 30235.379
B82: 9 | E82: =(1+$C$8/12)*E81 -> 20828.843 | F82: =F81 -> 51056.592 | G82: =K82-E82 -> 9406.5365 | H82: =H81-E82 -> 610715.32 | I82: =G82 -> 9406.5365 | J82: =J81 -> 24121.877 | K82: =($C$9/12)/(1-(1+$C$9/12)^(-$C$10))*$H$27 -> 30235.379
B83: 10 | E83: =(1+$C$8/12)*E82 -> 20950.344 | F83: =F82 -> 51056.592 | G83: =K83-E83 -> 9285.0349 | H83: =H82-E83 -> 589764.98 | I83: =G83 -> 9285.0349 | J83: =J82 -> 24121.877 | K83: =($C$9/12)/(1-(1+$C$9/12)^(-$C$10))*$H$27 -> 30235.379
B84: 11 | E84: =(1+$C$8/12)*E83 -> 21072.555 | F84: =F83 -> 51056.592 | G84: =K84-E84 -> 9162.8246 | H84: =H83-E84 -> 568692.42 | I84: =G84 -> 9162.8246 | J84: =J83 -> 24121.877 | K84: =($C$9/12)/(1-(1+$C$9/12)^(-$C$10))*$H$27 -> 30235.379
B85: 12 | E85: =(1+$C$8/12)*E84 -> 21195.478 | F85: =F84 -> 51056.592 | G85: =K85-E85 -> 9039.9013 | H85: =H84-E85 -> 547496.94 | I85: =G85 -> 9039.9013 | J85: =J84 -> 24121.877 | K85: =($C$9/12)/(1-(1+$C$9/12)^(-$C$10))*$H$27 -> 30235.379
A86: 2032 | B86: 1 | E86: =(1+$C$8/12)*E85 -> 21319.118 | G86: =K86-E86 -> 8916.2611 | H86: =H85-E86 -> 526177.83 | I86: =G86 -> 8916.2611 | K86: =($C$9/12)/(1-(1+$C$9/12)^(-$C$10))*$H$27 -> 30235.379
B87: 2 | E87: =(1+$C$8/12)*E86 -> 21443.48 | G87: =K87-E87 -> 8791.8995 | H87: =H86-E87 -> 504734.35 | I87: =G87 -> 8791.8995 | K87: =($C$9/12)/(1-(1+$C$9/12)^(-$C$10))*$H$27 -> 30235.379
B88: 3 | E88: =(1+$C$8/12)*E87 -> 21568.567 | G88: =K88-E88 -> 8666.8126 | H88: =H87-E88 -> 483165.78 | I88: =G88 -> 8666.8126 | K88: =($C$9/12)/(1-(1+$C$9/12)^(-$C$10))*$H$27 -> 30235.379
B89: 4 | E89: =(1+$C$8/12)*E88 -> 21694.383 | G89: =K89-E89 -> 8540.9959 | H89: =H88-E89 -> 461471.4 | I89: =G89 -> 8540.9959 | K89: =($C$9/12)/(1-(1+$C$9/12)^(-$C$10))*$H$27 -> 30235.379
B90: 5 | E90: =(1+$C$8/12)*E89 -> 21820.934 | G90: =K90-E90 -> 8414.4454 | H90: =H89-E90 -> 439650.46 | I90: =G90 -> 8414.4454 | K90: =($C$9/12)/(1-(1+$C$9/12)^(-$C$10))*$H$27 -> 30235.379
B91: 6 | E91: =(1+$C$8/12)*E90 -> 21948.223 | G91: =K91-E91 -> 8287.1566 | H91: =H90-E91 -> 417702.24 | I91: =G91 -> 8287.1566 | K91: =($C$9/12)/(1-(1+$C$9/12)^(-$C$10))*$H$27 -> 30235.379
B92: 7 | E92: =(1+$C$8/12)*E91 -> 22076.254 | F92: =SUM(E86:E97)/6+SUM(E50:E61)/6*(100%-N34) -> 54747.477 | G92: =K92-E92 -> 8159.1253 | H92: =H91-E92 -> 395625.99 | I92: =G92 -> 8159.1253 | J92: =SUM(I86:I97)/6+SUM(I50:I61)/6*(100%-N34) -> 20430.992 | K92: =($C$9/12)/(1-(1+$C$9/12)^(-$C$10))*$H$27 -> 30235.379
B93: 8 | E93: =(1+$C$8/12)*E92 -> 22205.032 | F93: =F92 -> 54747.477 | G93: =K93-E93 -> 8030.3471 | H93: =H92-E93 -> 373420.95 | I93: =G93 -> 8030.3471 | J93: =J92 -> 20430.992 | K93: =($C$9/12)/(1-(1+$C$9/12)^(-$C$10))*$H$27 -> 30235.379
B94: 9 | E94: =(1+$C$8/12)*E93 -> 22334.561 | F94: =F93 -> 54747.477 | G94: =K94-E94 -> 7900.8178 | H94: =H93-E94 -> 351086.39 | I94: =G94 -> 7900.8178 | J94: =J93 -> 20430.992 | K94: =($C$9/12)/(1-(1+$C$9/12)^(-$C$10))*$H$27 -> 30235.379
B95: 10 | E95: =(1+$C$8/12)*E94 -> 22464.846 | F95: =F94 -> 54747.477 | G95: =K95-E95 -> 7770.5328 | H95: =H94-E95 -> 328621.55 | I95: =G95 -> 7770.5328 | J95: =J94 -> 20430.992 | K95: =($C$9/12)/(1-(1+$C$9/12)^(-$C$10))*$H$27 -> 30235.379
B96: 11 | E96: =(1+$C$8/12)*E95 -> 22595.891 | F96: =F95 -> 54747.477 | G96: =K96-E96 -> 7639.4879 | H96: =H95-E96 -> 306025.66 | I96: =G96 -> 7639.4879 | J96: =J95 -> 20430.992 | K96: =($C$9/12)/(1-(1+$C$9/12)^(-$C$10))*$H$27 -> 30235.379
B97: 12 | E97: =(1+$C$8/12)*E96 -> 22727.701 | F97: =F96 -> 54747.477 | G97: =K97-E97 -> 7507.6785 | H97: =H96-E97 -> 283297.96 | I97: =G97 -> 7507.6785 | J97: =J96 -> 20430.992 | K97: =($C$9/12)/(1-(1+$C$9/12)^(-$C$10))*$H$27 -> 30235.379
A98: 2033 | B98: 1 | E98: =(1+$C$8/12)*E97 -> 22860.279 | G98: =K98-E98 -> 7375.1003 | H98: =H97-E98 -> 260437.68 | I98: =G98 -> 7375.1003 | K98: =($C$9/12)/(1-(1+$C$9/12)^(-$C$10))*$H$27 -> 30235.379
B99: 2 | E99: =(1+$C$8/12)*E98 -> 22993.63 | G99: =K99-E99 -> 7241.7487 | H99: =H98-E99 -> 237444.05 | I99: =G99 -> 7241.7487 | K99: =($C$9/12)/(1-(1+$C$9/12)^(-$C$10))*$H$27 -> 30235.379
B100: 3 | E100: =(1+$C$8/12)*E99 -> 23127.76 | G100: =K100-E100 -> 7107.6191 | H100: =H99-E100 -> 214316.29 | I100: =G100 -> 7107.6191 | K100: =($C$9/12)/(1-(1+$C$9/12)^(-$C$10))*$H$27 -> 30235.379
B101: 4 | E101: =(1+$C$8/12)*E100 -> 23262.672 | G101: =K101-E101 -> 6972.7072 | H101: =H100-E101 -> 191053.61 | I101: =G101 -> 6972.7072 | K101: =($C$9/12)/(1-(1+$C$9/12)^(-$C$10))*$H$27 -> 30235.379
B102: 5 | E102: =(1+$C$8/12)*E101 -> 23398.371 | G102: =K102-E102 -> 6837.0083 | H102: =H101-E102 -> 167655.24 | I102: =G102 -> 6837.0083 | K102: =($C$9/12)/(1-(1+$C$9/12)^(-$C$10))*$H$27 -> 30235.379
B103: 6 | E103: =(1+$C$8/12)*E102 -> 23534.861 | G103: =K103-E103 -> 6700.5178 | H103: =H102-E103 -> 144120.38 | I103: =G103 -> 6700.5178 | K103: =($C$9/12)/(1-(1+$C$9/12)^(-$C$10))*$H$27 -> 30235.379
B104: 7 | E104: =(1+$C$8/12)*E103 -> 23672.148 | F104: =SUM(E98:E109)/6 -> 47216.326 | G104: =K104-E104 -> 6563.2311 | H104: =H103-E104 -> 120448.23 | I104: =G104 -> 6563.2311 | J104: =SUM(I98:I109)/6 -> 13254.432 | K104: =($C$9/12)/(1-(1+$C$9/12)^(-$C$10))*$H$27 -> 30235.379
...

Sheet ОПиУ
A1: =Panel!A1
A2: =Panel!A2 -> Строительство ГЭС -5 МВТ
A4: ПРОГНОЗНЫЙ ОТЧЕТ О ДОХОДАХ И РАСХОДАХ (про-форма)
A6: в тыс.тенге, если не указано иное
A7: Income statement | B7: янв | C7: фев | D7: мар | E7: апр | F7: май | G7: июн | H7: июл | I7: авг | J7: сен | K7: окт | L7: ноя | M7: дек | N7: 2026 | O7: янв | P7: фев | Q7: мар | R7: апр | S7: май | T7: июн | U7: июл | V7: авг | W7: сен | X7: окт | Y7: ноя | Z7: дек | AA7: 2027 | AB7: янв | AC7: фев | AD7: мар | AE7: апр | AF7: май | AG7: июн | AH7: июл | AI7: авг | AJ7: сен | AK7: окт | AL7: ноя | AM7: дек | AN7: 2028 | AO7: 2029 | AP7: 2030 | AQ7: 2031 | AR7: 2032 | AS7: 2033 | AT7: 2034 | AU7: 2035 | AV7: 2036 | AW7: 2037 | AX7: 2038 | AY7: 2039 | AZ7: 2040 | BA7: 2041 | BB7: 2042
A8: Доход от основной деятельности | B8: ='Выручка'!C13 -> 29009.299 | C8: ='Выручка'!D13 -> 24623.493 | D8: ='Выручка'!E13 -> 38688.925 | E8: ='Выручка'!F13 -> 22817.101 | F8: ='Выручка'!G13 -> 51857.622 | G8: ='Выручка'!H13 -> 58345.554 | H8: ='Выручка'!I13 -> 72710.354 | I8: ='Выручка'!J13 -> 72710.354 | ... BB8: ='Выручка'!BC13 -> 2484287.1
A9: Себестоимость реализованной готовой продукции | B9: ='Произв.затраты'!C17 -> 18528.62 | C9: ='Произв.затраты'!D17 -> 18470.426 | D9: ='Произв.затраты'!E17 -> 18808.573 | E9: ='Произв.затраты'!F17 -> 18426.999 | F9: ='Произв.затраты'!G17 -> 19125.161 | G9: ='Произв.затраты'!H17 -> 19281.138 | H9: ='Произв.затраты'!I17 -> 19626.481 | I9: ='Произв.затраты'!J17 -> 19626.481 | ... BB9: ='Произв.затраты'!BC17 -> 409523.68
A10: ='Произв.затраты'!B8 -> Амортизационные отчисления | B10: ='Произв.затраты'!C8 -> 14417.246 | C10: ='Произв.затраты'!D8 -> 14417.246 | D10: ='Произв.затраты'!E8 -> 14417.246 | E10: ='Произв.затраты'!F8 -> 14417.246 | F10: ='Произв.затраты'!G8 -> 14417.246 | G10: ='Произв.затраты'!H8 -> 14417.246 | H10: ='Произв.затраты'!I8 -> 14417.246 | ... BB10: ='Произв.затраты'!BC8 -> 173006.95
A11: ='Произв.затраты'!B9 -> Текущий ремонт оборудования | B11: ='Произв.затраты'!C9 -> 194.05348 | C11: ='Произв.затраты'!D9 -> 194.05348 | D11: ='Произв.затраты'!E9 -> 194.05348 | E11: ='Произв.затраты'!F9 -> 194.05348 | F11: ='Произв.затраты'!G9 -> 194.05348 | G11: ='Произв.затраты'!H9 -> 194.05348 | H11: ='Произв.затраты'!I9 -> 194.05348 | ... BB11: ='Произв.затраты'!BC9 -> 13675.822
A12: ='Произв.затраты'!B10 -> Электроэнергия на объекте | B12: ='Произв.затраты'!C10 -> 99.055116 | C12: ='Произв.затраты'!D10 -> 99.055116 | D12: ='Произв.затраты'!E10 -> 99.055116 | E12: ='Произв.затраты'!F10 -> 99.055116 | F12: ='Произв.затраты'!G10 -> 99.055116 | G12: ='Произв.затраты'!H10 -> 99.055116 | H12: ='Произв.затраты'!I10 -> 99.055116 | ... BB12: ='Произв.затраты'!BC10 -> 6980.86
A13: ='Произв.затраты'!B11 -> Налог на имущество | B13: ='Произв.затраты'!C11 -> 1008.2866 | C13: ='Произв.затраты'!D11 -> 1008.2866 | D13: ='Произв.затраты'!E11 -> 1008.2866 | E13: ='Произв.затраты'!F11 -> 1008.2866 | F13: ='Произв.затраты'!G11 -> 1008.2866 | G13: ='Произв.затраты'!H11 -> 1008.2866 | H13: ='Произв.затраты'!I11 -> 1008.2866 | ... BB13: ='Произв.затраты'!BC11 -> 0
A14: ='Произв.затраты'!B12 -> Земельный налог | B14: ='Произв.затраты'!C12 -> 8.6245833 | C14: ='Произв.затраты'!D12 -> 8.6245833 | D14: ='Произв.затраты'!E12 -> 8.6245833 | E14: ='Произв.затраты'!F12 -> 8.6245833 | F14: ='Произв.затраты'!G12 -> 8.6245833 | G14: ='Произв.затраты'!H12 -> 8.6245833 | H14: ='Произв.затраты'!I12 -> 8.6245833 | ... BB14: ='Произв.затраты'!BC12 -> 103.495
A15: ='Произв.затраты'!B13 -> Плата за пользование водными ресурсами | B15: ='Произв.затраты'!C13 -> 101.31772 | C15: ='Произв.затраты'!D13 -> 85.999872 | D15: ='Произв.затраты'!E13 -> 135.12472 | E15: ='Произв.затраты'!F13 -> 79.690879 | F15: ='Произв.затраты'!G13 -> 181.11764 | G15: ='Произв.затраты'!H13 -> 203.77735 | H15: ='Произв.затраты'!I13 -> 253.94777 | ... BB15: ='Произв.затраты'!BC13 -> 1915.9618
A16: ='Произв.затраты'!B14 -> Услуги диспетчеризации | B16: ='Произв.затраты'!C14 -> 403.80267 | C16: ='Произв.затраты'!D14 -> 382.8554 | D16: ='Произв.затраты'!E14 -> 601.55007 | E16: ='Произв.затраты'!F14 -> 354.76893 | F16: ='Произв.затраты'!G14 -> 806.30195 | G16: ='Произв.затраты'!H14 -> 907.17877 | H16: ='Произв.затраты'!I14 -> 1130.5281 | ... BB16: ='Произв.затраты'!BC14 -> 49815.254
A17: ='Произв.затраты'!B15 -> Оперативно-техническое и диспетчерское обслуживание | B17: ='Произв.затраты'!C15 -> 2151.1879 | C17: ='Произв.затраты'!D15 -> 2151.1879 | D17: ='Произв.затраты'!E15 -> 2151.1879 | E17: ='Произв.затраты'!F15 -> 2151.1879 | F17: ='Произв.затраты'!G15 -> 2151.1879 | G17: ='Произв.затраты'!H15 -> 2151.1879 | H17: ='Произв.затраты'!I15 -> 2151.1879 | ... BB17: ='Произв.затраты'!BC15 -> 151603.9
A18: ='Произв.затраты'!B16 -> Непредвиденные расходы | B18: ='Произв.затраты'!C16 -> 145.0465 | C18: ='Произв.затраты'!D16 -> 123.11746 | D18: ='Произв.затраты'!E16 -> 193.44463 | E18: ='Произв.затраты'!F16 -> 114.08551 | F18: ='Произв.затраты'!G16 -> 259.28811 | G18: ='Произв.затраты'!H16 -> 291.72777 | H18: ='Произв.затраты'!I16 -> 363.55177 | ... BB18: ='Произв.затраты'!BC16 -> 12421.436
A19: ВАЛОВЫЙ ДОХОД/ (УБЫТОК) | B19: =B8-B9 -> 10480.679 | C19: =C8-C9 -> 6153.0665 | D19: =D8-D9 -> 19880.352 | E19: =E8-E9 -> 4390.1023 | F19: =F8-F9 -> 32732.46 | G19: =G8-G9 -> 39064.416 | H19: =H8-H9 -> 53083.872 | I19: =I8-I9 -> 53083.872 | ... BB19: =BB8-BB9 -> 2074763.4
A20: НОРМА ВАЛОВОЙ ПРИБЫЛИ | B20: =IF(B8=0,0,B19/B8) -> 0.36128687 | C20: =IF(C8=0,0,C19/C8) -> 0.24988602 | D20: =IF(D8=0,0,D19/D8) -> 0.51385124 | E20: =IF(E8=0,0,E19/E8) -> 0.19240403 | F20: =IF(F8=0,0,F19/F8) -> 0.63119864 | G20: =IF(G8=0,0,G19/G8) -> 0.66953544 | H20: =IF(H8=0,0,H19/H8) -> 0.73007309 | I20: =IF(I8=0,0,I19/I8) -> 0.73007309 | ... BB20: =IF(BB8=0,0,BB19/BB8) -> 0.83515445
A21: АДМИНИСТРАТИВНЫЕ РАСХОДЫ | B21: ='Адм.затраты'!C24 -> 2004.1208 | C21: ='Адм.затраты'!D24 -> 2004.1208 | D21: ='Адм.затраты'!E24 -> 2004.1208 | E21: ='Адм.затраты'!F24 -> 2004.1208 | F21: ='Адм.затраты'!G24 -> 2004.1208 | G21: ='Адм.затраты'!H24 -> 2004.1208 | H21: ='Адм.затраты'!I24 -> 2004.1208 | I21: ='Адм.затраты'!J24 -> 2004.1208 | ... BB21: ='Адм.затраты'!BC24 -> 87132.749
A22: ='Адм.затраты'!B8 -> Гос.пошлина | B22: ='Адм.затраты'!C8 -> 1.3708333 | C22: ='Адм.затраты'!D8 -> 1.3708333 | D22: ='Адм.затраты'!E8 -> 1.3708333 | E22: ='Адм.затраты'!F8 -> 1.3708333 | F22: ='Адм.затраты'!G8 -> 1.3708333 | G22: ='Адм.затраты'!H8 -> 1.3708333 | H22: ='Адм.затраты'!I8 -> 1.3708333 | ... BB22: ='Адм.затраты'!BC8 -> 16.45
A23: ='Адм.затраты'!B9 -> Гос.регистрация | B23: ='Адм.затраты'!C9 -> 2.1744167 | C23: ='Адм.затраты'!D9 -> 2.1744167 | D23: ='Адм.затраты'!E9 -> 2.1744167 | E23: ='Адм.затраты'!F9 -> 2.1744167 | F23: ='Адм.затраты'!G9 -> 2.1744167 | G23: ='Адм.затраты'!H9 -> 2.1744167 | H23: ='Адм.затраты'!I9 -> 2.1744167 | ... BB23: ='Адм.затраты'!BC9 -> 26.093
A24: ='Адм.затраты'!B10 -> Заправка картриджа | B24: ='Адм.затраты'!C10 -> 1.6666667 | C24: ='Адм.затраты'!D10 -> 1.6666667 | D24: ='Адм.затраты'!E10 -> 1.6666667 | E24: ='Адм.затраты'!F10 -> 1.6666667 | F24: ='Адм.затраты'!G10 -> 1.6666667 | G24: ='Адм.затраты'!H10 -> 1.6666667 | H24: ='Адм.затраты'!I10 -> 1.6666667 | ... BB24: ='Адм.затраты'!BC10 -> 117.4575
A25: ='Адм.затраты'!B11 -> Изготовление и цветная распечатка | B25: ='Адм.затраты'!C11 -> 0.27833333 | C25: ='Адм.затраты'!D11 -> 0.27833333 | D25: ='Адм.затраты'!E11 -> 0.27833333 | E25: ='Адм.затраты'!F11 -> 0.27833333 | F25: ='Адм.затраты'!G11 -> 0.27833333 | G25: ='Адм.затраты'!H11 -> 0.27833333 | H25: ='Адм.затраты'!I11 -> 0.27833333 | ... BB25: ='Адм.затраты'!BC11 -> 19.615403
A26: ='Адм.затраты'!B12 -> Канцелярские товары | B26: ='Адм.затраты'!C12 -> 5.1040408 | C26: ='Адм.затраты'!D12 -> 5.1040408 | D26: ='Адм.затраты'!E12 -> 5.1040408 | E26: ='Адм.затраты'!F12 -> 5.1040408 | F26: ='Адм.затраты'!G12 -> 5.1040408 | G26: ='Адм.затраты'!H12 -> 5.1040408 | H26: ='Адм.затраты'!I12 -> 5.1040408 | ... BB26: ='Адм.затраты'!BC12 -> 359.70474
A27: ='Адм.затраты'!B13 -> Налог на транспорт | B27: ='Адм.затраты'!C13 -> 0.52 | C27: ='Адм.затраты'!D13 -> 0.52 | D27: ='Адм.затраты'!E13 -> 0.52 | E27: ='Адм.затраты'!F13 -> 0.52 | F27: ='Адм.затраты'!G13 -> 0.52 | G27: ='Адм.затраты'!H13 -> 0.52 | H27: ='Адм.затраты'!I13 -> 0.52 | ... BB27: ='Адм.затраты'!BC13 -> 6.24
A28: ='Адм.затраты'!B14 -> Отчисления ОСМС | B28: ='Адм.затраты'!C14 -> 11.111111 | C28: ='Адм.затраты'!D14 -> 11.111111 | D28: ='Адм.затраты'!E14 -> 11.111111 | E28: ='Адм.затраты'!F14 -> 11.111111 | F28: ='Адм.затраты'!G14 -> 11.111111 | G28: ='Адм.затраты'!H14 -> 11.111111 | H28: ='Адм.затраты'!I14 -> 11.111111 | ... BB28: ='Адм.затраты'!BC14 -> 266.66667
A29: ='Адм.затраты'!B15 -> Оценка имущества | B29: ='Адм.затраты'!C15 -> 41.666667 | C29: ='Адм.затраты'!D15 -> 41.666667 | D29: ='Адм.затраты'!E15 -> 41.666667 | E29: ='Адм.затраты'!F15 -> 41.666667 | F29: ='Адм.затраты'!G15 -> 41.666667 | G29: ='Адм.затраты'!H15 -> 41.666667 | H29: ='Адм.затраты'!I15 -> 41.666667 | ... BB29: ='Адм.затраты'!BC15 -> 500
A30: ='Адм.затраты'!B16 -> Расходы по заработной плате | B30: ='Адм.затраты'!C16 -> 740.74074 | C30: ='Адм.затраты'!D16 -> 740.74074 | D30: ='Адм.затраты'!E16 -> 740.74074 | E30: ='Адм.затраты'!F16 -> 740.74074 | F30: ='Адм.затраты'!G16 -> 740.74074 | G30: ='Адм.затраты'!H16 -> 740.74074 | H30: ='Адм.затраты'!I16 -> 740.74074 | ... BB30: ='Адм.затраты'!BC16 -> 8888.8889
A31: ='Адм.затраты'!B17 -> Социальные отчисления | B31: ='Адм.затраты'!C17 -> 17.677178 | C31: ='Адм.затраты'!D17 -> 17.677178 | D31: ='Адм.затраты'!E17 -> 17.677178 | E31: ='Адм.затраты'!F17 -> 17.677178 | F31: ='Адм.затраты'!G17 -> 17.677178 | G31: ='Адм.затраты'!H17 -> 17.677178 | H31: ='Адм.затраты'!I17 -> 17.677178 | ... BB31: ='Адм.затраты'!BC17 -> 212.12613
A32: ='Адм.затраты'!B18 -> Социальный налог | B32: ='Адм.затраты'!C18 -> 45.656156 | C32: ='Адм.затраты'!D18 -> 45.656156 | D32: ='Адм.затраты'!E18 -> 45.656156 | E32: ='Адм.затраты'!F18 -> 45.656156 | F32: ='Адм.затраты'!G18 -> 45.656156 | G32: ='Адм.затраты'!H18 -> 45.656156 | H32: ='Адм.затраты'!I18 -> 45.656156 | ... BB32: ='Адм.затраты'!BC18 -> 547.87387
A33: ='Адм.затраты'!B19 -> Страхование | B33: ='Адм.затраты'!C19 -> 66.666667 | C33: ='Адм.затраты'!D19 -> 66.666667 | D33: ='Адм.затраты'!E19 -> 66.666667 | E33: ='Адм.затраты'!F19 -> 66.666667 | F33: ='Адм.затраты'!G19 -> 66.666667 | G33: ='Адм.затраты'!H19 -> 66.666667 | H33: ='Адм.затраты'!I19 -> 66.666667 | ... BB33: ='Адм.затраты'!BC19 -> 800
A34: ='Адм.затраты'!B20 -> Консалтинговые услуги | B34: ='Адм.затраты'!C20 -> 892.85714 | C34: ='Адм.затраты'!D20 -> 892.85714 | D34: ='Адм.затраты'!E20 -> 892.85714 | E34: ='Адм.затраты'!F20 -> 892.85714 | F34: ='Адм.затраты'!G20 -> 892.85714 | G34: ='Адм.затраты'!H20 -> 892.85714 | H34: ='Адм.затраты'!I20 -> 892.85714 | ... BB34: ='Адм.затраты'!BC20 -> 62923.663
A35: ='Адм.затраты'!B22 -> Услуги сотовой связи | B35: ='Адм.затраты'!C22 -> 4.0117925 | C35: ='Адм.затраты'!D22 -> 4.0117925 | D35: ='Адм.затраты'!E22 -> 4.0117925 | E35: ='Адм.затраты'!F22 -> 4.0117925 | F35: ='Адм.затраты'!G22 -> 4.0117925 | G35: ='Адм.затраты'!H22 -> 4.0117925 | H35: ='Адм.затраты'!I22 -> 4.0117925 | ... BB35: ='Адм.затраты'!BC22 -> 282.72908
A36: ='Адм.затраты'!B23 -> Аренда | B36: ='Адм.затраты'!C23 -> 89.285714 | C36: ='Адм.затраты'!D23 -> 89.285714 | D36: ='Адм.затраты'!E23 -> 89.285714 | E36: ='Адм.затраты'!F23 -> 89.285714 | F36: ='Адм.затраты'!G23 -> 89.285714 | G36: ='Адм.затраты'!H23 -> 89.285714 | H36: ='Адм.затраты'!I23 -> 89.285714 | ... BB36: ='Адм.затраты'!BC23 -> 6292.3663
A37: EBITDA | B37: =B38+'Произв.затраты'!C8 -> 22893.804 | C37: =C38+'Произв.затраты'!D8 -> 18566.192 | D37: =D38+'Произв.затраты'!E8 -> 32293.477 | E37: =E38+'Произв.затраты'!F8 -> 16803.227 | F37: =F38+'Произв.затраты'!G8 -> 45145.586 | G37: =G38+'Произв.затраты'!H8 -> 51477.541 | H37: =H38+'Произв.затраты'!I8 -> 65496.998 | I37: =I38+'Произв.затраты'!J8 -> 65496.998 | ... BB37: =BB38+'Произв.затраты'!BC8 -> 2160637.6
A38: ДОХОД/ (УБЫТОК) ДО ВОЗНАГРАЖДЕНИЯ И НАЛОГООБЛОЖЕНИЯ | B38: =B19-B21 -> 8476.5581 | C38: =C19-C21 -> 4148.9458 | D38: =D19-D21 -> 17876.231 | E38: =E19-E21 -> 2385.9815 | F38: =F19-F21 -> 30728.34 | G38: =G19-G21 -> 37060.295 | H38: =H19-H21 -> 51079.752 | I38: =I19-I21 -> 51079.752 | ... BB38: =BB19-BB21 -> 1987630.7
A39: НОРМА ОПЕРАЦИОННОЙ ПРИБЫЛИ | B39: =IF(B8=0,0,B38/B8) -> 0.29220141 | C39: =IF(C8=0,0,C38/C8) -> 0.16849542 | D39: =IF(D8=0,0,D38/D8) -> 0.46205035 | E39: =IF(E8=0,0,E38/E8) -> 0.10456988 | F39: =IF(F8=0,0,F38/F8) -> 0.59255204 | G39: =IF(G8=0,0,G38/G8) -> 0.63518628 | H39: =IF(H8=0,0,H38/H8) -> 0.70251001 | I39: =IF(I8=0,0,I38/I8) -> 0.70251001 | ... BB39: =IF(BB8=0,0,BB38/BB8) -> 0.80008091
A40: Расходы в виде вознаграждения | B40: ='Займ'!$J$26 -> 0 | C40: ='Займ'!$J$27 -> 0 | D40: ='Займ'!$J$28 -> 0 | E40: ='Займ'!$J$29 -> 0 | F40: ='Займ'!$J$30 -> 0 | G40: ='Займ'!$J$31 -> 0 | H40: ='Займ'!$J$32 -> 18669.997 | I40: ='Займ'!$J$33 -> 18669.997 | J40: ='Займ'!$J$34 -> 18669.997 | K40: ='Займ'!$J$35 -> 18669.997 | L40: ='Займ'!$J$36 -> 18669.997 | M40: ='Займ'!$J$37 -> 18669.997 | N40: =SUM(B40:M40) -> 112019.98 | O40: ='Займ'!$J$38 -> 0 | P40: ='Займ'!$J$39 -> 0 | Q40: ='Займ'!$J$40 -> 0 | R40: ='Займ'!$J$41 -> 0 | S40: ='Займ'!$J$42 -> 0 | T40: ='Займ'!$J$43 -> 0 | U40: ='Займ'!$J$44 -> 16417.19 | V40: ='Займ'!$J$45 -> 16417.19 | W40: ='Займ'!$J$46 -> 16417.19 | X40: ='Займ'!$J$47 -> 16417.19 | Y40: ='Займ'!$J$48 -> 16417.19 | Z40: ='Займ'!$J$49 -> 16417.19 | AA40: =SUM(O40:Z40) -> 98503.138 | AB40: ='Займ'!$J$50 -> 0 | AC40: ='Займ'!$J$51 -> 0 | AD40: ='Займ'!$J$52 -> 0 | AE40: ='Займ'!$J$53 -> 0 | AF40: ='Займ'!$J$54 -> 0 | AG40: ='Займ'!$J$55 -> 0 | AH40: ='Займ'!$J$56 -> 13902.517 | AI40: ='Займ'!$J$57 -> 13902.517 | AJ40: ='Займ'!$J$58 -> 13902.517 | AK40: ='Займ'!$J$59 -> 13902.517 | AL40: ='Займ'!$J$60 -> 13902.517 | AM40: ='Займ'!$J$61 -> 13902.517 | AN40: =SUM(AB40:AM40) -> 83415.1 | AO40: =SUM('Займ'!$J$62:$J$73) -> 144060.49 | AP40: =SUM('Займ'!$J$74:$J$85) -> 215941.63 | AQ40: =SUM('Займ'!$J$86:$J$97) -> 182900.43 | AR40: =SUM('Займ'!$J$98:$J$109) -> 118655.1 | AS40: =SUM('Займ'!$L$131:$L$142) -> 0 | AT40: =SUM('Займ'!$L$143:$L$154) -> 0 | AU40: =SUM('Займ'!$L$155:$L$166) -> 0 | AV40: =SUM('Займ'!$L$167:$L$178) -> 0 | AW40: =SUM('Займ'!$L$179:$L$190) -> 0
A41: ДОХОД/ (УБЫТОК) ДО НАЛОГООБЛОЖЕНИЯ | B41: =B38-B40 -> 8476.5581 | C41: =C38-C40 -> 4148.9458 | D41: =D38-D40 -> 17876.231 | E41: =E38-E40 -> 2385.9815 | F41: =F38-F40 -> 30728.34 | G41: =G38-G40 -> 37060.295 | H41: =H38-H40 -> 32409.755 | I41: =I38-I40 -> 32409.755 | ... BB41: =BB38-BB40 -> 1987630.7
A42: НОРМА ДОХОДА ДО НАЛОГООБЛОЖЕНИЯ | B42: =IF(B8=0,0,B41/B8) -> 0.29220141 | C42: =IF(C8=0,0,C41/C8) -> 0.16849542 | D42: =IF(D8=0,0,D41/D8) -> 0.46205035 | E42: =IF(E8=0,0,E41/E8) -> 0.10456988 | F42: =IF(F8=0,0,F41/F8) -> 0.59255204 | G42: =IF(G8=0,0,G41/G8) -> 0.63518628 | H42: =IF(H8=0,0,H41/H8) -> 0.44573783 | I42: =IF(I8=0,0,I41/I8) -> 0.44573783 | ... BB42: =IF(BB8=0,0,BB41/BB8) -> 0.80008091
A43: Расходы по подоходному налогу | B43: =N43/12 -> 3080.4403 | C43: =B43 -> 3080.4403 | D43: =C43 -> 3080.4403 | E43: =D43 -> 3080.4403 | F43: =E43 -> 3080.4403 | G43: =F43 -> 3080.4403 | H43: =G43 -> 3080.4403 | I43: =H43 -> 3080.4403 | J43: =I43 -> 3080.4403 | ... M43: =L43 -> 3080.4403 | N43: =IF(N41<0,0,N41*Panel!$B$27) -> 36965.284 | O43: =AA43/12 -> 4121.8767 | P43: =O43 -> 4121.8767 | Q43: =P43 -> 4121.8767 | R43: =Q43 -> 4121.8767 | S43: =R43 -> 4121.8767 | T43: =S43 -> 4121.8767 | U43: =T43 -> 4121.8767 | V43: =U43 -> 4121.8767 | W43: =V43 -> 4121.8767 | ... Z43: =Y43 -> 4121.8767 | AA43: =IF(AA41<0,0,AA41*Panel!$B$27) -> 49462.521 | AB43: =AN43/12 -> 5264.8651 | AC43: =AB43 -> 5264.8651 | AD43: =AC43 -> 5264.8651 | AE43: =AD43 -> 5264.8651 | AF43: =AE43 -> 5264.8651 | AG43: =AF43 -> 5264.8651 | AH43: =AG43 -> 5264.8651 | AI43: =AH43 -> 5264.8651 | AJ43: =AI43 -> 5264.8651 | ... AM43: =AL43 -> 5264.8651 | AN43: =IF(AN41<0,0,AN41*Panel!$B$27) -> 63178.382 | AO43: =IF(AO41<0,0,AO41*Panel!$B$27) -> 62794.951 | AP43: =IF(AP41<0,0,AP41*Panel!$B$27) -> 61283.354 | AQ43: =IF(AQ41<0,0,AQ41*Panel!$B$27) -> 81982.871 | AR43: =IF(AR41<0,0,AR41*Panel!$B$27) -> 110267.81 | AS43: =IF(AS41<0,0,AS41*Panel!$B$27) -> 150908.53 | AT43: =IF(AT41<0,0,AT41*Panel!$B$27) -> 169433.61 | AU43: =IF(AU41<0,0,AU41*Panel!$B$27) -> 189729.15 | ... BB43: =IF(BB41<0,0,BB41*Panel!$B$27) -> 397526.14
A44: ЧИСТЫЙ ДОХОД/ (УБЫТОК) | B44: =B41-B43 -> 5396.1178 | C44: =C41-C43 -> 1068.5054 | D44: =D41-D43 -> 14795.791 | E44: =E41-E43 -> -694.45879 | F44: =F41-F43 -> 27647.899 | G44: =G41-G43 -> 33979.855 | H44: =H41-H43 -> 29329.315 | I44: =I41-I43 -> 29329.315 | ... BB44: =BB41-BB43 -> 1590104.6
A45: НОРМА ЧИСТОЙ ПРИБЫЛИ | B45: =IF(B8=0,0,B44/B8) -> 0.18601338 | C45: =IF(C8=0,0,C44/C8) -> 0.043393739 | D45: =IF(D8=0,0,D44/D8) -> 0.38242962 | E45: =IF(E8=0,0,E44/E8) -> -0.03043589 | F45: =IF(F8=0,0,F44/F8) -> 0.53315016 | G45: =IF(G8=0,0,G44/G8) -> 0.58238979 | H45: =IF(H8=0,0,H44/H8) -> 0.40337192 | I45: =IF(I8=0,0,I44/I8) -> 0.40337192 | ... BB45: =IF(BB8=0,0,BB44/BB8) -> 0.64006473
N47: =(N37-'Произв.затраты'!O8)/'ОДДС'!AG23 -> 2.6499416 | O47: =(O37-'Произв.затраты'!P8)/'ОДДС'!AH23 -> #DIV/0! | P47: =(P37-'Произв.затраты'!Q8)/'ОДДС'!AI23 -> #DIV/0! | Q47: =(Q37-'Произв.затраты'!R8)/'ОДДС'!AJ23 -> #DIV/0! | R47: =(R37-'Произв.затраты'!S8)/'ОДДС'!AK23 -> #DIV/0! | S47: =(S37-'Произв.затраты'!T8)/'ОДДС'!AL23 -> #DIV/0! | T47: =(T37-'Произв.затраты'!U8)/'ОДДС'!AM23 -> #DIV/0! | U47: =(U37-'Произв.затраты'!V8)/'ОДДС'!AN23 -> 3.5188819 | ... AR47: =(AR37-'Произв.затраты'!AS8)/'ОДДС'!BK23 -> 5.6465686
N49: =('Инвестиции'!F15-SUM('Займ'!F26:F37))/N37 -> 4.700002

Sheet ОДДС
A1: =Panel!A1
A2: =Panel!A2 -> Строительство ГЭС -5 МВТ
BP3: =60*300 -> 18000
A4: ОТЧЕТ О ДВИЖЕНИИ ДЕНЕЖНЫХ СРЕДСТВ (про-форма)
B5: =Panel!$B$26 -> 0.16 | C5: =Panel!$B$26 -> 0.16 | D5: =Panel!$B$26 -> 0.16 | E5: =Panel!$B$26 -> 0.16 | F5: =Panel!$B$26 -> 0.16 | G5: =Panel!$B$26 -> 0.16 | H5: =Panel!$B$26 -> 0.16 | I5: =Panel!$B$26 -> 0.16 | ... BU5: =Panel!$B$26 -> 0.16
A6: в тыс.тенге, если не указано иное
A7: ДВИЖЕНИЕ ДЕНЕГ ОТ ОПЕРАЦИОННОЙ ДЕЯТЕЛЬНОСТИ ПО ПРЯМОМУ МЕТОДУ | B7: авг | C7: сен | D7: окт | E7: ноя | F7: дек | G7: 2030 | H7: янв | I7: фев | J7: мар | K7: апр | L7: май | M7: июн | N7: июл | O7: авг | P7: сен | Q7: окт | R7: ноя | S7: дек | T7: 2031 | U7: янв | V7: фев | W7: мар | X7: апр | Y7: май | Z7: июн | AA7: июл | AB7: авг | AC7: сен | AD7: окт | AE7: ноя | AF7: дек | AG7: 2026 | AH7: янв | AI7: фев | AJ7: мар | AK7: апр | AL7: май | AM7: июн | AN7: июл | AO7: авг | AP7: сен | AQ7: окт | AR7: ноя | AS7: дек | AT7: 2027 | AU7: янв | AV7: фев | AW7: мар | AX7: апр | AY7: май | AZ7: июн | BA7: июл | BB7: авг | BC7: сен | BD7: окт | BE7: ноя | BF7: дек | BG7: 2028 | BH7: 2029 | BI7: 2030 | BJ7: 2031 | BK7: 2032 | BL7: 2033 | BM7: 2034 | BN7: 2035 | BO7: 2036 | BP7: 2037 | BQ7: 2038 | BR7: 2039 | BS7: 2040 | BT7: 2041 | BU7: 2042
A9: ПРИТОК ДЕНЕЖНЫХ СРЕДСТВ:
A10: Поступление денег от продажи товаров и оказания услуг (вкл. НДС) | U10: ='ОПиУ'!B8*(1+'ОДДС'!U5) -> 33650.787 | V10: ='ОПиУ'!C8*(1+'ОДДС'!V5) -> 28563.252 | W10: ='ОПиУ'!D8*(1+'ОДДС'!W5) -> 44879.153 | X10: ='ОПиУ'!E8*(1+'ОДДС'!X5) -> 26467.837 | Y10: ='ОПиУ'!F8*(1+'ОДДС'!Y5) -> 60154.841 | Z10: ='ОПиУ'!G8*(1+'ОДДС'!Z5) -> 67680.842 | AA10: ='ОПиУ'!H8*(1+'ОДДС'!AA5) -> 84344.01 | AB10: ='ОПиУ'!I8*(1+'ОДДС'!AB5) -> 84344.01 | ... BU10: ='ОПиУ'!BB8*(1+'ОДДС'!BU5) -> 2881773.1
A11: Авансы, полученные под поставку ТМЗ и оказание услуг | G11: =SUM(B11:F11) -> 0 | T11: =SUM(H11:S11) -> 0 | AG11: 0 | AT11: 0 | BG11: 0 | BH11: 0 | BI11: 0 | BJ11: 0 | BK11: 0 | BL11: 0 | BM11: 0 | BN11: 0 | BO11: 0 | BP11: 0 | BQ11: 0 | BR11: 0 | BS11: 0 | BT11: 0 | BU11: 0
A12: Поступление денег в виде вознаграждений, дивидендов и роялти | G12: =SUM(B12:F12) -> 0 | T12: =SUM(H12:S12) -> 0 | AG12: 0 | AT12: 0 | BG12: 0 | BH12: 0 | BI12: 0 | BJ12: 0 | BK12: 0 | BL12: 0 | BM12: 0 | BN12: 0 | BO12: 0 | BP12: 0 | BQ12: 0 | BR12: 0 | BS12: 0 | BT12: 0 | BU12: 0
A13: Поступление денег в виде субсидий исполнительных органов власти | G13: =SUM(B13:F13) -> 0 | T13: =SUM(H13:S13) -> 0 | AG13: 0 | AT13: 0 | BG13: 0 | BH13: 0 | BI13: 0 | BJ13: 0 | BK13: 0 | BL13: 0 | BM13: 0 | BN13: 0 | BO13: 0 | BP13: 0 | BQ13: 0 | BR13: 0 | BS13: 0 | BT13: 0 | BU13: 0
A14: Прочие поступления | G14: =SUM(B14:F14) -> 0 | T14: =SUM(H14:S14) -> 0 | AG14: 0 | AT14: 0 | BG14: 0 | BH14: 0 | BI14: 0 | BJ14: 0 | BK14: 0 | BL14: 0 | BM14: 0 | BN14: 0 | BO14: 0 | BP14: 0 | BQ14: 0 | BR14: 0 | BS14: 0 | BT14: 0 | BU14: 0
A15: ИТОГО ПРИТОК ДЕНЕЖНЫХ СРЕДСТВ | B15: =SUM(B10:B14) -> 0 | C15: =SUM(C10:C14) -> 0 | D15: =SUM(D10:D14) -> 0 | E15: =SUM(E10:E14) -> 0 | F15: =SUM(F10:F14) -> 0 | G15: =SUM(G10:G14) -> 0 | H15: =SUM(H10:H14) -> 0 | I15: =SUM(I10:I14) -> 0 | ... BU15: =SUM(BU10:BU14) -> 2881773.1
A17: ОТТОК ДЕНЕЖНЫХ СРЕДСТВ, вкл. НДС:
A18: Выплаты заработной платы (вкл. пенс.отч и ИПН) | U18: ='Адм.затраты'!C16 -> 740.74074 | V18: ='Адм.затраты'!D16 -> 740.74074 | W18: ='Адм.затраты'!E16 -> 740.74074 | X18: ='Адм.затраты'!F16 -> 740.74074 | Y18: ='Адм.затраты'!G16 -> 740.74074 | Z18: ='Адм.затраты'!H16 -> 740.74074 | AA18: ='Адм.затраты'!I16 -> 740.74074 | AB18: ='Адм.затраты'!J16 -> 740.74074 | ... BU18: ='Адм.затраты'!BC16 -> 8888.8889
A19: Выплаты за сырье, материалы и эксплуатационные, облагаемые НДС | U19: =('Адм.затраты'!C10+'Адм.затраты'!C11+'Адм.затраты'!C12+'Адм.затраты'!C20+'Адм.затраты'!C22+'Адм.затраты'!C23+'Произв.затраты'!C9+'Произв.затраты'!C10+'Произв.затраты'!C14+'Произв.затраты'!C15+'Произв.затраты'!C16)*(1+U5) -> 4624.1653 | V19: =('Адм.затраты'!D10+'Адм.затраты'!D11+'Адм.затраты'!D12+'Адм.затраты'!D20+'Адм.затраты'!D22+'Адм.затраты'!D23+'Произв.затраты'!D9+'Произв.затраты'!D10+'Произв.затраты'!D14+'Произв.затраты'!D15+'Произв.затраты'!D16)*(1+V5) -> 4574.4288 | W19: =('Адм.затраты'!E10+'Адм.затраты'!E11+'Адм.затраты'!E12+'Адм.затраты'!E20+'Адм.затраты'!E22+'Адм.затраты'!E23+'Произв.затраты'!E9+'Произв.затраты'!E10+'Произв.затраты'!E14+'Произв.затраты'!E15+'Произв.затраты'!E16)*(1+W5) -> 4909.6941 | X19: =('Адм.затраты'!F10+'Адм.затраты'!F11+'Адм.затраты'!F12+'Адм.затраты'!F20+'Адм.затраты'!F22+'Адм.затраты'!F23+'Произв.затраты'!F9+'Произв.затраты'!F10+'Произв.затраты'!F14+'Произв.затраты'!F15+'Произв.затраты'!F16)*(1+X5) -> 4531.3714 | Y19: =('Адм.затраты'!G10+'Адм.затраты'!G11+'Адм.затраты'!G12+'Адм.затраты'!G20+'Адм.затраты'!G22+'Адм.затраты'!G23+'Произв.затраты'!G9+'Произв.затраты'!G10+'Произв.затраты'!G14+'Произв.затраты'!G15+'Произв.затраты'!G16)*(1+Y5) -> 5223.5847 | Z19: =('Адм.затраты'!H10+'Адм.затраты'!H11+'Адм.затраты'!H12+'Адм.затраты'!H20+'Адм.затраты'!H22+'Адм.затраты'!H23+'Произв.затраты'!H9+'Произв.затраты'!H10+'Произв.затраты'!H14+'Произв.затраты'!H15+'Произв.затраты'!H16)*(1+Z5) -> 5378.2318 | AA19: =('Адм.затраты'!I10+'Адм.затраты'!I11+'Адм.затраты'!I12+'Адм.затраты'!I20+'Адм.затраты'!I22+'Адм.затраты'!I23+'Произв.затраты'!I9+'Произв.затраты'!I10+'Произв.затраты'!I14+'Произв.затраты'!I15+'Произв.затраты'!I16)*(1+AA5) -> 5720.6329 | AB19: =('Адм.затраты'!J10+'Адм.затраты'!J11+'Адм.затраты'!J12+'Адм.затраты'!J20+'Адм.затраты'!J22+'Адм.затраты'!J23+'Произв.затраты'!J9+'Произв.затраты'!J10+'Произв.затраты'!J14+'Произв.затраты'!J15+'Произв.затраты'!J16)*(1+AB5) -> 5720.6329 | ... BU19: =('Адм.затраты'!BC10+'Адм.затраты'!BC11+'Адм.затраты'!BC12+'Адм.затраты'!BC20+'Адм.затраты'!BC22+'Адм.затраты'!BC23+'Произв.затраты'!BC9+'Произв.затраты'!BC10+'Произв.затраты'!BC14+'Произв.затраты'!BC15+'Произв.затраты'!BC16)*(1+BU5) -> 353211.65
A20: Авансы выданные
A21: Выплаты за услуги и прочее, не облагаемые НДС | U21: ='Адм.затраты'!C19+'Адм.затраты'!C21+'Адм.затраты'!C15 -> 191.66667 | V21: ='Адм.затраты'!D19+'Адм.затраты'!D21+'Адм.затраты'!D15 -> 191.66667 | W21: ='Адм.затраты'!E19+'Адм.затраты'!E21+'Адм.затраты'!E15 -> 191.66667 | X21: ='Адм.затраты'!F19+'Адм.затраты'!F21+'Адм.затраты'!F15 -> 191.66667 | Y21: ='Адм.затраты'!G19+'Адм.затраты'!G21+'Адм.затраты'!G15 -> 191.66667 | Z21: ='Адм.затраты'!H19+'Адм.затраты'!H21+'Адм.затраты'!H15 -> 191.66667 | AA21: ='Адм.затраты'!I19+'Адм.затраты'!I21+'Адм.затраты'!I15 -> 191.66667 | AB21: ='Адм.затраты'!J19+'Адм.затраты'!J21+'Адм.затраты'!J15 -> 191.66667 | ... BU21: ='Адм.затраты'!BC19+'Адм.затраты'!BC21+'Адм.затраты'!BC15 -> 7172.8752
A22: Налоги (имущ., социальный, зем.) | U22: ='Произв.затраты'!C11+'Произв.затраты'!C12+'Произв.затраты'!C13+'Адм.затраты'!C8+'Адм.затраты'!C9+'Адм.затраты'!C13+'Адм.затраты'!C14+'Адм.затраты'!C17+'Адм.затраты'!C18 -> 1196.7386 | V22: ='Произв.затраты'!D11+'Произв.затраты'!D12+'Произв.затраты'!D13+'Адм.затраты'!D8+'Адм.затраты'!D9+'Адм.затраты'!D13+'Адм.затраты'!D14+'Адм.затраты'!D17+'Адм.затраты'!D18 -> 1181.4207 | W22: ='Произв.затраты'!E11+'Произв.затраты'!E12+'Произв.затраты'!E13+'Адм.затраты'!E8+'Адм.затраты'!E9+'Адм.затраты'!E13+'Адм.затраты'!E14+'Адм.затраты'!E17+'Адм.затраты'!E18 -> 1230.5456 | X22: ='Произв.затраты'!F11+'Произв.затраты'!F12+'Произв.затраты'!F13+'Адм.затраты'!F8+'Адм.затраты'!F9+'Адм.затраты'!F13+'Адм.затраты'!F14+'Адм.затраты'!F17+'Адм.затраты'!F18 -> 1175.1117 | Y22: ='Произв.затраты'!G11+'Произв.затраты'!G12+'Произв.затраты'!G13+'Адм.затраты'!G8+'Адм.затраты'!G9+'Адм.затраты'!G13+'Адм.затраты'!G14+'Адм.затраты'!G17+'Адм.затраты'!G18 -> 1276.5385 | Z22: ='Произв.затраты'!H11+'Произв.затраты'!H12+'Произв.затраты'!H13+'Адм.затраты'!H8+'Адм.затраты'!H9+'Адм.затраты'!H13+'Адм.затраты'!H14+'Адм.затраты'!H17+'Адм.затраты'!H18 -> 1299.1982 | AA22: ='Произв.затраты'!I11+'Произв.затраты'!I12+'Произв.затраты'!I13+'Адм.затраты'!I8+'Адм.затраты'!I9+'Адм.затраты'!I13+'Адм.затраты'!I14+'Адм.затраты'!I17+'Адм.затраты'!I18 -> 1349.3686 | AB22: ='Произв.затраты'!J11+'Произв.затраты'!J12+'Произв.затраты'!J13+'Адм.затраты'!J8+'Адм.затраты'!J9+'Адм.затраты'!J13+'Адм.затраты'!J14+'Адм.затраты'!J17+'Адм.затраты'!J18 -> 1349.3686 | ... BU22: ='Произв.затраты'!BC11+'Произв.затраты'!BC12+'Произв.затраты'!BC13+'Адм.затраты'!BC8+'Адм.затраты'!BC9+'Адм.затраты'!BC13+'Адм.затраты'!BC14+'Адм.затраты'!BC17+'Адм.затраты'!BC18 -> 3094.9065
A23: Выплата вознаграждения | I23: ='Займ'!I15 -> 0 | J23: ='Займ'!I16 -> 0 | K23: ='Займ'!I17 -> 4718.2969 | L23: ='Займ'!I18 -> 5846.1064 | M23: ='Займ'!I19 -> 6973.916 | N23: ='Займ'!I20 -> 8101.7255 | O23: ='Займ'!I21 -> 9229.535 | P23: ='Займ'!I22 -> 10357.344 | Q23: ='Займ'!I23 -> 11485.154 | R23: ='Займ'!I24 -> 12612.964 | S23: ='Займ'!I25 -> 13740.773 | T23: =SUM(H23:S23) -> 83065.815 | U23: ='ОПиУ'!B40 -> 0 | V23: ='ОПиУ'!C40 -> 0 | W23: ='ОПиУ'!D40 -> 0 | X23: ='ОПиУ'!E40 -> 0 | Y23: ='ОПиУ'!F40 -> 0 | Z23: ='ОПиУ'!G40 -> 0 | AA23: ='ОПиУ'!H40 -> 18669.997 | AB23: ='ОПиУ'!I40 -> 18669.997 | ... AF23: ='ОПиУ'!M40 -> 18669.997 | AG23: =SUM(U23:AF23) -> 112019.98 | AH23: ='ОПиУ'!O40 -> 0 | AI23: ='ОПиУ'!P40 -> 0 | AJ23: ='ОПиУ'!Q40 -> 0 | AK23: ='ОПиУ'!R40 -> 0 | AL23: ='ОПиУ'!S40 -> 0 | AM23: ='ОПиУ'!T40 -> 0 | AN23: ='ОПиУ'!U40 -> 16417.19 | AO23: ='ОПиУ'!V40 -> 16417.19 | ... AS23: ='ОПиУ'!Z40 -> 16417.19 | AT23: =SUM(AH23:AS23) -> 98503.138 | AU23: ='ОПиУ'!AB40 -> 0 | AV23: ='ОПиУ'!AC40 -> 0 | AW23: ='ОПиУ'!AD40 -> 0 | AX23: ='ОПиУ'!AE40 -> 0 | AY23: ='ОПиУ'!AF40 -> 0 | AZ23: ='ОПиУ'!AG40 -> 0 | BA23: ='ОПиУ'!AH40 -> 13902.517 | BB23: ='ОПиУ'!AI40 -> 13902.517 | ... BF23: ='ОПиУ'!AM40 -> 13902.517 | BG23: =SUM(AU23:BF23) -> 83415.1 | BH23: ='ОПиУ'!AO40 -> 144060.49 | BI23: ='ОПиУ'!AP40 -> 215941.63 | BJ23: ='ОПиУ'!AQ40 -> 182900.43 | BK23: ='ОПиУ'!AR40 -> 118655.1 | BL23: ='ОПиУ'!AS40 -> 0 | BM23: ='ОПиУ'!AT40 -> 0 | BN23: ='ОПиУ'!AU40 -> 0 | BO23: ='ОПиУ'!AV40 -> 0 | ... BU23: ='ОПиУ'!BB40
A24: Расчеты по подоходному налогу | U24: ='ОПиУ'!B43 -> 3080.4403 | V24: ='ОПиУ'!C43 -> 3080.4403 | W24: ='ОПиУ'!D43 -> 3080.4403 | X24: ='ОПиУ'!E43 -> 3080.4403 | Y24: ='ОПиУ'!F43 -> 3080.4403 | Z24: ='ОПиУ'!G43 -> 3080.4403 | AA24: ='ОПиУ'!H43 -> 3080.4403 | AB24: ='ОПиУ'!I43 -> 3080.4403 | ... BU24: ='ОПиУ'!BB43 -> 397526.14
A25: Прочие выплаты
A26: Выплаты по НДС | U26: =U91 -> 0 | V26: =V91 -> 0 | W26: =W91 -> 0 | X26: =X91 -> 0 | Y26: =Y91 -> 0 | Z26: =Z91 -> 0 | AA26: =AA91 -> 0 | AB26: =AB91 -> 0 | ... AF26: =AF91 -> 0 | AG26: =SUM(U26:AF26) -> 0 | AH26: =AH91 -> 0 | AI26: =AI91 -> 0 | AJ26: =AJ91 -> 0 | AK26: =AK91 -> 0 | AL26: =AL91 -> 0 | AM26: =AM91 -> 0 | AN26: =AN91 -> 0 | AO26: =AO91 -> 0 | ... AS26: =AS91 -> 0 | AT26: =SUM(AH26:AS26) -> 0 | AU26: =AU91 -> 0 | AV26: =AV91 -> 0 | AW26: =AW91 -> 0 | AX26: =AX91 -> 0 | AY26: =AY91 -> 0 | AZ26: =AZ91 -> 0 | BA26: =BA91 -> 0 | BB26: =BB91 -> 0 | ... BF26: =BF91 -> 0 | BG26: =SUM(AU26:BF26) -> 0 | BH26: =BH91 -> 0 | BI26: =BI91 -> 76963.031 | BJ26: =BJ91 -> 203140.2 | BK26: =BK91 -> 138419.66 | BL26: =BL91 -> 151845.01 | BM26: =BM91 -> 166566.92 | BN26: =BN91 -> 182709.94 | BO26: =BO91 -> 200410.52 | ... BU26: =BU91 -> 348767.09
A27: ИТОГО ОТТОК ДЕНЕЖНЫХ СРЕДСТВ | B27: =SUM(B18:B26) -> 0 | C27: =SUM(C18:C26) -> 0 | D27: =SUM(D18:D26) -> 0 | E27: =SUM(E18:E26) -> 0 | F27: =SUM(F18:F26) -> 0 | G27: =SUM(G18:G26) -> 0 | H27: =SUM(H18:H26) -> 0 | I27: =SUM(I18:I26) -> 0 | ... BU27: =SUM(BU18:BU26) -> 1118661.6
A29: ИТОГО ЧИСТЫЙ ДЕНЕЖНЫЙ ПОТОК (+/-) ОТ ОПЕРАЦИОННОЙ ДЕЯТЕЛЬНОСТИ | B29: =B15-B27 -> 0 | C29: =C15-C27 -> 0 | D29: =D15-D27 -> 0 | E29: =E15-E27 -> 0 | F29: =F15-F27 -> 0 | G29: =G15-G27 -> 0 | H29: =H15-H27 -> 0 | I29: =I15-I27 -> 0 | ... BU29: =BU15-BU27 -> 1763111.5
A31: ДВИЖЕНИЕ ДЕНЕГ ОТ ИНВЕСТИЦИОННОЙ ДЕЯТЕЛЬНОСТИ:
A33: ПРИТОК ДЕНЕЖНЫХ СРЕДСТВ:
A34: Реализация нематериальных активов | G34: 0 | T34: 0 | AG34: 0 | AT34: 0 | BG34: 0 | BH34: 0 | BI34: 0 | BJ34: 0 | BK34: 0 | BL34: 0 | BM34: 0 | BN34: 0 | BO34: 0 | BP34: 0 | BQ34: 0 | BR34: 0 | BS34: 0 | BT34: 0 | BU34: 0
A35: Реализация основных средств и других долгосрочных активов | G35: 0 | T35: 0 | AG35: 0 | AT35: 0 | BG35: 0 | BH35: 0 | BI35: 0 | BJ35: 0 | BK35: 0 | BL35: 0 | BM35: 0 | BN35: 0 | BO35: 0 | BP35: 0 | BQ35: 0 | BR35: 0 | BS35: 0 | BT35: 0 | BU35: 0
A36: Получение займов, предоставленных другим юридическим лицам | G36: 0 | T36: 0 | AG36: 0 | AT36: 0 | BG36: 0 | BH36: 0 | BI36: 0 | BJ36: 0 | BK36: 0 | BL36: 0 | BM36: 0 | BN36: 0 | BO36: 0 | BP36: 0 | BQ36: 0 | BR36: 0 | BS36: 0 | BT36: 0 | BU36: 0
A37: Прочие поступления | G37: 0 | T37: 0 | AG37: 0 | AT37: 0 | BG37: 0 | BH37: 0 | BI37: 0 | BJ37: 0 | BK37: 0 | BL37: 0 | BM37: 0 | BN37: 0 | BO37: 0 | BP37: 0 | BQ37: 0 | BR37: 0 | BS37: 0 | BT37: 0 | BU37: 0
A38: ИТОГО ПРИТОК ДЕНЕЖНЫХ СРЕДСТВ | B38: =SUM(B34:B37) -> 0 | C38: =SUM(C34:C37) -> 0 | D38: =SUM(D34:D37) -> 0 | E38: =SUM(E34:E37) -> 0 | F38: =SUM(F34:F37) -> 0 | G38: =SUM(G34:G37) -> 0 | H38: =SUM(H34:H37) -> 0 | I38: =SUM(I34:I37) -> 0 | ... T38: =SUM(T34:T37) -> 0 | AG38: =SUM(AG34:AG37) -> 0 | AT38: =SUM(AT34:AT37) -> 0 | BG38: =SUM(BG34:BG37) -> 0 | BH38: =SUM(BH34:BH37) -> 0 | BI38: =SUM(BI34:BI37) -> 0 | BJ38: =SUM(BJ34:BJ37) -> 0 | BK38: =SUM(BK34:BK37) -> 0 | BL38: =SUM(BL34:BL37) -> 0 | BM38: =SUM(BM34:BM37) -> 0 | BN38: =SUM(BN34:BN37) -> 0 | ... BU38: =SUM(BU34:BU37) -> 0
A40: ОТТОК ДЕНЕЖНЫХ СРЕДСТВ:
A41: Приобретение нематериальных активов | G41: =SUM(B41:F41) -> 0 | T41: =SUM(H41:S41) -> 0 | AG41: =SUM(U41:AF41) -> 0 | AT41: 0 | BG41: 0 | BH41: 0 | BI41: 0 | BJ41: 0 | BK41: 0 | BL41: 0 | BM41: 0 | BN41: 0 | BO41: 0 | BP41: 0 | BQ41: 0 | BR41: 0 | BS41: 0 | BT41: 0 | BU41: 0
A42: Приобретение основных средств и других долгосрочных активов | B42: ='A-0'!J14 -> 0 | C42: ='A-0'!K14 -> 0 | D42: ='A-0'!L14 -> 0 | E42: ='A-0'!M14 -> 0 | F42: ='A-0'!N14 -> 0 | G42: =SUM(B42:F42) -> 0 | H42: ='A-0'!O14 -> 241673.47 | I42: ='A-0'!P14 -> 241673.47 | J42: ='A-0'!Q14 -> 241673.47 | K42: ='A-0'!R14 -> 241673.47 | L42: ='A-0'!S14 -> 241673.47 | M42: ='A-0'!T14 -> 241673.47 | N42: ='A-0'!U14 -> 241673.47 | O42: ='A-0'!V14 -> 241673.47 | ... S42: ='A-0'!Z14 -> 241673.47 | T42: =SUM(H42:S42) -> 2900081.6
A43: Незавершенное строительство | G43: =SUM(B43:F43) -> 0 | T43: =SUM(H43:S43) -> 0 | AG43: =SUM(U43:AF43) -> 0 | AT43: 0 | BG43: 0 | BH43: 0 | BI43: 0 | BJ43: 0 | BK43: 0 | BL43: 0 | BM43: 0 | BN43: 0 | BO43: 0 | BP43: 0 | BQ43: 0 | BR43: 0 | BS43: 0 | BT43: 0 | BU43: 0
A44: Предоставление займов другим юридическим лицам | G44: =SUM(B44:F44) -> 0 | T44: =SUM(H44:S44) -> 0 | AG44: =SUM(U44:AF44) -> 0 | AT44: 0 | BG44: 0 | BH44: 0 | BI44: 0 | BJ44: 0 | BK44: 0 | BL44: 0 | BM44: 0 | BN44: 0 | BO44: 0 | BP44: 0 | BQ44: 0 | BR44: 0 | BS44: 0 | BT44: 0 | BU44: 0
A45: Прочие выплаты | G45: =SUM(B45:F45) -> 0 | H45: ='A-0'!O9 -> 35495.805 | T45: =SUM(H45:S45) -> 35495.805 | AG45: =SUM(U45:AF45) -> 0 | AT45: 0 | BG45: 0 | BH45: 0 | BI45: 0 | BJ45: 0 | BK45: 0 | BL45: 0 | BM45: 0 | BN45: 0 | BO45: 0 | BP45: 0 | BQ45: 0 | BR45: 0 | BS45: 0 | BT45: 0 | BU45: 0
A46: ИТОГО ОТТОК ДЕНЕЖНЫХ СРЕДСТВ | B46: =SUM(B41:B45) -> 0 | C46: =SUM(C41:C45) -> 0 | D46: =SUM(D41:D45) -> 0 | E46: =SUM(E41:E45) -> 0 | F46: =SUM(F41:F45) -> 0 | G46: =SUM(G41:G45) -> 0 | H46: =SUM(H41:H45) -> 277169.27 | I46: =SUM(I41:I45) -> 241673.47 | ... BU46: =SUM(BU41:BU45) -> 0
A48: ИТОГО ЧИСТЫЙ ДЕНЕЖНЫЙ ПОТОК (+/-) ОТ ИНВЕСТИЦИОННОЙ ДЕЯТЕЛЬНОСТИ | B48: =B38-B46 -> 0 | C48: =C38-C46 -> 0 | D48: =D38-D46 -> 0 | E48: =E38-E46 -> 0 | F48: =F38-F46 -> 0 | G48: =G38-G46 -> 0 | H48: =H38-H46 -> -277169.27 | I48: =I38-I46 -> -241673.47 | ... BU48: =BU38-BU46 -> 0
A50: ДВИЖЕНИЕ ДЕНЕГ ОТ ФИНАНСОВОЙ ДЕЯТЕЛЬНОСТИ:
A52: ПРИТОК ДЕНЕЖНЫХ СРЕДСТВ:
A53: Выпуск акций, облигаций, поступление собственных средств | C53: ='A-0'!K16 -> 0 | D53: ='A-0'!L16 -> 0 | E53: ='A-0'!M16 -> 0 | F53: ='A-0'!N16 -> 0 | G53: =SUM(B53:F53) -> 0 | H53: ='A-0'!O16 -> 48334.694 | I53: ='A-0'!P16 -> 48334.694 | J53: ='A-0'!Q16 -> 48334.694 | K53: ='A-0'!R16 -> 48334.694 | L53: ='A-0'!S16 -> 48334.694 | M53: ='A-0'!T16 -> 48334.694 | N53: ='A-0'!U16 -> 48334.694 | O53: ='A-0'!V16 -> 48334.694 | ... S53: ='A-0'!Z16 -> 48334.694 | T53: =SUM(H53:S53) -> 580016.32 | U53: =U42 | V53: =V42 | W53: =W42 | X53: =X42 | Y53: =Y42 | Z53: =Z42 | AA53: =AA42 | AB53: =AB42 | ... BU53: =BU42
A54: Получение займов от финансовых учреждений | C54: ='A-0'!K22 -> 0 | D54: ='A-0'!L22 -> 0 | E54: ='A-0'!M22 -> 0 | F54: ='A-0'!N22 -> 0 | G54: =SUM(B54:F54) -> 0 | H54: ='A-0'!O22 -> 228834.58 | I54: ='A-0'!P22 -> 193338.77 | J54: ='A-0'!Q22 -> 193338.77 | K54: ='A-0'!R22 -> 193338.77 | L54: ='A-0'!S22 -> 193338.77 | M54: ='A-0'!T22 -> 193338.77 | N54: ='A-0'!U22 -> 193338.77 | O54: ='A-0'!V22 -> 193338.77 | ... S54: ='A-0'!Z22 -> 193338.77 | T54: =SUM(H54:S54) -> 2355561.1 | AG54: =SUM(U54:AF54) -> 0
A55: Поступление собственных средств (оборотные средства) | G55: =SUM(B55:F55) -> 0 | T55: =SUM(H55:S55) -> 0 | AG55: =SUM(U55:AF55) -> 0
A56: Финансовая помощь, полученная от аффилиированных компаний | G56: =SUM(B56:F56) -> 0 | K56: =K23 -> 4718.2969 | L56: =L23 -> 5846.1064 | M56: =M23 -> 6973.916 | N56: =N23 -> 8101.7255 | O56: =O23 -> 9229.535 | P56: =P23 -> 10357.344 | Q56: =Q23 -> 11485.154 | R56: =R23 -> 12612.964 | S56: =S23 -> 13740.773 | T56: =SUM(H56:S56) -> 83065.815 | X56: 1400 | AG56: =SUM(U56:AF56) -> 1400 | AT56: 0 | BG56: 0 | BH56: 0 | BI56: 0 | BJ56: 0
A57: Прочие поступления | G57: =SUM(B57:F57) -> 0 | T57: =SUM(H57:S57) -> 0 | AG57: =SUM(U57:AF57) -> 0
A58: ИТОГО ПРИТОК ДЕНЕЖНЫХ СРЕДСТВ | B58: =SUM(B53:B57) -> 0 | C58: =SUM(C53:C57) -> 0 | D58: =SUM(D53:D57) -> 0 | E58: =SUM(E53:E57) -> 0 | F58: =SUM(F53:F57) -> 0 | G58: =SUM(G53:G57) -> 0 | H58: =SUM(H53:H57) -> 277169.27 | I58: =SUM(I53:I57) -> 241673.47 | ... BU58: =SUM(BU53:BU57) -> 0
A60: ОТТОК ДЕНЕЖНЫХ СРЕДСТВ:
A61: Погашение займов финансовых учреждений | G61: =SUM(B61:F61) -> 0 | T61: =SUM(H61:S61) -> 0 | U61: ='Займ'!$E$26 -> 0 | V61: ='Займ'!$E$27 -> 0 | W61: ='Займ'!$E$28 -> 0 | X61: ='Займ'!$F$29 -> 0 | Y61: ='Займ'!$F$30 -> 0 | Z61: ='Займ'!$F$31 -> 0 | AA61: ='Займ'!$F$32 -> 24541.565 | AB61: ='Займ'!$F$33 -> 24541.565 | AC61: ='Займ'!$F$34 -> 24541.565 | AD61: ='Займ'!$F$35 -> 24541.565 | AE61: ='Займ'!$F$36 -> 24541.565 | AF61: ='Займ'!$F$37 -> 24541.565 | AG61: =SUM(U61:AF61) -> 147249.39 | AH61: ='Займ'!$F$38 -> 0 | AI61: ='Займ'!$F$39 -> 0 | AJ61: ='Займ'!$F$40 -> 0 | AK61: ='Займ'!$F$41 -> 0 | AL61: ='Займ'!$F$42 -> 0 | AM61: ='Займ'!$F$43 -> 0 | AN61: ='Займ'!$F$44 -> 34785.866 | AO61: ='Займ'!$F$45 -> 34785.866 | AP61: ='Займ'!$F$46 -> 34785.866 | AQ61: ='Займ'!$F$47 -> 34785.866 | AR61: ='Займ'!$F$48 -> 34785.866 | AS61: ='Займ'!$F$49 -> 34785.866 | AT61: =SUM(AH61:AS61) -> 208715.19 | AU61: ='Займ'!$F$50 -> 0 | AV61: ='Займ'!$F$51 -> 0 | AW61: ='Займ'!$F$52 -> 0 | AX61: ='Займ'!$F$53 -> 0 | AY61: ='Займ'!$F$54 -> 0 | AZ61: ='Займ'!$F$55 -> 0 | BA61: ='Займ'!$F$56 -> 37300.539 | BB61: ='Займ'!$F$57 -> 37300.539 | BC61: ='Займ'!$F$58 -> 37300.539 | BD61: ='Займ'!$F$59 -> 37300.539 | BE61: ='Займ'!$F$60 -> 37300.539 | BF61: ='Займ'!$F$61 -> 37300.539 | BG61: =SUM(AU61:BF61) -> 223803.23 | BH61: =SUM('Займ'!$F$62:$F$73) -> 405938.29 | BI61: =SUM('Займ'!$F$74:$F$85) -> 457064.09 | BJ61: =SUM('Займ'!$F$86:$F$97) -> 490105.29 | BK61: =SUM('Займ'!$F$98:$F$109) -> 422685.61
A62: Финансовая помощь, предоставленная аффилиированным компаниям | G62: 0 | T62: 0 | AG62: 0 | AT62: 0 | BG62: 0 | BH62: 0 | BI62: 0 | BJ62: 0 | BK62: 0 | BL62: 0 | BM62: 0 | BN62: 0 | BO62: 0 | BP62: 0 | BQ62: 0 | BR62: 0 | BS62: 0 | BT62: 0 | BU62: 0
A63: Приобретение собственных акций | G63: 0 | T63: 0 | AG63: 0 | AT63: 0 | BG63: 0 | BH63: 0 | BI63: 0 | BJ63: 0 | BK63: 0 | BL63: 0 | BM63: 0 | BN63: 0 | BO63: 0 | BP63: 0 | BQ63: 0 | BR63: 0 | BS63: 0 | BT63: 0 | BU63: 0
A64: Погашение вознаграждения | G64: 0 | T64: 0 | AG64: 0 | AT64: 0 | BG64: 0 | BH64: 0 | BI64: 0 | BJ64: 0 | BK64: 0 | BL64: 0 | BM64: 0 | BN64: 0 | BO64: 0 | BP64: 0 | BQ64: 0 | BR64: 0 | BS64: 0 | BT64: 0 | BU64: 0
A65: Прочие выплаты | AG65: 0 | AT65: 0 | BG65: 0 | BH65: 0 | BI65: 0 | BJ65: 0 | BK65: 0 | BL65: 0 | BM65: 0 | BN65: 0 | BO65: 0 | BP65: 0 | BQ65: 0 | BR65: 0 | BS65: 0 | BT65: 0 | BU65: 0
A66: ИТОГО ОТТОК ДЕНЕЖНЫХ СРЕДСТВ | B66: =SUM(B61:B65) -> 0 | C66: =SUM(C61:C65) -> 0 | D66: =SUM(D61:D65) -> 0 | E66: =SUM(E61:E65) -> 0 | F66: =SUM(F61:F65) -> 0 | G66: =SUM(G61:G65) -> 0 | H66: =SUM(H61:H65) -> 0 | I66: =SUM(I61:I65) -> 0 | ... BU66: =SUM(BU61:BU65) -> 0
A68: ИТОГО ЧИСТЫЙ ДЕНЕЖНЫЙ ПОТОК (+/-) ОТ ФИНАНСОВОЙ ДЕЯТЕЛЬНОСТИ | B68: =B58-B66 -> 0 | C68: =C58-C66 -> 0 | D68: =D58-D66 -> 0 | E68: =E58-E66 -> 0 | F68: =F58-F66 -> 0 | G68: =G58-G66 -> 0 | H68: =H58-H66 -> 277169.27 | I68: =I58-I66 -> 241673.47 | ... BU68: =BU58-BU66 -> 0
A70: ЧИСТОЕ ИЗМЕНЕНИЕ В ДЕНЬГАХ И ДЕНЕЖНЫХ ЭКВИВАЛЕНТАХ | B70: =B29+B48+B68 -> 0 | C70: =C29+C48+C68 -> 0 | D70: =D29+D48+D68 -> 0 | E70: =E29+E48+E68 -> 0 | F70: =F29+F48+F68 -> 0 | G70: =G29+G48+G68 -> 0 | H70: =H29+H48+H68 -> 0 | I70: =I29+I48+I68 -> 0 | ... BU70: =BU29+BU48+BU68 -> 1763111.5
A71: ВЛИЯНИЕ ОБМЕННЫХ КУРСОВ ВАЛЮТ К ТЕНГЕ
